Workbook

Sheet Hierarchy
A1: DepartmentCode | B1: DepartmentName | C1: SectionCode | D1: SectionName | E1: SubSectionCode | F1: SubSectionName | G1: BudgetMargin | H1: TargetMargin | I1: MinimumMargin
A2: 6 | B2: Brands | C2: 100 | D2: Gerry Weber | E2: 1 | F2: Blouses | G2: 40 | H2: 50 | I2: 40
A3: 6 | B3: Brands | C3: 100 | D3: Gerry Weber | E3: 2 | F3: Tops | G3: 40 | H3: 50 | I3: 40
A4: 6 | B4: Brands | C4: 100 | D4: Gerry Weber | E4: 3 | F4: Knitwear | G4: 40 | H4: 50 | I4: 40
A5: 6 | B5: Brands | C5: 100 | D5: Gerry Weber | E5: 4 | F5: Dresses | G5: 40 | H5: 50 | I5: 40
A6: 6 | B6: Brands | C6: 100 | D6: Gerry Weber | E6: 5 | F6: Skirts | G6: 40 | H6: 50 | I6: 40
A7: 6 | B7: Brands | C7: 100 | D7: Gerry Weber | E7: 6 | F7: Trousers | G7: 40 | H7: 50 | I7: 40
A8: 6 | B8: Brands | C8: 100 | D8: Gerry Weber | E8: 7 | F8: Jackets | G8: 40 | H8: 50 | I8: 40
A9: 6 | B9: Brands | C9: 100 | D9: Gerry Weber | E9: 8 | F9: Accessories | G9: 40 | H9: 50 | I9: 40
A10: 6 | B10: Brands | C10: 103 | D10: Olsen | E10: 1 | F10: Blouses | G10: 40 | H10: 50 | I10: 40
A11: 6 | B11: Brands | C11: 103 | D11: Olsen | E11: 2 | F11: Tops | G11: 40 | H11: 50 | I11: 40
A12: 6 | B12: Brands | C12: 103 | D12: Olsen | E12: 3 | F12: Knitwear | G12: 40 | H12: 50 | I12: 40
A13: 6 | B13: Brands | C13: 103 | D13: Olsen | E13: 4 | F13: Dresses | G13: 40 | H13: 50 | I13: 40
... A151: 6 | B151: Brands | C151: 146 | D151: Laura Ashley | E151: 6 | F151: Trousers | G151: 40 | H151: 50 | I151: 40

Sheet Sheet1
A1: DepartmentCode | B1: DepartmentName | C1: SectionCode | D1: SectionName | E1: SubSectionCode | F1: SubSectionName | G1: BudgetMargin | H1: TargetMargin | I1: MinimumMargin | L1: Branch Code | M1: Name
A2: 1 | B2: Accessories | C2: 1 | D2: Hosiery | E2: 100 | F2: Special Hosiery | G2: 40 | H2: 50 | I2: 40 | L2: 1 | M2: Edinburgh
A3: 1 | B3: Accessories | C3: 1 | D3: Hosiery | E3: 101 | F3: Gentle Grip Socks | G3: 40 | H3: 50 | I3: 40 | L3: 2 | M3: North Berwich
A4: 1 | B4: Accessories | C4: 1 | D4: Hosiery | E4: 999 | F4: No Type | G4: 40 | H4: 50 | I4: 40 | L4: 3 | M4: Falkirk
A5: 1 | B5: Accessories | C5: 2 | D5: Handbags | E5: 120 | F5: Value Bags | G5: 40 | H5: 50 | I5: 40 | L5: 4 | M5: Helensburgh
A6: 1 | B6: Accessories | C6: 2 | D6: Handbags | E6: 121 | F6: Fashion Bags | G6: 40 | H6: 50 | I6: 40 | L6: 5 | M6: Kirkcaldy
A7: 1 | B7: Accessories | C7: 2 | D7: Handbags | E7: 122 | F7: Leather Bags | G7: 40 | H7: 50 | I7: 40 | L7: 6 | M7: Peebles
A8: 1 | B8: Accessories | C8: 2 | D8: Handbags | E8: 123 | F8: Evening Bags | G8: 40 | H8: 50 | I8: 40 | L8: 8 | M8: Perth
A9: 1 | B9: Accessories | C9: 2 | D9: Handbags | E9: 124 | F9: Travel Bags | G9: 40 | H9: 50 | I9: 40 | L9: 9 | M9: Largs
A10: 1 | B10: Accessories | C10: 2 | D10: Handbags | E10: 126 | F10: Sp Bags | G10: 40 | H10: 50 | I10: 40 | L10: 11 | M10: Dundee
A11: 1 | B11: Accessories | C11: 2 | D11: Handbags | E11: 999 | F11: No Type | G11: 40 | H11: 50 | I11: 40 | L11: 12 | M11: Castle Douglas
A12: 1 | B12: Accessories | C12: 3 | D12: Millinery | E12: 130 | F12: Occasionwear | G12: 40 | H12: 50 | I12: 40 | L12: 13 | M12: Ballater
A13: 1 | B13: Accessories | C13: 3 | D13: Millinery | E13: 131 | F13: Every Day | G13: 40 | H13: 50 | I13: 40 | L13: 15 | M13: Hamilton
... A15: 1 | B15: Accessories | C15: 4 | D15: Isotoner | E15: 140 | F15: Gloves | G15: 40 | H15: 50 | I15: 40 | L15: 990 | M15: Online
A16: 1 | B16: Accessories | C16: 4 | D16: Isotoner | E16: 141 | F16: Slippers | G16: 40 | H16: 50 | I16: 40
A17: 1 | B17: Accessories | C17: 5 | D17: Gifts | E17: 999 | F17: No Type | G17: 40 | H17: 50 | I17: 40
A18: 1 | B18: Accessories | C18: 8 | D18: Jewellery | E18: 195 | F18: Jewellery | G18: 40 | H18: 50 | I18: 40
A19: 1 | B19: Accessories | C19: 8 | D19: Jewellery | E19: 611 | F19: Gadgets | G19: 40 | H19: 50 | I19: 40
A20: 1 | B20: Accessories | C20: 9 | D20: Accessories | E20: 190 | F20: Umbrellas | G20: 40 | H20: 50 | I20: 40
A21: 1 | B21: Accessories | C21: 9 | D21: Accessories | E21: 191 | F21: Scarves | G21: 40 | H21: 50 | I21: 40
A22: 1 | B22: Accessories | C22: 9 | D22: Accessories | E22: 192 | F22: Small Leathers | G22: 40 | H22: 50 | I22: 40
A23: 1 | B23: Accessories | C23: 9 | D23: Accessories | E23: 193 | F23: Gloves | G23: 40 | H23: 50 | I23: 40
A24: 1 | B24: Accessories | C24: 9 | D24: Accessories | E24: 194 | F24: Miscellaneous | G24: 40 | H24: 50 | I24: 40
A25: 2 | B25: Underwear | C25: 22 | D25: Swimwear | E25: 999 | F25: No Type | G25: 40 | H25: 50 | I25: 40
A26: 2 | B26: Underwear | C26: 23 | D26: Nightwear | E26: 999 | F26: No Type | G26: 40 | H26: 50 | I26: 40
A27: 2 | B27: Underwear | C27: 24 | D27: Bras | E27: 200 | F27: Non Wired | G27: 40 | H27: 50 | I27: 40
... A483: 999 | B483: Concessions | C483: 752 | D483: Sock Shop Kids | E483: 999 | F483: No Type | G483: 40 | H483: 50 | I483: 40
A484: 998 | B484: Dump Code | G484: 40 | H484: 50 | I484: 40

Sheet Main
H1: Branch Code | I1: Values
H2: 1 | I2: 1 | J2: 1 | K2: 1 | L2: 1 | M2: 1 | N2: 2 | O2: 2 | P2: 2 | Q2: 2 | R2: 2 | S2: 2 | T2: 3 | U2: 3 | V2: 3 | W2: 3 | X2: 3 | Y2: 3 | Z2: 4 | AA2: 4 | AB2: 4 | AC2: 4 | AD2: 4 | AE2: 4 | AF2: 5 | AG2: 5 | AH2: 5 | AI2: 5 | AJ2: 5 | AK2: 5 | AL2: 6 | AM2: 6 | AN2: 6 | AO2: 6 | AP2: 6 | AQ2: 6 | AR2: 8 | AS2: 8 | AT2: 8 | AU2: 8 | AV2: 8 | AW2: 8 | AX2: 9 | AY2: 9 | AZ2: 9 | BA2: 9 | BB2: 9 | BC2: 9 | BD2: 11 | BE2: 11 | BF2: 11 | BG2: 11 | BH2: 11 | BI2: 11 | BJ2: 12 | BK2: 12 | BL2: 12 | BM2: 12 | BN2: 12 | BO2: 12 | BP2: 13 | BQ2: 13 | BR2: 13 | BS2: 13 | BT2: 13 | BU2: 13 | BV2: 15 | BW2: 15 | BX2: 15 | BY2: 15 | BZ2: 15 | CA2: 15 | CB2: 16 | CC2: 16 | CD2: 16 | CE2: 16 | CF2: 16 | CG2: 16 | CH2: 90 | CI2: 90 | CJ2: 90 | CK2: 90 | CL2: 90 | CM2: 90 | CN2: 990 | CO2: 990 | CP2: 990 | CQ2: 990 | CR2: 990 | CS2: 990 | CT2: Total Sales | CU2: Total Physical Qty | CV2: Total On Order | CW2: Total Sell-Through | CX2: Total Weeks Cover | CY2: Total Cost of Stock
A3: DepartmentName | B3: SectionName | C3: SupplierName | D3: StyleCode | E3: Description | F3: RangeDetail1 | G3: Unit Selling Price | H3: Sales | I3: Physical Qty | J3: On Order | K3: Sell-Through | L3: Weeks Cover | M3: Cost of Stock | N3: Sales | O3: Physical Qty | P3: On Order | Q3: Sell-Through | R3: Weeks Cover | S3: Cost of Stock | T3: Sales | U3: Physical Qty | V3: On Order | W3: Sell-Through | X3: Weeks Cover | Y3: Cost of Stock | Z3: Sales | AA3: Physical Qty | AB3: On Order | AC3: Sell-Through | AD3: Weeks Cover | AE3: Cost of Stock | AF3: Sales | AG3: Physical Qty | AH3: On Order | AI3: Sell-Through | AJ3: Weeks Cover | AK3: Cost of Stock | AL3: Sales | AM3: Physical Qty | AN3: On Order | AO3: Sell-Through | AP3: Weeks Cover | AQ3: Cost of Stock | AR3: Sales | AS3: Physical Qty | AT3: On Order | AU3: Sell-Through | AV3: Weeks Cover | AW3: Cost of Stock | AX3: Sales | AY3: Physical Qty | AZ3: On Order | BA3: Sell-Through | BB3: Weeks Cover | BC3: Cost of Stock | BD3: Sales | BE3: Physical Qty | BF3: On Order | BG3: Sell-Through | BH3: Weeks Cover | BI3: Cost of Stock | BJ3: Sales | BK3: Physical Qty | BL3: On Order | BM3: Sell-Through | BN3: Weeks Cover | BO3: Cost of Stock | BP3: Sales | BQ3: Physical Qty | BR3: On Order | BS3: Sell-Through | BT3: Weeks Cover | BU3: Cost of Stock | BV3: Sales | BW3: Physical Qty | BX3: On Order | BY3: Sell-Through | BZ3: Weeks Cover | CA3: Cost of Stock | CB3: Sales | CC3: Physical Qty | CD3: On Order | CE3: Sell-Through | CF3: Weeks Cover | CG3: Cost of Stock | CH3: Sales | CI3: Physical Qty | CJ3: On Order | CK3: Sell-Through | CL3: Weeks Cover | CM3: Cost of Stock | CN3: Sales | CO3: Physical Qty | CP3: On Order | CQ3: Sell-Through | CR3: Weeks Cover | CS3: Cost of Stock | DA3: 1st MD | DB3: Ratio | DC3: 2ND MD | DD3: Ratio | DE3: 3RD MD | DF3: Ratio | DG3: 4TH MD | DH3: Ratio
A4: Accessories | B4: Accessories | C4: EARTH SQUARED LTD CEN | D4: 103164 | E4: SS22 GINCAT SPRING GINGHAM CAT PURSE | F4: BLUE | G4: 9.99 | H4: 0 | I4: 2 | J4: 0 | K4: 0 | L4: 2 | M4: 8.32 | T4: 0 | U4: 2 | V4: 0 | W4: 0 | X4: 2 | Y4: 8.32 | Z4: 1 | AA4: -1 | AB4: 3 | AC4: 1 | AD4: 8 | AE4: -4.16 | AF4: 0 | AG4: 4 | AH4: 0 | AI4: 0 | AJ4: 4 | AK4: 16.64 | AR4: 0 | AS4: 1 | AT4: 0 | AU4: 0 | AV4: 1 | AW4: 4.16 | AX4: 0 | AY4: 4 | AZ4: 3 | BA4: 0 | BB4: 7 | BC4: 16.64 | BD4: 0 | BE4: 2 | BF4: 2 | BG4: 0 | BH4: 4 | BI4: 8.32 | BP4: 0 | BQ4: 3 | BR4: 0 | BS4: 0 | BT4: 3 | BU4: 12.48 | BV4: 2 | BW4: 1 | BX4: 0 | BY4: 0.66666667 | BZ4: 4 | CA4: 4.16 | CB4: 0 | CC4: 2 | CD4: 0 | CE4: 0 | CF4: 2 | CG4: 8.32 | CT4: 3 | CU4: 20 | CV4: 8 | CW4: 0.16666667 | CX4: 37 | CY4: 83.2 | DB4: =IF(DA4="","",1-(DA4/Main!$G4)) | DC4: 5 | DD4: =IF(DC4="","",1-(DC4/Main!$G4)) -> 0.4994995 | DE4: 3 | DF4: =IF(DE4="","",1-(DE4/Main!$G4)) -> 0.6996997 | DG4: =IF(DF4="","",1-(DF4/Main!$G4)) -> 0.92995999 | DH4: =IF(DG4="","",1-(DG4/Main!$G4)) -> 0.90691091
A5: Accessories | B5: Accessories | C5: EARTH SQUARED LTD CEN | D5: 103164 | E5: SS22 GINCAT SPRING GINGHAM CAT PURSE | F5: Grey | G5: 9.99 | H5: 0 | I5: 2 | J5: 0 | K5: 0 | L5: 2 | M5: 8.32 | T5: 0 | U5: 2 | V5: 0 | W5: 0 | X5: 2 | Y5: 8.32 | Z5: 0 | AA5: -2 | AB5: 3 | AC5: 0 | AD5: 1 | AE5: -8.32 | AF5: 0 | AG5: 4 | AH5: 0 | AI5: 0 | AJ5: 4 | AK5: 16.64 | AR5: 0 | AS5: 1 | AT5: 0 | AU5: 0 | AV5: 1 | AW5: 4.16 | AX5: 0 | AY5: 4 | AZ5: 3 | BA5: 0 | BB5: 7 | BC5: 16.64 | BD5: 0 | BE5: 2 | BF5: 2 | BG5: 0 | BH5: 4 | BI5: 8.32 | BP5: 0 | BQ5: 3 | BR5: 0 | BS5: 0 | BT5: 3 | BU5: 12.48 | BV5: 2 | BW5: 0 | BX5: 0 | BY5: 1 | BZ5: 0 | CA5: 0 | CB5: 1 | CC5: 1 | CD5: 0 | CE5: 0.5 | CF5: 4 | CG5: 4.16 | CT5: 3 | CU5: 17 | CV5: 8 | CW5: 0.15 | CX5: 28 | CY5: 70.72 | DB5: =IF(DA5="","",1-(DA5/Main!$G5)) | DD5: =IF(DC5="","",1-(DC5/Main!$G5)) | DF5: =IF(DE5="","",1-(DE5/Main!$G5)) | DH5: =IF(DG5="","",1-(DG5/Main!$G5))
A6: Accessories | B6: Accessories | C6: EARTH SQUARED LTD CEN | D6: 103164 | E6: SS22 GINCAT SPRING GINGHAM CAT PURSE | F6: RED | G6: 9.99 | H6: 1 | I6: 1 | J6: 0 | K6: 0.5 | L6: 4 | M6: 4.16 | T6: 0 | U6: 1 | V6: 0 | W6: 0 | X6: 1 | Y6: 4.16 | Z6: 3 | AA6: -3 | AB6: 3 | AC6: 1 | AD6: 0 | AE6: -12.48 | AF6: 0 | AG6: 4 | AH6: 0 | AI6: 0 | AJ6: 4 | AK6: 16.64 | AR6: 2 | AS6: 0 | AT6: 0 | AU6: 1 | AV6: 0 | AW6: 0 | AX6: 1 | AY6: 3 | AZ6: 3 | BA6: 0.25 | BB6: 24 | BC6: 12.48 | BD6: 0 | BE6: 2 | BF6: 2 | BG6: 0 | BH6: 4 | BI6: 8.32 | BJ6: 2 | BK6: 0 | BL6: 0 | BM6: 1 | BN6: 0 | BO6: 0 | BP6: 0 | BQ6: 3 | BR6: 0 | BS6: 0 | BT6: 3 | BU6: 12.48 | BV6: 1 | BW6: 1 | BX6: 0 | BY6: 0.5 | BZ6: 4 | CA6: 4.16 | CB6: 0 | CC6: 2 | CD6: 0 | CE6: 0 | CF6: 2 | CG6: 8.32 | CT6: 10 | CU6: 14 | CV6: 8 | CW6: 0.38636364 | CX6: 46 | CY6: 58.24 | DB6: =IF(DA6="","",1-(DA6/Main!$G6)) | DD6: =IF(DC6="","",1-(DC6/Main!$G6)) | DF6: =IF(DE6="","",1-(DE6/Main!$G6)) | DH6: =IF(DG6="","",1-(DG6/Main!$G6))
A7: Accessories | B7: Accessories | C7: EARTH SQUARED LTD CEN | D7: 103165 | E7: SS22 SOMPURBL SPRING PATCHWORK PLEAT PURSE | F7: Navy | G7: 9.99 | H7: 0 | I7: 1 | J7: 1 | K7: 0 | L7: 2 | M7: 4.16 | T7: 0 | U7: 1 | V7: 0 | W7: 0 | X7: 1 | Y7: 4.16 | Z7: 0 | AA7: 0 | AB7: 3 | AC7: 0 | AD7: 3 | AE7: 0 | AR7: 0 | AS7: 2 | AT7: 0 | AU7: 0 | AV7: 2 | AW7: 8.32 | AX7: 0 | AY7: 0 | AZ7: 4 | BA7: 0 | BB7: 4 | BC7: 0 | BD7: 0 | BE7: 2 | BF7: 2 | BG7: 0 | BH7: 4 | BI7: 8.32 | BP7: 0 | BQ7: 4 | BR7: 0 | BS7: 0 | BT7: 4 | BU7: 16.64 | CB7: 0 | CC7: 2 | CD7: 0 | CE7: 0 | CF7: 2 | CG7: 8.32 | CT7: 0 | CU7: 12 | CV7: 10 | CW7: 0 | CX7: 22 | CY7: 49.92 | DB7: =IF(DA7="","",1-(DA7/Main!$G7)) | DD7: =IF(DC7="","",1-(DC7/Main!$G7)) | DF7: =IF(DE7="","",1-(DE7/Main!$G7)) | DH7: =IF(DG7="","",1-(DG7/Main!$G7))
A8: Accessories | B8: Accessories | C8: EARTH SQUARED LTD CEN | D8: 103166 | E8: SS22 SOMPURGY BLUE SPRING BLOSSOM CANVAS JULIET PURSE | F8: Grey | G8: 9.99 | H8: 0 | I8: 1 | J8: 1 | K8: 0 | L8: 2 | M8: 4.16 | Z8: 0 | AA8: 0 | AB8: 5 | AC8: 0 | AD8: 5 | AE8: 0 | AF8: 0 | AG8: 4 | AH8: 0 | AI8: 0 | AJ8: 4 | AK8: 16.64 | AR8: 0 | AS8: 2 | AT8: 0 | AU8: 0 | AV8: 2 | AW8: 8.32 | AX8: 0 | AY8: 4 | AZ8: 3 | BA8: 0 | BB8: 7 | BC8: 16.64 | BD8: 0 | BE8: 2 | BF8: 2 | BG8: 0 | BH8: 4 | BI8: 8.32 | BJ8: 0 | BK8: 2 | BL8: 0 | BM8: 0 | BN8: 2 | BO8: 8.32 | BP8: 0 | BQ8: 4 | BR8: 0 | BS8: 0 | BT8: 4 | BU8: 16.64 | BV8: 0 | BW8: 1 | BX8: 0 | BY8: 0 | BZ8: 1 | CA8: 4.16 | CB8: 0 | CC8: 2 | CD8: 0 | CE8: 0 | CF8: 2 | CG8: 8.32 | CT8: 0 | CU8: 22 | CV8: 11 | CW8: 0 | CX8: 33 | CY8: 91.52 | DB8: =IF(DA8="","",1-(DA8/Main!$G8)) | DD8: =IF(DC8="","",1-(DC8/Main!$G8)) | DF8: =IF(DE8="","",1-(DE8/Main!$G8)) | DH8: =IF(DG8="","",1-(DG8/Main!$G8))
A9: Accessories | B9: Accessories | C9: EARTH SQUARED LTD CEN | D9: 103167 | E9: BEEJP ANIMAL APPLIQUE JULIET PURSE | F9: Multi | G9: 9.99 | H9: 3 | I9: 0 | J9: 2 | K9: 1 | L9: 4 | M9: 0 | T9: 0 | U9: 4 | V9: 1 | W9: 0 | X9: 5 | Y9: 16.64 | Z9: 0 | AA9: 3 | AB9: 5 | AC9: 0 | AD9: 8 | AE9: 12.48 | AF9: 4 | AG9: 7 | AH9: 0 | AI9: 0.36363636 | AJ9: 28 | AK9: 29.12 | AR9: 0 | AS9: 0 | AT9: 3 | AU9: 0 | AV9: 3 | AW9: 0 | AX9: 1 | AY9: 3 | AZ9: 3 | BA9: 0.25 | BB9: 24 | BC9: 12.48 | BD9: 0 | BE9: 7 | BF9: 4 | BG9: 0 | BH9: 11 | BI9: 29.12 | BJ9: 0 | BK9: 4 | BL9: 1 | BM9: 0 | BN9: 5 | BO9: 16.64 | BP9: 3 | BQ9: 5 | BR9: 1 | BS9: 0.375 | BT9: 24 | BU9: 20.8 | BV9: 0 | BW9: 0 | BX9: 3 | BY9: 0 | BZ9: 3 | CA9: 0 | CB9: 0 | CC9: 0 | CD9: 3 | CE9: 0 | CF9: 3 | CG9: 0 | CT9: 11 | CU9: 33 | CV9: 26 | CW9: 0.18078512 | CX9: 118 | CY9: 137.28 | DB9: =IF(DA9="","",1-(DA9/Main!$G9)) | DD9: =IF(DC9="","",1-(DC9/Main!$G9)) | DF9: =IF(DE9="","",1-(DE9/Main!$G9)) | DH9: =IF(DG9="","",1-(DG9/Main!$G9))
A10: Accessories | B10: Accessories | C10: EARTH SQUARED LTD CEN | D10: 103171 | E10: SS22 DOGJP DOG ANIMAL APPLIQUE JULIET PURSE | F10: Multi | G10: 9.99 | H10: 0 | I10: 0 | J10: 3 | K10: 0 | L10: 3 | M10: 0 | T10: 0 | U10: 0 | V10: 4 | W10: 0 | X10: 4 | Y10: 0 | Z10: 0 | AA10: -1 | AB10: 5 | AC10: 0 | AD10: 4 | AE10: -4.16 | AF10: 0 | AG10: 4 | AH10: 0 | AI10: 0 | AJ10: 4 | AK10: 16.64 | AR10: 0 | AS10: 0 | AT10: 4 | AU10: 0 | AV10: 4 | AW10: 0 | AX10: 1 | AY10: 3 | AZ10: 3 | BA10: 0.25 | BB10: 24 | BC10: 12.48 | BD10: 0 | BE10: 3 | BF10: 3 | BG10: 0 | BH10: 6 | BI10: 12.48 | BJ10: 0 | BK10: 1 | BL10: 4 | BM10: 0 | BN10: 5 | BO10: 4.16 | BP10: 0 | BQ10: 3 | BR10: 4 | BS10: 0 | BT10: 7 | BU10: 12.48 | CB10: 0 | CC10: 0 | CD10: 4 | CE10: 0 | CF10: 4 | CG10: 0 | CT10: 1 | CU10: 13 | CV10: 34 | CW10: 0.025 | CX10: 65 | CY10: 54.08 | DB10: =IF(DA10="","",1-(DA10/Main!$G10)) | DD10: =IF(DC10="","",1-(DC10/Main!$G10)) | DF10: =IF(DE10="","",1-(DE10/Main!$G10)) | DH10: =IF(DG10="","",1-(DG10/Main!$G10))
A11: Accessories | B11: Accessories | C11: EARTH SQUARED LTD CEN | D11: 103172 | E11: SS22 DOGEYE DOG ANIMAL APPLIQUE EYE GLASS CASE | F11: Multi | G11: 9.99 | H11: 0 | I11: 1 | J11: 2 | K11: 0 | L11: 3 | M11: 4.16 | T11: 3 | U11: 2 | V11: 2 | W11: 0.6 | X11: 16 | Y11: 8.32 | Z11: 0 | AA11: -1 | AB11: 5 | AC11: 0 | AD11: 4 | AE11: -4.16 | AF11: 0 | AG11: 4 | AH11: 0 | AI11: 0 | AJ11: 4 | AK11: 16.64 | AR11: 0 | AS11: 1 | AT11: 2 | AU11: 0 | AV11: 3 | AW11: 4.16 | AX11: 0 | AY11: 4 | AZ11: 3 | BA11: 0 | BB11: 7 | BC11: 16.64 | BD11: 0 | BE11: 3 | BF11: 3 | BG11: 0 | BH11: 6 | BI11: 12.48 | BJ11: 0 | BK11: 0 | BL11: 4 | BM11: 0 | BN11: 4 | BO11: 0 | BP11: 0 | BQ11: 4 | BR11: 2 | BS11: 0 | BT11: 6 | BU11: 16.64 | BV11: 1 | BW11: 1 | BX11: 1 | BY11: 0.5 | BZ11: 8 | CA11: 4.16 | CB11: 0 | CC11: 0 | CD11: 7 | CE11: 0 | CF11: 7 | CG11: 0 | CT11: 4 | CU11: 19 | CV11: 31 | CW11: 0.1 | CX11: 68 | CY11: 79.04 | DB11: =IF(DA11="","",1-(DA11/Main!$G11)) | DD11: =IF(DC11="","",1-(DC11/Main!$G11)) | DF11: =IF(DE11="","",1-(DE11/Main!$G11)) | DH11: =IF(DG11="","",1-(DG11/Main!$G11))
A12: Accessories | B12: Accessories | C12: EARTH SQUARED LTD CEN | D12: 103255 | E12: SS22 HCOWJP COW ANIMAL APPLIQUE JULIET PURSE | F12: Multi | G12: 9.99 | H12: 0 | I12: 0 | J12: 2 | K12: 0 | L12: 2 | M12: 0 | T12: 0 | U12: 0 | V12: 2 | W12: 0 | X12: 2 | Y12: 0 | Z12: 0 | AA12: -1 | AB12: 2 | AC12: 0 | AD12: 1 | AE12: -4.16 | AF12: 0 | AG12: 0 | AH12: 2 | AI12: 0 | AJ12: 2 | AK12: 0 | AR12: 0 | AS12: 1 | AT12: 2 | AU12: 0 | AV12: 3 | AW12: 4.16 | BD12: 0 | BE12: 0 | BF12: 2 | BG12: 0 | BH12: 2 | BI12: 0 | BJ12: 0 | BK12: 0 | BL12: 2 | BM12: 0 | BN12: 2 | BO12: 0 | BP12: 0 | BQ12: 1 | BR12: 2 | BS12: 0 | BT12: 3 | BU12: 4.16 | BV12: 0 | BW12: 0 | BX12: 2 | BY12: 0 | BZ12: 2 | CA12: 0 | CB12: 0 | CC12: 0 | CD12: 2 | CE12: 0 | CF12: 2 | CG12: 0 | CT12: 0 | CU12: 1 | CV12: 20 | CW12: 0 | CX12: 21 | CY12: 4.16 | DB12: =IF(DA12="","",1-(DA12/Main!$G12)) | DD12: =IF(DC12="","",1-(DC12/Main!$G12)) | DF12: =IF(DE12="","",1-(DE12/Main!$G12)) | DH12: =IF(DG12="","",1-(DG12/Main!$G12))
A13: Accessories | B13: Accessories | C13: EARTH SQUARED LTD CEN | D13: 103256 | E13: SS22 BEEEYE BEE ANIMAL APPLIQUE EYE GLASS CASE | F13: Multi | G13: 9.99 | H13: 0 | I13: 1 | J13: 3 | K13: 0 | L13: 4 | M13: 4.16 | T13: 0 | U13: 5 | V13: 0 | W13: 0 | X13: 5 | Y13: 20.8 | Z13: 0 | AA13: 8 | AB13: 4 | AC13: 0 | AD13: 12 | AE13: 33.28 | AF13: 4 | AG13: 3 | AH13: 0 | AI13: 0.57142857 | AJ13: 12 | AK13: 12.48 | AR13: 0 | AS13: 1 | AT13: 2 | AU13: 0 | AV13: 3 | AW13: 4.16 | AX13: 0 | AY13: 0 | AZ13: 3 | BA13: 0 | BB13: 3 | BC13: 0 | BD13: 0 | BE13: 5 | BF13: 3 | BG13: 0 | BH13: 8 | BI13: 20.8 | BJ13: 0 | BK13: 4 | BL13: 2 | BM13: 0 | BN13: 6 | BO13: 16.64 | BP13: 0 | BQ13: 2 | BR13: 4 | BS13: 0 | BT13: 6 | BU13: 8.32 | BV13: 0 | BW13: 1 | BX13: 2 | BY13: 0 | BZ13: 3 | CA13: 4.16 | CT13: 4 | CU13: 30 | CV13: 23 | CW13: 0.057142857 | CX13: 62 | CY13: 124.8 | DB13: =IF(DA13="","",1-(DA13/Main!$G13)) | DD13: =IF(DC13="","",1-(DC13/Main!$G13)) | DF13: =IF(DE13="","",1-(DE13/Main!$G13)) | DH13: =IF(DG13="","",1-(DG13/Main!$G13))
A14: Accessories | B14: Accessories | C14: EARTH SQUARED LTD CEN | D14: 103257 | E14: SS22 HCOWEYE | F14: Multi | G14: 9.99 | H14: 0 | I14: 0 | J14: 2 | K14: 0 | L14: 2 | M14: 0 | T14: 0 | U14: 0 | V14: 2 | W14: 0 | X14: 2 | Y14: 0 | Z14: 0 | AA14: 0 | AB14: 2 | AC14: 0 | AD14: 2 | AE14: 0 | AF14: 0 | AG14: 0 | AH14: 2 | AI14: 0 | AJ14: 2 | AK14: 0 | AR14: 0 | AS14: 0 | AT14: 2 | AU14: 0 | AV14: 2 | AW14: 0 | BD14: 0 | BE14: 0 | BF14: 2 | BG14: 0 | BH14: 2 | BI14: 0 | BP14: 4 | BQ14: 0 | BR14: 2 | BS14: 1 | BT14: 3 | BU14: 0 | BV14: 0 | BW14: 0 | BX14: 2 | BY14: 0 | BZ14: 2 | CA14: 0 | CT14: 4 | CU14: 0 | CV14: 16 | CW14: 0.125 | CX14: 17 | CY14: 0 | DB14: =IF(DA14="","",1-(DA14/Main!$G14)) | DD14: =IF(DC14="","",1-(DC14/Main!$G14)) | DF14: =IF(DE14="","",1-(DE14/Main!$G14)) | DH14: =IF(DG14="","",1-(DG14/Main!$G14))
A15: Accessories | B15: Accessories | C15: (blank) | D15: 103158 | E15: SS22 ASSTD FNJ | F15: Asstd | G15: 9.99 | H15: 94 | I15: 31 | J15: 82 | K15: 0.752 | L15: 22 | M15: 80.6 | N15: 31 | O15: 53 | P15: 0 | Q15: 0.36904762 | R15: 24 | S15: 137.8 | T15: 46 | U15: 83 | V15: 0 | W15: 0.35658915 | X15: 24 | Y15: 215.8 | Z15: 85 | AA15: 36 | AB15: 83 | AC15: 0.70247934 | AD15: 26 | AE15: 93.6 | AF15: 53 | AG15: -70 | AH15: 0 | AI15: 1 | AJ15: 0 | AK15: -182 | AL15: 52 | AM15: 33 | AN15: 0 | AO15: 0.61176471 | AP15: 11 | AQ15: 85.8 | AR15: 72 | AS15: 10 | AT15: 80 | AU15: 0.87804878 | AV15: 72 | AW15: 26 | AX15: 76 | AY15: 43 | AZ15: 80 | BA15: 0.63865546 | BB15: 38 | BC15: 111.8 | BD15: 80 | BE15: 44 | BF15: 80 | BG15: 0.64516129 | BH15: 33 | BI15: 114.4 | BJ15: 32 | BK15: 91 | BL15: 0 | BM15: 0.2601626 | BN15: 73 | BO15: 236.6 | BP15: 75 | BQ15: 49 | BR15: 0 | BS15: 0.60483871 | BT15: 10 | BU15: 127.4 | BV15: 33 | BW15: 47 | BX15: 80 | BY15: 0.4125 | BZ15: 127 | CA15: 122.2 | CB15: 65 | CC15: 22 | CD15: 0 | CE15: 0.74712644 | CF15: 15 | CG15: 57.2 | CT15: 794 | CU15: 472 | CV15: 485 | CW15: 0.61372108 | CX15: 475 | CY15: 1227.2 | DB15: =IF(DA15="","",1-(DA15/Main!$G15)) | DD15: =IF(DC15="","",1-(DC15/Main!$G15)) | DF15: =IF(DE15="","",1-(DE15/Main!$G15)) | DH15: =IF(DG15="","",1-(DG15/Main!$G15))
A16: Accessories | B16: Gifts | C16: FAYE UK LTD CENPAC | D16: 102603 | E16: SS22 THERMAL COFFEE MUG | F16: Asstd | G16: 19.99 | H16: 0 | I16: 5 | J16: 0 | K16: 0 | L16: 5 | M16: 41.65 | N16: 0 | O16: 6 | P16: 0 | Q16: 0 | R16: 6 | S16: 49.98 | T16: 0 | U16: 6 | V16: 0 | W16: 0 | X16: 6 | Y16: 49.98 | Z16: 0 | AA16: 4 | AB16: 0 | AC16: 0 | AD16: 4 | AE16: 33.32 | AF16: 0 | AG16: 5 | AH16: 0 | AI16: 0 | AJ16: 5 | AK16: 41.65 | AL16: 0 | AM16: 6 | AN16: 0 | AO16: 0 | AP16: 6 | AQ16: 49.98 | AR16: 0 | AS16: 0 | AT16: 6 | AU16: 0 | AV16: 6 | AW16: 0 | AX16: 0 | AY16: 5 | AZ16: 0 | BA16: 0 | BB16: 5 | BC16: 41.65 | BD16: 0 | BE16: 5 | BF16: 0 | BG16: 0 | BH16: 5 | BI16: 41.65 | BJ16: 1 | BK16: 5 | BL16: 0 | BM16: 0.16666667 | BN16: 20 | BO16: 41.65 | BP16: 0 | BQ16: 3 | BR16: 0 | BS16: 0 | BT16: 3 | BU16: 24.99 | CT16: 1 | CU16: 50 | CV16: 6 | CW16: 0.015151515 | CX16: 71 | CY16: 416.5 | DB16: =IF(DA16="","",1-(DA16/Main!$G16)) | DD16: =IF(DC16="","",1-(DC16/Main!$G16)) | DF16: =IF(DE16="","",1-(DE16/Main!$G16)) | DH16: =IF(DG16="","",1-(DG16/Main!$G16))
A17: Accessories | B17: Gifts | C17: FAYE UK LTD CENPAC | D17: 102830 | E17: SS22 ASSORTED CROSSBODY 4BAG | F17: Asstd | G17: 17.99 | H17: 0 | I17: 6 | J17: 0 | K17: 0 | L17: 6 | M17: 45 | N17: 1 | O17: 7 | P17: 0 | Q17: 0.125 | R17: 28 | S17: 52.5 | T17: 0 | U17: 7 | V17: 0 | W17: 0 | X17: 7 | Y17: 52.5 | Z17: 0 | AA17: 3 | AB17: 0 | AC17: 0 | AD17: 3 | AE17: 22.5 | AL17: 0 | AM17: 8 | AN17: 0 | AO17: 0 | AP17: 8 | AQ17: 60 | BD17: 0 | BE17: 6 | BF17: 0 | BG17: 0 | BH17: 6 | BI17: 45 | BJ17: 2 | BK17: 6 | BL17: 0 | BM17: 0.25 | BN17: 24 | BO17: 45 | BP17: 0 | BQ17: 7 | BR17: 0 | BS17: 0 | BT17: 7 | BU17: 52.5 | CT17: 3 | CU17: 50 | CV17: 0 | CW17: 0.046875 | CX17: 89 | CY17: 375 | DB17: =IF(DA17="","",1-(DA17/Main!$G17)) | DD17: =IF(DC17="","",1-(DC17/Main!$G17)) | DF17: =IF(DE17="","",1-(DE17/Main!$G17)) | DH17: =IF(DG17="","",1-(DG17/Main!$G17))
A18: Accessories | B18: Gifts | C18: FAYE UK LTD CENPAC | D18: 102831 | E18: SS22 B43PK FOLD BACKPACK | F18: Asstd | G18: 19.99 | H18: 0 | I18: 13 | J18: 0 | K18: 0 | L18: 52 | M18: 108.29 | N18: 0 | O18: 15 | P18: 0 | Q18: 0 | R18: 15 | S18: 124.95 | T18: 0 | U18: 13 | V18: 0 | W18: 0 | X18: 13 | Y18: 108.29 | Z18: 8 | AA18: 8 | AB18: 0 | AC18: 0.5 | AD18: 8 | AE18: 66.64 | AF18: 4 | AG18: 11 | AH18: 0 | AI18: 0.26666667 | AJ18: 22 | AK18: 91.63 | AL18: 2 | AM18: 14 | AN18: 0 | AO18: 0.125 | AP18: 28 | AQ18: 116.62 | AR18: 0 | AS18: -2 | AT18: 20 | AU18: 0 | AV18: 18 | AW18: -16.66 | AX18: 7 | AY18: 9 | AZ18: 0 | BA18: 0.4375 | BB18: 9 | BC18: 74.97 | BD18: 8 | BE18: 8 | BF18: 0 | BG18: 0.5 | BH18: 8 | BI18: 66.64 | BJ18: 0 | BK18: 16 | BL18: 0 | BM18: 0 | BN18: 16 | BO18: 133.28 | BP18: 4 | BQ18: 11 | BR18: 0 | BS18: 0.26666667 | BT18: 22 | BU18: 91.63 | BV18: 0 | BW18: -1 | BX18: 0 | BY18: 0 | BZ18: 0 | CA18: -8.33 | CT18: 33 | CU18: 115 | CV18: 20 | CW18: 0.17465278 | CX18: 211 | CY18: 957.95 | DB18: =IF(DA18="","",1-(DA18/Main!$G18)) | DD18: =IF(DC18="","",1-(DC18/Main!$G18)) | DF18: =IF(DE18="","",1-(DE18/Main!$G18)) | DH18: =IF(DG18="","",1-(DG18/Main!$G18))
A19: Accessories | B19: Gifts | C19: FAYE UK LTD CENPAC | D19: 102832 | E19: SS22 B50MB FOLDAWAY BACKPACK PLAIN | F19: Asstd | G19: 19.99 | H19: 1 | I19: 3 | J19: 0 | K19: 0.25 | L19: 12 | M19: 24.99 | N19: 0 | O19: 3 | P19: 0 | Q19: 0 | R19: 3 | S19: 24.99 | T19: 1 | U19: 2 | V19: 0 | W19: 0.33333333 | X19: 8 | Y19: 16.66 | Z19: 3 | AA19: 1 | AB19: 0 | AC19: 0.75 | AD19: 4 | AE19: 8.33 | AF19: 0 | AG19: 3 | AH19: 0 | AI19: 0 | AJ19: 3 | AK19: 24.99 | AL19: 2 | AM19: 2 | AN19: 0 | AO19: 0.5 | AP19: 8 | AQ19: 16.66 | AX19: 0 | AY19: 3 | AZ19: 0 | BA19: 0 | BB19: 3 | BC19: 24.99 | BD19: 1 | BE19: 3 | BF19: 0 | BG19: 0.25 | BH19: 12 | BI19: 24.99 | BJ19: 0 | BK19: 3 | BL19: 0 | BM19: 0 | BN19: 3 | BO19: 24.99 | BP19: 4 | BQ19: 0 | BR19: 0 | BS19: 1 | BT19: 0 | BU19: 0 | BV19: 0 | BW19: 4 | BX19: 0 | BY19: 0 | BZ19: 4 | CA19: 33.32 | CB19: 4 | CC19: 2 | CD19: 0 | CE19: 0.66666667 | CF19: 8 | CG19: 16.66 | CT19: 16 | CU19: 29 | CV19: 0 | CW19: 0.3125 | CX19: 68 | CY19: 241.57 | DB19: =IF(DA19="","",1-(DA19/Main!$G19)) | DD19: =IF(DC19="","",1-(DC19/Main!$G19)) | DF19: =IF(DE19="","",1-(DE19/Main!$G19)) | DH19: =IF(DG19="","",1-(DG19/Main!$G19))
A20: Accessories | B20: Gifts | C20: FAYE UK LTD CENPAC | D20: 102833 | E20: SS22 ECO SHOPPER | F20: Asstd | G20: 5.99 | H20: 5 | I20: 41 | J20: 0 | K20: 0.10869565 | L20: 23 | M20: 102.5 | N20: 3 | O20: 45 | P20: 0 | Q20: 0.0625 | R20: 60 | S20: 112.5 | T20: 1 | U20: 47 | V20: 0 | W20: 0.020833333 | X20: 188 | Y20: 117.5 | Z20: 2 | AA20: 44 | AB20: 0 | AC20: 0.043478261 | AD20: 44 | AE20: 110 | AF20: 0 | AG20: 48 | AH20: 0 | AI20: 0 | AJ20: 48 | AK20: 120 | AL20: 6 | AM20: 42 | AN20: 0 | AO20: 0.125 | AP20: 28 | AQ20: 105 | AR20: 5 | AS20: -5 | AT20: 48 | AU20: 1 | AV20: 34 | AW20: -12.5 | AX20: 5 | AY20: 43 | AZ20: 0 | BA20: 0.10416667 | BB20: 34 | BC20: 107.5 | BD20: 4 | BE20: 44 | BF20: 0 | BG20: 0.083333333 | BH20: 44 | BI20: 110 | BJ20: 4 | BK20: 44 | BL20: 0 | BM20: 0.083333333 | BN20: 44 | BO20: 110 | BP20: 4 | BQ20: 43 | BR20: 0 | BS20: 0.085106383 | BT20: 34 | BU20: 107.5 | BV20: 1 | BW20: 46 | BX20: 0 | BY20: 0.021276596 | BZ20: 92 | CA20: 115 | CB20: 0 | CC20: 25 | CD20: 0 | CE20: 0 | CF20: 25 | CG20: 62.5 | CT20: 40 | CU20: 507 | CV20: 48 | CW20: 0.13367104 | CX20: 698 | CY20: 1267.5 | DB20: =IF(DA20="","",1-(DA20/Main!$G20)) | DD20: =IF(DC20="","",1-(DC20/Main!$G20)) | DF20: =IF(DE20="","",1-(DE20/Main!$G20)) | DH20: =IF(DG20="","",1-(DG20/Main!$G20))
A21: Accessories | B21: Gifts | C21: FAYE UK LTD CENPAC | D21: 102835 | E21: SS22 FOLDABLE HOLDALL | F21: Asstd | G21: 19.99 | Z21: 0 | AA21: 13 | AB21: 0 | AC21: 0 | AD21: 13 | AE21: 108.29 | AF21: 0 | AG21: 12 | AH21: 0 | AI21: 0 | AJ21: 12 | AK21: 99.96 | AL21: 0 | AM21: 11 | AN21: 0 | AO21: 0 | AP21: 11 | AQ21: 91.63 | AR21: 0 | AS21: 0 | AT21: 14 | AU21: 0 | AV21: 14 | AW21: 0 | AX21: 0 | AY21: 12 | AZ21: 0 | BA21: 0 | BB21: 12 | BC21: 99.96 | BJ21: 0 | BK21: 14 | BL21: 0 | BM21: 0 | BN21: 14 | BO21: 116.62 | BP21: 0 | BQ21: 0 | BR21: 14 | BS21: 0 | BT21: 14 | BU21: 0 | CT21: 0 | CU21: 62 | CV21: 28 | CW21: 0 | CX21: 90 | CY21: 516.46 | DB21: =IF(DA21="","",1-(DA21/Main!$G21)) | DD21: =IF(DC21="","",1-(DC21/Main!$G21)) | DF21: =IF(DE21="","",1-(DE21/Main!$G21)) | DH21: =IF(DG21="","",1-(DG21/Main!$G21))
A22: Accessories | B22: Gifts | C22: FAYE UK LTD CENPAC | D22: 103777 | E22: SS22 LARGE COOL BAG E17TL | F22: Asstd | G22: 13.99 | T22: 0 | U22: 12 | V22: 0 | W22: 0 | X22: 12 | Y22: 69.96 | AR22: 1 | AS22: -1 | AT22: 12 | AU22: 1 | AV22: 44 | AW22: -5.83 | BP22: 1 | BQ22: 11 | BR22: 0 | BS22: 0.083333333 | BT22: 44 | BU22: 64.13 | CT22: 2 | CU22: 22 | CV22: 12 | CW22: 0.36111111 | CX22: 100 | CY22: 128.26 | DB22: =IF(DA22="","",1-(DA22/Main!$G22)) | DD22: =IF(DC22="","",1-(DC22/Main!$G22)) | DF22: =IF(DE22="","",1-(DE22/Main!$G22)) | DH22: =IF(DG22="","",1-(DG22/Main!$G22))
A23: Accessories | B23: Gifts | C23: FAYE UK LTD CENPAC | D23: 105660 | E23: SS22 BACK PACK COOLER | F23: Asstd | G23: 26.99 | BP23: 0 | BQ23: 0 | BR23: 9 | BS23: 0 | BT23: 9 | BU23: 0 | CT23: 0 | CU23: 0 | CV23: 9 | CW23: 0 | CX23: 9 | CY23: 0 | DB23: =IF(DA23="","",1-(DA23/Main!$G23)) | DD23: =IF(DC23="","",1-(DC23/Main!$G23)) | DF23: =IF(DE23="","",1-(DE23/Main!$G23)) | DH23: =IF(DG23="","",1-(DG23/Main!$G23))
A24: Accessories | B24: Gifts | C24: FAYE UK LTD CENPAC | D24: 105661 | E24: SS22 LRG ADULT PONCHO | F24: Asstd | G24: 17.99 | AL24: 0 | AM24: 0 | AN24: 8 | AO24: 0 | AP24: 8 | AQ24: 0 | AX24: 0 | AY24: 0 | AZ24: 8 | BA24: 0 | BB24: 8 | BC24: 0 | BP24: 0 | BQ24: 0 | BR24: 8 | BS24: 0 | BT24: 8 | BU24: 0 | CT24: 0 | CU24: 0 | CV24: 24 | CW24: 0 | CX24: 24 | CY24: 0 | DB24: =IF(DA24="","",1-(DA24/Main!$G24)) | DD24: =IF(DC24="","",1-(DC24/Main!$G24)) | DF24: =IF(DE24="","",1-(DE24/Main!$G24)) | DH24: =IF(DG24="","",1-(DG24/Main!$G24))
A25: Accessories | B25: Gifts | C25: MAD BEAUTY LTD | D25: 103133 | E25: SS22 FB-FG5563 IN FULL BLOOM WATERING CAN GIFT SET | F25: Multi | G25: 13.99 | H25: 0 | I25: 3 | J25: 0 | K25: 0 | L25: 3 | M25: 17.49 | T25: 0 | U25: 4 | V25: 0 | W25: 0 | X25: 4 | Y25: 23.32 | Z25: 4 | AA25: 3 | AB25: 0 | AC25: 0.57142857 | AD25: 12 | AE25: 17.49 | AF25: 1 | AG25: 0 | AH25: 0 | AI25: 1 | AJ25: 0 | AK25: 0 | AL25: 0 | AM25: 4 | AN25: 0 | AO25: 0 | AP25: 4 | AQ25: 23.32 | AR25: 0 | AS25: 4 | AT25: 0 | AU25: 0 | AV25: 4 | AW25: 23.32 | AX25: 8 | AY25: 1 | AZ25: 0 | BA25: 0.88888889 | BB25: 1 | BC25: 5.83 | BD25: 0 | BE25: 5 | BF25: 0 | BG25: 0 | BH25: 5 | BI25: 29.15 | BJ25: 3 | BK25: 0 | BL25: 3 | BM25: 1 | BN25: 12 | BO25: 0 | BP25: 0 | BQ25: 4 | BR25: 0 | BS25: 0 | BT25: 4 | BU25: 23.32 | BV25: 2 | BW25: 0 | BX25: 0 | BY25: 1 | BZ25: 0 | CA25: 0 | CB25: 0 | CC25: 2 | CD25: 0 | CE25: 0 | CF25: 2 | CG25: 11.66 | CT25: 18 | CU25: 30 | CV25: 3 | CW25: 0.37169312 | CX25: 51 | CY25: 174.9 | DB25: =IF(DA25="","",1-(DA25/Main!$G25)) | DD25: =IF(DC25="","",1-(DC25/Main!$G25)) | DF25: =IF(DE25="","",1-(DE25/Main!$G25)) | DH25: =IF(DG25="","",1-(DG25/Main!$G25))
A26: Accessories | B26: Gifts | C26: MAD BEAUTY LTD | D26: 103134 | E26: SS22 FB-FG5560 IN FULL BLOOM BATH SALT S | F26: Multi | G26: 3.5 | H26: 0 | I26: 6 | J26: 0 | K26: 0 | L26: 6 | M26: 8.76 | T26: 0 | U26: 5 | V26: 0 | W26: 0 | X26: 5 | Y26: 7.3 | Z26: 0 | AA26: 6 | AB26: 0 | AC26: 0 | AD26: 6 | AE26: 8.76 | AF26: 2 | AG26: 4 | AH26: 0 | AI26: 0.33333333 | AJ26: 16 | AK26: 5.84 | AL26: 0 | AM26: 10 | AN26: 0 | AO26: 0 | AP26: 10 | AQ26: 14.6 | AR26: 0 | AS26: 5 | AT26: 0 | AU26: 0 | AV26: 5 | AW26: 7.3 | AX26: 0 | AY26: 5 | AZ26: 0 | BA26: 0 | BB26: 5 | BC26: 7.3 | BD26: 0 | BE26: 5 | BF26: 0 | BG26: 0 | BH26: 5 | BI26: 7.3 | BJ26: 0 | BK26: 3 | BL26: 6 | BM26: 0 | BN26: 9 | BO26: 4.38 | BP26: 0 | BQ26: 5 | BR26: 0 | BS26: 0 | BT26: 5 | BU26: 7.3 | BV26: 0 | BW26: 6 | BX26: 0 | BY26: 0 | BZ26: 6 | CA26: 8.76 | CB26: 2 | CC26: 4 | CD26: 0 | CE26: 0.33333333 | CF26: 16 | CG26: 5.84 | CN26: 0 | CO26: 6 | CP26: 0 | CQ26: 0 | CR26: 6 | CS26: 8.76 | CT26: 4 | CU26: 70 | CV26: 6 | CW26: 0.051282051 | CX26: 100 | CY26: 102.2 | DB26: =IF(DA26="","",1-(DA26/Main!$G26)) | DD26: =IF(DC26="","",1-(DC26/Main!$G26)) | DF26: =IF(DE26="","",1-(DE26/Main!$G26)) | DH26: =IF(DG26="","",1-(DG26/Main!$G26))
A27: Accessories | B27: Gifts | C27: MAD BEAUTY LTD | D27: 103135 | E27: SS22 FB-FG5544-6 IN FULL BLOOM HAND CARE SET | F27: Multi | G27: 4.99 | H27: 0 | I27: 4 | J27: 0 | K27: 0 | L27: 4 | M27: 8.32 | T27: 0 | U27: 5 | V27: 0 | W27: 0 | X27: 5 | Y27: 10.4 | Z27: 0 | AA27: 5 | AB27: 0 | AC27: 0 | AD27: 5 | AE27: 10.4 | AF27: 0 | AG27: 5 | AH27: 0 | AI27: 0 | AJ27: 5 | AK27: 10.4 | AL27: 5 | AM27: 4 | AN27: 0 | AO27: 0.55555556 | AP27: 16 | AQ27: 8.32 | AR27: 0 | AS27: 5 | AT27: 0 | AU27: 0 | AV27: 5 | AW27: 10.4 | AX27: 2 | AY27: 4 | AZ27: 0 | BA27: 0.33333333 | BB27: 16 | BC27: 8.32 | BD27: 0 | BE27: 2 | BF27: 0 | BG27: 0 | BH27: 2 | BI27: 4.16 | BJ27: 3 | BK27: 0 | BL27: 3 | BM27: 1 | BN27: 6 | BO27: 0 | BP27: 0 | BQ27: 3 | BR27: 0 | BS27: 0 | BT27: 3 | BU27: 6.24 | BV27: 0 | BW27: 3 | BX27: 0 | BY27: 0 | BZ27: 3 | CA27: 6.24 | CB27: 0 | CC27: 1 | CD27: 0 | CE27: 0 | CF27: 1 | CG27: 2.08 | CN27: 0 | CO27: 3 | CP27: 0 | CQ27: 0 | CR27: 3 | CS27: 6.24 | CT27: 10 | CU27: 44 | CV27: 3 | CW27: 0.14529915 | CX27: 74 | CY27: 91.52 | DB27: =IF(DA27="","",1-(DA27/Main!$G27)) | DD27: =IF(DC27="","",1-(DC27/Main!$G27)) | DF27: =IF(DE27="","",1-(DE27/Main!$G27)) | DH27: =IF(DG27="","",1-(DG27/Main!$G27))
A28: Accessories | B28: Gifts | C28: MAD BEAUTY LTD | D28: 103136 | E28: SS22 FB-FG5557-6 IN FULL BLOOM MELTING BATH PETALS | F28: Multi | G28: 10.99 | H28: 0 | I28: 1 | J28: 0 | K28: 0 | L28: 1 | M28: 4.58 | N28: 0 | O28: 3 | P28: 0 | Q28: 0 | R28: 3 | S28: 13.74 | T28: 0 | U28: 3 | V28: 0 | W28: 0 | X28: 3 | Y28: 13.74 | Z28: 0 | AA28: 3 | AB28: 0 | AC28: 0 | AD28: 3 | AE28: 13.74 | AF28: 0 | AG28: 1 | AH28: 0 | AI28: 0 | AJ28: 1 | AK28: 4.58 | AL28: 1 | AM28: 2 | AN28: 0 | AO28: 0.33333333 | AP28: 8 | AQ28: 9.16 | AR28: 0 | AS28: 1 | AT28: 0 | AU28: 0 | AV28: 1 | AW28: 4.58 | AX28: 0 | AY28: 4 | AZ28: 0 | BA28: 0 | BB28: 4 | BC28: 18.32 | BD28: 0 | BE28: 3 | BF28: 0 | BG28: 0 | BH28: 3 | BI28: 13.74 | BJ28: 0 | BK28: 1 | BL28: 3 | BM28: 0 | BN28: 4 | BO28: 4.58 | BP28: 3 | BQ28: 0 | BR28: 0 | BS28: 1 | BT28: 0 | BU28: 0 | CB28: 1 | CC28: 2 | CD28: 0 | CE28: 0.33333333 | CF28: 8 | CG28: 9.16 | CT28: 5 | CU28: 24 | CV28: 3 | CW28: 0.13888889 | CX28: 39 | CY28: 109.92 | DB28: =IF(DA28="","",1-(DA28/Main!$G28)) | DD28: =IF(DC28="","",1-(DC28/Main!$G28)) | DF28: =IF(DE28="","",1-(DE28/Main!$G28)) | DH28: =IF(DG28="","",1-(DG28/Main!$G28))
A29: Accessories | B29: Gifts | C29: MAD BEAUTY LTD | D29: 103137 | E29: SS22 MBHSG-24 | F29: Multi | G29: 2.99 | H29: 0 | I29: 47 | J29: 0 | K29: 0 | L29: 188 | M29: 58.75 | N29: 3 | O29: 45 | P29: 0 | Q29: 0.0625 | R29: 60 | S29: 56.25 | Z29: 2 | AA29: 46 | AB29: 0 | AC29: 0.041666667 | AD29: 92 | AE29: 57.5 | AL29: 0 | AM29: 48 | AN29: 0 | AO29: 0 | AP29: 48 | AQ29: 60 | AX29: 0 | AY29: -4 | AZ29: 0 | BA29: 0 | BB29: 0 | BC29: -5 | BD29: 0 | BE29: 48 | BF29: 0 | BG29: 0 | BH29: 48 | BI29: 60 | BJ29: 0 | BK29: 24 | BL29: 12 | BM29: 0 | BN29: 36 | BO29: 30 | BP29: 0 | BQ29: -1 | BR29: 0 | BS29: 0 | BT29: 0 | BU29: -1.25 | CB29: 0 | CC29: -2 | CD29: 0 | CE29: 0 | CF29: 0 | CG29: -2.5 | CT29: 5 | CU29: 251 | CV29: 12 | CW29: 0.011574074 | CX29: 472 | CY29: 313.75 | DB29: =IF(DA29="","",1-(DA29/Main!$G29)) | DD29: =IF(DC29="","",1-(DC29/Main!$G29)) | DF29: =IF(DE29="","",1-(DE29/Main!$G29)) | DH29: =IF(DG29="","",1-(DG29/Main!$G29))
A30: Accessories | B30: Gifts | C30: MAD BEAUTY LTD | D30: 103138 | E30: SS22 MBD-FG2559-EU24 DOGS HAND CLEANSING GEL | F30: Multi | G30: 2.5 | H30: 0 | I30: 48 | J30: 0 | K30: 0 | L30: 48 | M30: 50.4 | N30: 0 | O30: 24 | P30: 0 | Q30: 0 | R30: 24 | S30: 25.2 | Z30: 0 | AA30: 48 | AB30: 0 | AC30: 0 | AD30: 48 | AE30: 50.4 | AL30: 0 | AM30: 48 | AN30: 0 | AO30: 0 | AP30: 48 | AQ30: 50.4 | BD30: 0 | BE30: 48 | BF30: 0 | BG30: 0 | BH30: 48 | BI30: 50.4 | BJ30: 0 | BK30: 24 | BL30: 12 | BM30: 0 | BN30: 36 | BO30: 25.2 | CT30: 0 | CU30: 240 | CV30: 12 | CW30: 0 | CX30: 252 | CY30: 252 | DB30: =IF(DA30="","",1-(DA30/Main!$G30)) | DD30: =IF(DC30="","",1-(DC30/Main!$G30)) | DF30: =IF(DE30="","",1-(DE30/Main!$G30)) | DH30: =IF(DG30="","",1-(DG30/Main!$G30))
A31: Accessories | B31: Gifts | C31: MAD BEAUTY LTD | D31: 103139 | E31: SS22 MBHSS-24 | F31: Multi | G31: 2.99 | H31: 0 | I31: 24 | J31: 0 | K31: 0 | L31: 24 | M31: 30 | Z31: 0 | AA31: 36 | AB31: 12 | AC31: 0 | AD31: 48 | AE31: 45 | AL31: 0 | AM31: 36 | AN31: 12 | AO31: 0 | AP31: 48 | AQ31: 45 | BD31: 0 | BE31: 48 | BF31: 0 | BG31: 0 | BH31: 48 | BI31: 60 | BJ31: 0 | BK31: 24 | BL31: 12 | BM31: 0 | BN31: 36 | BO31: 30 | CT31: 0 | CU31: 168 | CV31: 36 | CW31: 0 | CX31: 204 | CY31: 210 | DB31: =IF(DA31="","",1-(DA31/Main!$G31)) | DD31: =IF(DC31="","",1-(DC31/Main!$G31)) | DF31: =IF(DE31="","",1-(DE31/Main!$G31)) | DH31: =IF(DG31="","",1-(DG31/Main!$G31))
A32: Accessories | B32: Gifts | C32: MAD BEAUTY LTD | D32: 103140 | E32: SS22 MBHSM1-24 | F32: Multi | G32: 2.99 | H32: 0 | I32: 24 | J32: 0 | K32: 0 | L32: 24 | M32: 30 | Z32: 0 | AA32: 48 | AB32: 0 | AC32: 0 | AD32: 48 | AE32: 60 | AL32: 0 | AM32: 48 | AN32: 0 | AO32: 0 | AP32: 48 | AQ32: 60 | BJ32: 0 | BK32: 24 | BL32: 12 | BM32: 0 | BN32: 36 | BO32: 30 | CT32: 0 | CU32: 144 | CV32: 12 | CW32: 0 | CX32: 156 | CY32: 180 | DB32: =IF(DA32="","",1-(DA32/Main!$G32)) | DD32: =IF(DC32="","",1-(DC32/Main!$G32)) | DF32: =IF(DE32="","",1-(DE32/Main!$G32)) | DH32: =IF(DG32="","",1-(DG32/Main!$G32))
A33: Accessories | B33: Gifts | C33: REX INTERNATIONAL | D33: 103141 | E33: SS22 28656 LOVE BIRDS LUNCH BAG | F33: Multi | G33: 4.95 | H33: 0 | I33: 8 | J33: 0 | K33: 0 | L33: 8 | M33: 13.2 | N33: 2 | O33: 5 | P33: 0 | Q33: 0.28571429 | R33: 20 | S33: 8.25 | T33: 0 | U33: 9 | V33: 0 | W33: 0 | X33: 9 | Y33: 14.85 | Z33: 0 | AA33: 6 | AB33: 0 | AC33: 0 | AD33: 6 | AE33: 9.9 | AF33: 2 | AG33: 8 | AH33: 0 | AI33: 0.2 | AJ33: 32 | AK33: 13.2 | AL33: 3 | AM33: 4 | AN33: 0 | AO33: 0.42857143 | AP33: 16 | AQ33: 6.6 | AR33: 0 | AS33: 7 | AT33: 0 | AU33: 0 | AV33: 7 | AW33: 11.55 | AX33: 0 | AY33: 9 | AZ33: 0 | BA33: 0 | BB33: 9 | BC33: 14.85 | BD33: 0 | BE33: 5 | BF33: 0 | BG33: 0 | BH33: 5 | BI33: 8.25 | BJ33: 0 | BK33: 6 | BL33: 0 | BM33: 0 | BN33: 6 | BO33: 9.9 | BP33: 0 | BQ33: 5 | BR33: 0 | BS33: 0 | BT33: 5 | BU33: 8.25 | BV33: 0 | BW33: 5 | BX33: 0 | BY33: 0 | BZ33: 5 | CA33: 8.25 | CB33: 0 | CC33: 2 | CD33: 0 | CE33: 0 | CF33: 2 | CG33: 3.3 | CN33: 0 | CO33: 3 | CP33: 0 | CQ33: 0 | CR33: 3 | CS33: 4.95 | CT33: 7 | CU33: 82 | CV33: 0 | CW33: 0.065306122 | CX33: 133 | CY33: 135.3 | DB33: =IF(DA33="","",1-(DA33/Main!$G33)) | DD33: =IF(DC33="","",1-(DC33/Main!$G33)) | DF33: =IF(DE33="","",1-(DE33/Main!$G33)) | DH33: =IF(DG33="","",1-(DG33/Main!$G33))
A34: Accessories | B34: Gifts | C34: REX INTERNATIONAL | D34: 103142 | E34: SS22 28659 LOVE BIRDS SHOPPING BAG | F34: Multi | G34: 3.95 | H34: 3 | I34: 4 | J34: 0 | K34: 0.42857143 | L34: 16 | M34: 5.8 | N34: 0 | O34: 7 | P34: 0 | Q34: 0 | R34: 7 | S34: 10.15 | T34: 2 | U34: 9 | V34: 0 | W34: 0.18181818 | X34: 36 | Y34: 13.05 | Z34: 0 | AA34: 7 | AB34: 0 | AC34: 0 | AD34: 7 | AE34: 10.15 | AF34: 0 | AG34: 10 | AH34: 0 | AI34: 0 | AJ34: 10 | AK34: 14.5 | AL34: 1 | AM34: 3 | AN34: 0 | AO34: 0.25 | AP34: 12 | AQ34: 4.35 | AR34: 0 | AS34: 7 | AT34: 0 | AU34: 0 | AV34: 7 | AW34: 10.15 | AX34: 0 | AY34: 10 | AZ34: 0 | BA34: 0 | BB34: 10 | BC34: 14.5 | BD34: 5 | BE34: 3 | BF34: 0 | BG34: 0.625 | BH34: 12 | BI34: 4.35 | BJ34: 0 | BK34: 6 | BL34: 0 | BM34: 0 | BN34: 6 | BO34: 8.7 | BP34: 4 | BQ34: 7 | BR34: 0 | BS34: 0.36363636 | BT34: 28 | BU34: 10.15 | BV34: 0 | BW34: 7 | BX34: 0 | BY34: 0 | BZ34: 7 | CA34: 10.15 | CB34: 0 | CC34: 3 | CD34: 0 | CE34: 0 | CF34: 3 | CG34: 4.35 | CN34: 0 | CO34: 4 | CP34: 0 | CQ34: 0 | CR34: 4 | CS34: 5.8 | CT34: 15 | CU34: 87 | CV34: 0 | CW34: 0.13207328 | CX34: 165 | CY34: 126.15 | DB34: =IF(DA34="","",1-(DA34/Main!$G34)) | DD34: =IF(DC34="","",1-(DC34/Main!$G34)) | DF34: =IF(DE34="","",1-(DE34/Main!$G34)) | DH34: =IF(DG34="","",1-(DG34/Main!$G34))
A35: Accessories | B35: Gifts | C35: REX INTERNATIONAL | D35: 103143 | E35: SS22 28801 LOVE BIRDS CARD HOLDER PURSE | F35: Multi | G35: 6.95 | H35: 1 | I35: 5 | J35: 0 | K35: 0.16666667 | L35: 20 | M35: 12.45 | N35: 1 | O35: 2 | P35: 0 | Q35: 0.33333333 | R35: 8 | S35: 4.98 | T35: 0 | U35: 6 | V35: 0 | W35: 0 | X35: 6 | Y35: 14.94 | Z35: 0 | AA35: 3 | AB35: 0 | AC35: 0 | AD35: 3 | AE35: 7.47 | AF35: 1 | AG35: 2 | AH35: 0 | AI35: 0.33333333 | AJ35: 8 | AK35: 4.98 | AL35: 0 | AM35: 3 | AN35: 0 | AO35: 0 | AP35: 3 | AQ35: 7.47 | AR35: 0 | AS35: 3 | AT35: 0 | AU35: 0 | AV35: 3 | AW35: 7.47 | AX35: 0 | AY35: 3 | AZ35: 0 | BA35: 0 | BB35: 3 | BC35: 7.47 | BD35: 0 | BE35: 2 | BF35: 0 | BG35: 0 | BH35: 2 | BI35: 4.98 | BJ35: 0 | BK35: 2 | BL35: 0 | BM35: 0 | BN35: 2 | BO35: 4.98 | BP35: 2 | BQ35: 2 | BR35: 0 | BS35: 0.5 | BT35: 4 | BU35: 4.98 | BV35: 0 | BW35: 3 | BX35: 0 | BY35: 0 | BZ35: 3 | CA35: 7.47 | CB35: 0 | CC35: 3 | CD35: 0 | CE35: 0 | CF35: 3 | CG35: 7.47 | CT35: 5 | CU35: 39 | CV35: 0 | CW35: 0.1025641 | CX35: 68 | CY35: 97.11 | DB35: =IF(DA35="","",1-(DA35/Main!$G35)) | DD35: =IF(DC35="","",1-(DC35/Main!$G35)) | DF35: =IF(DE35="","",1-(DE35/Main!$G35)) | DH35: =IF(DG35="","",1-(DG35/Main!$G35))
A36: Accessories | B36: Gifts | C36: REX INTERNATIONAL | D36: 103144 | E36: SS22 28805 LOVE BIRDS PURSE | F36: Multi | G36: 5.95 | H36: 0 | I36: 6 | J36: 0 | K36: 0 | L36: 6 | M36: 12.48 | T36: 3 | U36: 1 | V36: 0 | W36: 0.75 | X36: 4 | Y36: 2.08 | Z36: 0 | AA36: 1 | AB36: 0 | AC36: 0 | AD36: 1 | AE36: 2.08 | AF36: 0 | AG36: 5 | AH36: 0 | AI36: 0 | AJ36: 5 | AK36: 10.4 | AL36: 0 | AM36: 3 | AN36: 0 | AO36: 0 | AP36: 3 | AQ36: 6.24 | AR36: 0 | AS36: 2 | AT36: 0 | AU36: 0 | AV36: 2 | AW36: 4.16 | AX36: 0 | AY36: 5 | AZ36: 0 | BA36: 0 | BB36: 5 | BC36: 10.4 | BD36: 0 | BE36: 1 | BF36: 0 | BG36: 0 | BH36: 1 | BI36: 2.08 | BJ36: 0 | BK36: 2 | BL36: 0 | BM36: 0 | BN36: 2 | BO36: 4.16 | BP36: 0 | BQ36: 3 | BR36: 0 | BS36: 0 | BT36: 3 | BU36: 6.24 | BV36: 0 | BW36: 3 | BX36: 0 | BY36: 0 | BZ36: 3 | CA36: 6.24 | CB36: 3 | CC36: 0 | CD36: 0 | CE36: 1 | CF36: 0 | CG36: 0 | CT36: 6 | CU36: 32 | CV36: 0 | CW36: 0.14583333 | CX36: 35 | CY36: 66.56 | DB36: =IF(DA36="","",1-(DA36/Main!$G36)) | DD36: =IF(DC36="","",1-(DC36/Main!$G36)) | DF36: =IF(DE36="","",1-(DE36/Main!$G36)) | DH36: =IF(DG36="","",1-(DG36/Main!$G36))
A37: Accessories | B37: Gifts | C37: REX INTERNATIONAL | D37: 103145 | E37: SS22 28841 LOVE BIRDS MAGNETIC SHOPPING LIST | F37: Multi | G37: 3.95 | H37: 6 | I37: 0 | J37: 0 | K37: 1 | L37: 0 | M37: 0 | T37: 3 | U37: 4 | V37: 0 | W37: 0.42857143 | X37: 16 | Y37: 5.8 | Z37: 3 | AA37: 0 | AB37: 0 | AC37: 1 | AD37: 0 | AE37: 0 | AL37: 0 | AM37: 2 | AN37: 0 | AO37: 0 | AP37: 2 | AQ37: 2.9 | AR37: 0 | AS37: 2 | AT37: 0 | AU37: 0 | AV37: 2 | AW37: 2.9 | BJ37: 0 | BK37: 1 | BL37: 0 | BM37: 0 | BN37: 1 | BO37: 1.45 | BP37: 0 | BQ37: 3 | BR37: 0 | BS37: 0 | BT37: 3 | BU37: 4.35 | BV37: 2 | BW37: 1 | BX37: 0 | BY37: 0.66666667 | BZ37: 4 | CA37: 1.45 | CB37: 2 | CC37: 1 | CD37: 0 | CE37: 0.66666667 | CF37: 4 | CG37: 1.45 | CT37: 16 | CU37: 14 | CV37: 0 | CW37: 0.41798942 | CX37: 32 | CY37: 20.3 | DB37: =IF(DA37="","",1-(DA37/Main!$G37)) | DD37: =IF(DC37="","",1-(DC37/Main!$G37)) | DF37: =IF(DE37="","",1-(DE37/Main!$G37)) | DH37: =IF(DG37="","",1-(DG37/Main!$G37))
A38: Accessories | B38: Gifts | C38: REX INTERNATIONAL | D38: 103146 | E38: SS22 28972 LOVE BIRDS GLASSES CASE & CLEANING CLOTH | F38: Multi | G38: 4.95 | N38: 3 | O38: 1 | P38: 0 | Q38: 0.75 | R38: 4 | S38: 1.79 | T38: 0 | U38: 4 | V38: 0 | W38: 0 | X38: 4 | Y38: 7.16 | Z38: 0 | AA38: 2 | AB38: 0 | AC38: 0 | AD38: 2 | AE38: 3.58 | AF38: 0 | AG38: 2 | AH38: 0 | AI38: 0 | AJ38: 2 | AK38: 3.58 | AX38: 0 | AY38: 2 | AZ38: 0 | BA38: 0 | BB38: 2 | BC38: 3.58 | BD38: 0 | BE38: 1 | BF38: 0 | BG38: 0 | BH38: 1 | BI38: 1.79 | BJ38: 0 | BK38: 1 | BL38: 0 | BM38: 0 | BN38: 1 | BO38: 1.79 | BP38: 0 | BQ38: 3 | BR38: 0 | BS38: 0 | BT38: 3 | BU38: 5.37 | CB38: 3 | CC38: 0 | CD38: 0 | CE38: 1 | CF38: 0 | CG38: 0 | CT38: 6 | CU38: 16 | CV38: 0 | CW38: 0.19444444 | CX38: 19 | CY38: 28.64 | DB38: =IF(DA38="","",1-(DA38/Main!$G38)) | DD38: =IF(DC38="","",1-(DC38/Main!$G38)) | DF38: =IF(DE38="","",1-(DE38/Main!$G38)) | DH38: =IF(DG38="","",1-(DG38/Main!$G38))
A39: Accessories | B39: Gifts | C39: REX INTERNATIONAL | D39: 103147 | E39: SS22 29130 LOVE BIRDS 420ML GLASS DRINKING BOTTLE | F39: Multi | G39: 9.95 | H39: 0 | I39: 4 | J39: 0 | K39: 0 | L39: 4 | M39: 15 | T39: 0 | U39: 2 | V39: 0 | W39: 0 | X39: 2 | Y39: 7.5 | Z39: 2 | AA39: 1 | AB39: 0 | AC39: 0.66666667 | AD39: 4 | AE39: 3.75 | AF39: 0 | AG39: 3 | AH39: 0 | AI39: 0 | AJ39: 3 | AK39: 11.25 | AL39: 0 | AM39: 1 | AN39: 0 | AO39: 0 | AP39: 1 | AQ39: 3.75 | AR39: 0 | AS39: 3 | AT39: 0 | AU39: 0 | AV39: 3 | AW39: 11.25 | AX39: 0 | AY39: 3 | AZ39: 0 | BA39: 0 | BB39: 3 | BC39: 11.25 | BD39: 4 | BE39: 2 | BF39: 0 | BG39: 0.66666667 | BH39: 8 | BI39: 7.5 | BJ39: 0 | BK39: 3 | BL39: 0 | BM39: 0 | BN39: 3 | BO39: 11.25 | BP39: 0 | BQ39: 3 | BR39: 0 | BS39: 0 | BT39: 3 | BU39: 11.25 | CB39: 0 | CC39: 3 | CD39: 0 | CE39: 0 | CF39: 3 | CG39: 11.25 | CT39: 6 | CU39: 28 | CV39: 0 | CW39: 0.12121212 | CX39: 37 | CY39: 105 | DB39: =IF(DA39="","",1-(DA39/Main!$G39)) | DD39: =IF(DC39="","",1-(DC39/Main!$G39)) | DF39: =IF(DE39="","",1-(DE39/Main!$G39)) | DH39: =IF(DG39="","",1-(DG39/Main!$G39))
A40: Accessories | B40: Gifts | C40: REX INTERNATIONAL | D40: 103148 | E40: SS22 29148 ASSORTED RECYCLED SHOPPER BAGS | F40: Multi | G40: 5.95 | H40: 24 | I40: 39 | J40: 0 | K40: 0.38095238 | L40: 31 | M40: 81.12 | N40: 6 | O40: 10 | P40: 0 | Q40: 0.375 | R40: 10 | S40: 20.8 | T40: 12 | U40: 22 | V40: 0 | W40: 0.35294118 | X40: 22 | Y40: 45.76 | Z40: 15 | AA40: 12 | AB40: 0 | AC40: 0.55555556 | AD40: 6 | AE40: 24.96 | AF40: 4 | AG40: -2 | AH40: 0 | AI40: 2 | AJ40: 0 | AK40: -4.16 | AL40: 9 | AM40: 18 | AN40: 0 | AO40: 0.33333333 | AP40: 12 | AQ40: 37.44 | AR40: 6 | AS40: 21 | AT40: 0 | AU40: 0.22222222 | AV40: 42 | AW40: 43.68 | AX40: 13 | AY40: 43 | AZ40: 0 | BA40: 0.23214286 | BB40: 86 | BC40: 89.44 | BD40: 4 | BE40: 10 | BF40: 0 | BG40: 0.28571429 | BH40: 40 | BI40: 20.8 | BJ40: 17 | BK40: 7 | BL40: 0 | BM40: 0.70833333 | BN40: 5 | BO40: 14.56 | BP40: 7 | BQ40: 23 | BR40: 0 | BS40: 0.23333333 | BT40: 31 | BU40: 47.84 | BV40: 0 | BW40: 17 | BX40: 0 | BY40: 0 | BZ40: 17 | CA40: 35.36 | CB40: 6 | CC40: 21 | CD40: 0 | CE40: 0.22222222 | CF40: 42 | CG40: 43.68 | CN40: 0 | CO40: 4 | CP40: 0 | CQ40: 0 | CR40: 4 | CS40: 8.32 | CT40: 123 | CU40: 245 | CV40: 0 | CW40: 0.42155362 | CX40: 348 | CY40: 509.6 | DB40: =IF(DA40="","",1-(DA40/Main!$G40)) | DD40: =IF(DC40="","",1-(DC40/Main!$G40)) | DF40: =IF(DE40="","",1-(DE40/Main!$G40)) | DH40: =IF(DG40="","",1-(DG40/Main!$G40))
A41: Accessories | B41: Gifts | C41: REX INTERNATIONAL | D41: 103149 | E41: SS22 29181 WILD FLOWERS TEA TOWEL | F41: Multi | G41: 5.95 | H41: 6 | I41: 13 | J41: 0 | K41: 0.31578947 | L41: 52 | M41: 27.04 | N41: 0 | O41: 5 | P41: 0 | Q41: 0 | R41: 5 | S41: 10.4 | T41: 0 | U41: 8 | V41: 0 | W41: 0 | X41: 8 | Y41: 16.64 | Z41: 4 | AA41: 6 | AB41: 0 | AC41: 0.4 | AD41: 12 | AE41: 12.48 | AF41: 0 | AG41: 11 | AH41: 0 | AI41: 0 | AJ41: 11 | AK41: 22.88 | AL41: 5 | AM41: 5 | AN41: 0 | AO41: 0.5 | AP41: 20 | AQ41: 10.4 | AR41: 6 | AS41: 4 | AT41: 0 | AU41: 0.6 | AV41: 4 | AW41: 8.32 | AX41: 0 | AY41: 11 | AZ41: 0 | BA41: 0 | BB41: 11 | BC41: 22.88 | BD41: 0 | BE41: 8 | BF41: 0 | BG41: 0 | BH41: 8 | BI41: 16.64 | BJ41: 0 | BK41: 1 | BL41: 0 | BM41: 0 | BN41: 1 | BO41: 2.08 | BP41: 3 | BQ41: 12 | BR41: 0 | BS41: 0.2 | BT41: 48 | BU41: 24.96 | BV41: 1 | BW41: 9 | BX41: 0 | BY41: 0.1 | BZ41: 36 | CA41: 18.72 | CB41: 0 | CC41: 4 | CD41: 0 | CE41: 0 | CF41: 4 | CG41: 8.32 | CN41: 0 | CO41: 1 | CP41: 0 | CQ41: 0 | CR41: 1 | CS41: 2.08 | CT41: 25 | CU41: 98 | CV41: 0 | CW41: 0.15112782 | CX41: 221 | CY41: 203.84 | DB41: =IF(DA41="","",1-(DA41/Main!$G41)) | DD41: =IF(DC41="","",1-(DC41/Main!$G41)) | DF41: =IF(DE41="","",1-(DE41/Main!$G41)) | DH41: =IF(DG41="","",1-(DG41/Main!$G41))
A42: Accessories | B42: Gifts | C42: REX INTERNATIONAL | D42: 103150 | E42: SS22 29242 WILD FLOWERS LUNCH BAG | F42: Multi | G42: 4.95 | H42: 0 | I42: 6 | J42: 0 | K42: 0 | L42: 6 | M42: 9.9 | N42: 2 | O42: 5 | P42: 0 | Q42: 0.28571429 | R42: 20 | S42: 8.25 | T42: 0 | U42: 6 | V42: 0 | W42: 0 | X42: 6 | Y42: 9.9 | Z42: 3 | AA42: 5 | AB42: 0 | AC42: 0.375 | AD42: 20 | AE42: 8.25 | AF42: 2 | AG42: 5 | AH42: 0 | AI42: 0.28571429 | AJ42: 20 | AK42: 8.25 | AL42: 3 | AM42: 4 | AN42: 0 | AO42: 0.42857143 | AP42: 8 | AQ42: 6.6 | AR42: 3 | AS42: 4 | AT42: 0 | AU42: 0.42857143 | AV42: 5 | AW42: 6.6 | AX42: 5 | AY42: 5 | AZ42: 0 | BA42: 0.5 | BB42: 20 | BC42: 8.25 | BD42: 0 | BE42: 6 | BF42: 0 | BG42: 0 | BH42: 6 | BI42: 9.9 | BJ42: 0 | BK42: 5 | BL42: 0 | BM42: 0 | BN42: 5 | BO42: 8.25 | BP42: 0 | BQ42: 9 | BR42: 0 | BS42: 0 | BT42: 9 | BU42: 14.85 | BV42: 0 | BW42: 6 | BX42: 0 | BY42: 0 | BZ42: 6 | CA42: 9.9 | CB42: 3 | CC42: 1 | CD42: 0 | CE42: 0.75 | CF42: 4 | CG42: 1.65 | CN42: 0 | CO42: 4 | CP42: 0 | CQ42: 0 | CR42: 4 | CS42: 6.6 | CT42: 21 | CU42: 71 | CV42: 0 | CW42: 0.21811224 | CX42: 139 | CY42: 117.15 | DB42: =IF(DA42="","",1-(DA42/Main!$G42)) | DD42: =IF(DC42="","",1-(DC42/Main!$G42)) | DF42: =IF(DE42="","",1-(DE42/Main!$G42)) | DH42: =IF(DG42="","",1-(DG42/Main!$G42))
A43: Accessories | B43: Gifts | C43: REX INTERNATIONAL | D43: 103151 | E43: SS22 29359 WILD FLOWERS SHOPPING BAG | F43: Multi | G43: 3.95 | H43: 0 | I43: 10 | J43: 0 | K43: 0 | L43: 10 | M43: 14.5 | N43: 0 | O43: 6 | P43: 0 | Q43: 0 | R43: 6 | S43: 8.7 | T43: 0 | U43: 6 | V43: 0 | W43: 0 | X43: 6 | Y43: 8.7 | Z43: 0 | AA43: 8 | AB43: 0 | AC43: 0 | AD43: 8 | AE43: 11.6 | AF43: 7 | AG43: 6 | AH43: 0 | AI43: 0.53846154 | AJ43: 8 | AK43: 8.7 | AL43: 7 | AM43: 0 | AN43: 0 | AO43: 1 | AP43: 0 | AQ43: 0 | AR43: 4 | AS43: 4 | AT43: 0 | AU43: 0.5 | AV43: 16 | AW43: 5.8 | AX43: 6 | AY43: 4 | AZ43: 0 | BA43: 0.6 | BB43: 3 | BC43: 5.8 | BD43: 0 | BE43: 6 | BF43: 0 | BG43: 0 | BH43: 6 | BI43: 8.7 | BJ43: 1 | BK43: 3 | BL43: 0 | BM43: 0.25 | BN43: 12 | BO43: 4.35 | BP43: 0 | BQ43: 9 | BR43: 0 | BS43: 0 | BT43: 9 | BU43: 13.05 | BV43: 0 | BW43: 7 | BX43: 0 | BY43: 0 | BZ43: 7 | CA43: 10.15 | CB43: 0 | CC43: 1 | CD43: 0 | CE43: 0 | CF43: 1 | CG43: 1.45 | CN43: 0 | CO43: 3 | CP43: 0 | CQ43: 0 | CR43: 3 | CS43: 4.35 | CT43: 25 | CU43: 73 | CV43: 0 | CW43: 0.20631868 | CX43: 95 | CY43: 105.85 | DB43: =IF(DA43="","",1-(DA43/Main!$G43)) | DD43: =IF(DC43="","",1-(DC43/Main!$G43)) | DF43: =IF(DE43="","",1-(DE43/Main!$G43)) | DH43: =IF(DG43="","",1-(DG43/Main!$G43))
A44: Accessories | B44: Gifts | C44: REX INTERNATIONAL | D44: 103152 | E44: SS22 29361 WILD FLOWERS MAGNETIC SHOPPING LIST | F44: Multi | G44: 3.95 | H44: 0 | I44: 2 | J44: 0 | K44: 0 | L44: 2 | M44: 2.9 | T44: 5 | U44: 2 | V44: 0 | W44: 0.71428571 | X44: 8 | Y44: 2.9 | AF44: 3 | AG44: -1 | AH44: 0 | AI44: 1.5 | AJ44: 0 | AK44: -1.45 | AL44: 0 | AM44: 1 | AN44: 0 | AO44: 0 | AP44: 1 | AQ44: 1.45 | AR44: 0 | AS44: 2 | AT44: 0 | AU44: 0 | AV44: 2 | AW44: 2.9 | BD44: 0 | BE44: 1 | BF44: 0 | BG44: 0 | BH44: 1 | BI44: 1.45 | BP44: 0 | BQ44: 5 | BR44: 0 | BS44: 0 | BT44: 5 | BU44: 7.25 | CB44: 3 | CC44: 0 | CD44: 0 | CE44: 1 | CF44: 0 | CG44: 0 | CT44: 11 | CU44: 12 | CV44: 0 | CW44: 0.40178571 | CX44: 19 | CY44: 17.4 | DB44: =IF(DA44="","",1-(DA44/Main!$G44)) | DD44: =IF(DC44="","",1-(DC44/Main!$G44)) | DF44: =IF(DE44="","",1-(DE44/Main!$G44)) | DH44: =IF(DG44="","",1-(DG44/Main!$G44))
A45: Accessories | B45: Gifts | C45: REX INTERNATIONAL | D45: 103153 | E45: SS22 29369 ASSORTED YOUR GARDEN FLOWER SEEDS | F45: Multi | G45: 1.95 | H45: 25 | I45: 22 | J45: 0 | K45: 0.53191489 | L45: 18 | M45: 15.84 | N45: 0 | O45: 8 | P45: 0 | Q45: 0 | R45: 8 | S45: 5.76 | T45: 0 | U45: 9 | V45: 0 | W45: 0 | X45: 9 | Y45: 6.48 | Z45: 0 | AA45: 5 | AB45: 0 | AC45: 0 | AD45: 5 | AE45: 3.6 | AF45: 0 | AG45: 3 | AH45: 0 | AI45: 0 | AJ45: 3 | AK45: 2.16 | AL45: 14 | AM45: 19 | AN45: 0 | AO45: 0.42424242 | AP45: 25 | AQ45: 13.68 | AR45: 0 | AS45: 5 | AT45: 0 | AU45: 0 | AV45: 5 | AW45: 3.6 | AX45: 20 | AY45: 2 | AZ45: 0 | BA45: 0.90909091 | BB45: 8 | BC45: 1.44 | BD45: 5 | BE45: 17 | BF45: 0 | BG45: 0.22727273 | BH45: 23 | BI45: 12.24 | BP45: 0 | BQ45: 16 | BR45: 0 | BS45: 0 | BT45: 16 | BU45: 11.52 | BV45: 0 | BW45: 10 | BX45: 0 | BY45: 0 | BZ45: 10 | CA45: 7.2 | CB45: 19 | CC45: 3 | CD45: 0 | CE45: 0.86363636 | CF45: 2 | CG45: 2.16 | CN45: 0 | CO45: 10 | CP45: 0 | CQ45: 0 | CR45: 10 | CS45: 7.2 | CT45: 83 | CU45: 129 | CV45: 0 | CW45: 0.22739672 | CX45: 142 | CY45: 92.88 | DB45: =IF(DA45="","",1-(DA45/Main!$G45)) | DD45: =IF(DC45="","",1-(DC45/Main!$G45)) | DF45: =IF(DE45="","",1-(DE45/Main!$G45)) | DH45: =IF(DG45="","",1-(DG45/Main!$G45))
A46: Accessories | B46: Gifts | C46: REX INTERNATIONAL | D46: 103154 | E46: SS22 29404 WONDERS OF NATURE FLOWER PRESS | F46: Multi | G46: 12.95 | H46: 0 | I46: 1 | J46: 0 | K46: 0 | L46: 1 | M46: 4.55 | N46: 0 | O46: 2 | P46: 0 | Q46: 0 | R46: 2 | S46: 9.1 | T46: 0 | U46: 1 | V46: 0 | W46: 0 | X46: 1 | Y46: 4.55 | AF46: 0 | AG46: 2 | AH46: 0 | AI46: 0 | AJ46: 2 | AK46: 9.1 | AL46: 0 | AM46: 1 | AN46: 0 | AO46: 0 | AP46: 1 | AQ46: 4.55 | AX46: 0 | AY46: 2 | AZ46: 0 | BA46: 0 | BB46: 2 | BC46: 9.1 | BD46: 0 | BE46: 2 | BF46: 0 | BG46: 0 | BH46: 2 | BI46: 9.1 | BJ46: 1 | BK46: 1 | BL46: 0 | BM46: 0.5 | BN46: 4 | BO46: 4.55 | BP46: 0 | BQ46: 2 | BR46: 0 | BS46: 0 | BT46: 2 | BU46: 9.1 | BV46: 0 | BW46: 1 | BX46: 0 | BY46: 0 | BZ46: 1 | CA46: 4.55 | CB46: 0 | CC46: 2 | CD46: 0 | CE46: 0 | CF46: 2 | CG46: 9.1 | CT46: 1 | CU46: 17 | CV46: 0 | CW46: 0.045454545 | CX46: 20 | CY46: 77.35 | DB46: =IF(DA46="","",1-(DA46/Main!$G46)) | DD46: =IF(DC46="","",1-(DC46/Main!$G46)) | DF46: =IF(DE46="","",1-(DE46/Main!$G46)) | DH46: =IF(DG46="","",1-(DG46/Main!$G46))
A47: Accessories | B47: Gifts | C47: REX INTERNATIONAL | D47: 103155 | E47: SS22 29453 WILD FLOWERS MAKE UP BAG | F47: Multi | G47: 7.95 | H47: 0 | I47: 5 | J47: 0 | K47: 0 | L47: 5 | M47: 13.75 | N47: 1 | O47: 2 | P47: 0 | Q47: 0.33333333 | R47: 8 | S47: 5.5 | T47: 0 | U47: 2 | V47: 0 | W47: 0 | X47: 2 | Y47: 5.5 | Z47: 0 | AA47: 2 | AB47: 0 | AC47: 0 | AD47: 2 | AE47: 5.5 | AF47: 0 | AG47: 5 | AH47: 0 | AI47: 0 | AJ47: 5 | AK47: 13.75 | AL47: 0 | AM47: 2 | AN47: 0 | AO47: 0 | AP47: 2 | AQ47: 5.5 | AR47: 0 | AS47: 2 | AT47: 0 | AU47: 0 | AV47: 2 | AW47: 5.5 | AX47: 2 | AY47: 4 | AZ47: 0 | BA47: 0.33333333 | BB47: 16 | BC47: 11 | BD47: 0 | BE47: 3 | BF47: 0 | BG47: 0 | BH47: 3 | BI47: 8.25 | BJ47: 0 | BK47: 3 | BL47: 0 | BM47: 0 | BN47: 3 | BO47: 8.25 | BP47: 0 | BQ47: 5 | BR47: 0 | BS47: 0 | BT47: 5 | BU47: 13.75 | CB47: 0 | CC47: 1 | CD47: 0 | CE47: 0 | CF47: 1 | CG47: 2.75 | CT47: 3 | CU47: 36 | CV47: 0 | CW47: 0.055555556 | CX47: 54 | CY47: 99 | DB47: =IF(DA47="","",1-(DA47/Main!$G47)) | DD47: =IF(DC47="","",1-(DC47/Main!$G47)) | DF47: =IF(DE47="","",1-(DE47/Main!$G47)) | DH47: =IF(DG47="","",1-(DG47/Main!$G47))
A48: Accessories | B48: Gifts | C48: REX INTERNATIONAL | D48: 103156 | E48: SS22 29518 WILD FLOWERS COASTERS(SET OF 4) | F48: Multi | G48: 4.95 | H48: 0 | I48: 5 | J48: 0 | K48: 0 | L48: 5 | M48: 8.95 | N48: 0 | O48: 1 | P48: 0 | Q48: 0 | R48: 1 | S48: 1.79 | T48: 1 | U48: 4 | V48: 0 | W48: 0.2 | X48: 16 | Y48: 7.16 | Z48: 0 | AA48: 3 | AB48: 0 | AC48: 0 | AD48: 3 | AE48: 5.37 | AF48: 1 | AG48: 4 | AH48: 0 | AI48: 0.2 | AJ48: 16 | AK48: 7.16 | AR48: 0 | AS48: 2 | AT48: 0 | AU48: 0 | AV48: 2 | AW48: 3.58 | AX48: 3 | AY48: 3 | AZ48: 0 | BA48: 0.5 | BB48: 6 | BC48: 5.37 | BD48: 0 | BE48: 2 | BF48: 0 | BG48: 0 | BH48: 2 | BI48: 3.58 | BJ48: 0 | BK48: 2 | BL48: 0 | BM48: 0 | BN48: 2 | BO48: 3.58 | BP48: 2 | BQ48: 3 | BR48: 0 | BS48: 0.4 | BT48: 6 | BU48: 5.37 | BV48: 0 | BW48: 2 | BX48: 0 | BY48: 0 | BZ48: 2 | CA48: 3.58 | CB48: 3 | CC48: 0 | CD48: 0 | CE48: 1 | CF48: 0 | CG48: 0 | CT48: 10 | CU48: 31 | CV48: 0 | CW48: 0.19166667 | CX48: 61 | CY48: 55.49 | DB48: =IF(DA48="","",1-(DA48/Main!$G48)) | DD48: =IF(DC48="","",1-(DC48/Main!$G48)) | DF48: =IF(DE48="","",1-(DE48/Main!$G48)) | DH48: =IF(DG48="","",1-(DG48/Main!$G48))
A49: Accessories | B49: Gifts | C49: REX INTERNATIONAL | D49: 103157 | E49: SS22 29581 WILD FLOWERS GLASS CASE AND CLEANING CLOTH | F49: Multi | G49: 4.95 | H49: 6 | I49: 0 | J49: 0 | K49: 1 | L49: 0 | M49: 0 | T49: 3 | U49: 2 | V49: 0 | W49: 0.6 | X49: 8 | Y49: 3.58 | AF49: 2 | AG49: -1 | AH49: 0 | AI49: 2 | AJ49: 0 | AK49: -1.79 | BP49: 0 | BQ49: 1 | BR49: 0 | BS49: 0 | BT49: 1 | BU49: 1.79 | CB49: 3 | CC49: 0 | CD49: 0 | CE49: 1 | CF49: 0 | CG49: 0 | CT49: 14 | CU49: 2 | CV49: 0 | CW49: 0.92 | CX49: 9 | CY49: 3.58 | DB49: =IF(DA49="","",1-(DA49/Main!$G49)) | DD49: =IF(DC49="","",1-(DC49/Main!$G49)) | DF49: =IF(DE49="","",1-(DE49/Main!$G49)) | DH49: =IF(DG49="","",1-(DG49/Main!$G49))
A50: Accessories | B50: Gifts | C50: REX INTERNATIONAL | D50: 103220 | E50: SS22 29572 WILD FLOWERS FLASK AND CUP | F50: Multi | G50: 12.95 | H50: 0 | I50: 5 | J50: 0 | K50: 0 | L50: 5 | M50: 20.75 | AF50: 2 | AG50: -1 | AH50: 0 | AI50: 2 | AJ50: 0 | AK50: -4.15 | AR50: 0 | AS50: 1 | AT50: 0 | AU50: 0 | AV50: 1 | AW50: 4.15 | BP50: 4 | BQ50: 2 | BR50: 0 | BS50: 0.66666667 | BT50: 8 | BU50: 8.3 | BV50: 0 | BW50: 1 | BX50: 0 | BY50: 0 | BZ50: 1 | CA50: 4.15 | CT50: 6 | CU50: 8 | CV50: 0 | CW50: 0.53333333 | CX50: 15 | CY50: 33.2 | DB50: =IF(DA50="","",1-(DA50/Main!$G50)) | DD50: =IF(DC50="","",1-(DC50/Main!$G50)) | DF50: =IF(DE50="","",1-(DE50/Main!$G50)) | DH50: =IF(DG50="","",1-(DG50/Main!$G50))
A51: Accessories | B51: Gifts | C51: REX INTERNATIONAL | D51: 103414 | E51: SS22 29470 FOLK DOVES DOORMAT | F51: Multi | G51: 15 | AF51: 0 | AG51: 1 | AH51: 0 | AI51: 0 | AJ51: 1 | AK51: 5.95 | AL51: 0 | AM51: 2 | AN51: 0 | AO51: 0 | AP51: 2 | AQ51: 11.9 | AX51: 0 | AY51: 1 | AZ51: 0 | BA51: 0 | BB51: 1 | BC51: 5.95 | BJ51: 0 | BK51: 1 | BL51: 0 | BM51: 0 | BN51: 1 | BO51: 5.95 | CN51: 0 | CO51: 1 | CP51: 0 | CQ51: 0 | CR51: 1 | CS51: 5.95 | CT51: 0 | CU51: 6 | CV51: 0 | CW51: 0 | CX51: 6 | CY51: 35.7 | DB51: =IF(DA51="","",1-(DA51/Main!$G51)) | DD51: =IF(DC51="","",1-(DC51/Main!$G51)) | DF51: =IF(DE51="","",1-(DE51/Main!$G51)) | DH51: =IF(DG51="","",1-(DG51/Main!$G51))
A52: Accessories | B52: Gifts | C52: REX INTERNATIONAL | D52: 103415 | E52: SS22 29473 WILD FLOWERS DOORMAT | F52: Multi | G52: 15 | AF52: 0 | AG52: 1 | AH52: 0 | AI52: 0 | AJ52: 1 | AK52: 5.95 | AX52: 0 | AY52: 1 | AZ52: 0 | BA52: 0 | BB52: 1 | BC52: 5.95 | CB52: 2 | CC52: 1 | CD52: 0 | CE52: 0.66666667 | CF52: 4 | CG52: 5.95 | CT52: 2 | CU52: 3 | CV52: 0 | CW52: 0.22222222 | CX52: 6 | CY52: 17.85 | DB52: =IF(DA52="","",1-(DA52/Main!$G52)) | DD52: =IF(DC52="","",1-(DC52/Main!$G52)) | DF52: =IF(DE52="","",1-(DE52/Main!$G52)) | DH52: =IF(DG52="","",1-(DG52/Main!$G52))
A53: Accessories | B53: Gifts | C53: WAX LYRICAL LTD CEN | D53: 103093 | E53: SS22 AIS0802 BEE HAPPY REED DIFFUSER 200ML | F53: Lilac | G53: 9.99 | H53: 0 | I53: 20 | J53: 0 | K53: 0 | L53: 20 | M53: 83.4 | N53: 7 | O53: 17 | P53: 0 | Q53: 0.29166667 | R53: 14 | S53: 70.89 | T53: 11 | U53: 16 | V53: 0 | W53: 0.40740741 | X53: 64 | Y53: 66.72 | AF53: 0 | AG53: 19 | AH53: 0 | AI53: 0 | AJ53: 19 | AK53: 79.23 | AL53: 0 | AM53: 19 | AN53: 0 | AO53: 0 | AP53: 19 | AQ53: 79.23 | AR53: 7 | AS53: 18 | AT53: 0 | AU53: 0.28 | AV53: 72 | AW53: 75.06 | AX53: 0 | AY53: 19 | AZ53: 0 | BA53: 0 | BB53: 19 | BC53: 79.23 | BD53: 0 | BE53: 18 | BF53: 0 | BG53: 0 | BH53: 18 | BI53: 75.06 | BJ53: 0 | BK53: 18 | BL53: 0 | BM53: 0 | BN53: 18 | BO53: 75.06 | BP53: 11 | BQ53: 15 | BR53: 0 | BS53: 0.42307692 | BT53: 15 | BU53: 62.55 | BV53: 0 | BW53: 17 | BX53: 0 | BY53: 0 | BZ53: 17 | CA53: 70.89 | CN53: 0 | CO53: 4 | CP53: 0 | CQ53: 0 | CR53: 4 | CS53: 16.68 | CT53: 36 | CU53: 200 | CV53: 0 | CW53: 0.11684592 | CX53: 299 | CY53: 834 | DB53: =IF(DA53="","",1-(DA53/Main!$G53)) | DD53: =IF(DC53="","",1-(DC53/Main!$G53)) | DF53: =IF(DE53="","",1-(DE53/Main!$G53)) | DH53: =IF(DG53="","",1-(DG53/Main!$G53))
A54: Accessories | B54: Gifts | C54: WAX LYRICAL LTD CEN | D54: 103778 | E54: WR0102 REED DIFFUSER 200ML WOODLAND | F54: 0 | G54: 32 | T54: 0 | U54: 4 | V54: 0 | W54: 0 | X54: 4 | Y54: 53.32 | CT54: 0 | CU54: 4 | CV54: 0 | CW54: 0 | CX54: 4 | CY54: 53.32 | DB54: =IF(DA54="","",1-(DA54/Main!$G54)) | DD54: =IF(DC54="","",1-(DC54/Main!$G54)) | DF54: =IF(DE54="","",1-(DE54/Main!$G54)) | DH54: =IF(DG54="","",1-(DG54/Main!$G54))
A55: Accessories | B55: Gifts | C55: WAX LYRICAL LTD CEN | D55: 103779 | E55: WR0103 REED DIFFUSER 200ML MEADOW | F55: 0 | G55: 32 | T55: 0 | U55: 4 | V55: 0 | W55: 0 | X55: 4 | Y55: 53.32 | CT55: 0 | CU55: 4 | CV55: 0 | CW55: 0 | CX55: 4 | CY55: 53.32 | DB55: =IF(DA55="","",1-(DA55/Main!$G55)) | DD55: =IF(DC55="","",1-(DC55/Main!$G55)) | DF55: =IF(DE55="","",1-(DE55/Main!$G55)) | DH55: =IF(DG55="","",1-(DG55/Main!$G55))
A56: Accessories | B56: Gifts | C56: WAX LYRICAL LTD CEN | D56: 103780 | E56: WR0401 MINI SET/2 HEDGEROW | F56: 0 | G56: 21 | T56: 0 | U56: 6 | V56: 0 | W56: 0 | X56: 6 | Y56: 52.5 | CT56: 0 | CU56: 6 | CV56: 0 | CW56: 0 | CX56: 6 | CY56: 52.5 | DB56: =IF(DA56="","",1-(DA56/Main!$G56)) | DD56: =IF(DC56="","",1-(DC56/Main!$G56)) | DF56: =IF(DE56="","",1-(DE56/Main!$G56)) | DH56: =IF(DG56="","",1-(DG56/Main!$G56))
A57: Accessories | B57: Gifts | C57: WAX LYRICAL LTD CEN | D57: 103781 | E57: WR0402 MINI SET/2 WOODLAND | F57: 0 | G57: 21 | T57: 0 | U57: 6 | V57: 0 | W57: 0 | X57: 6 | Y57: 52.5 | CT57: 0 | CU57: 6 | CV57: 0 | CW57: 0 | CX57: 6 | CY57: 52.5 | DB57: =IF(DA57="","",1-(DA57/Main!$G57)) | DD57: =IF(DC57="","",1-(DC57/Main!$G57)) | DF57: =IF(DE57="","",1-(DE57/Main!$G57)) | DH57: =IF(DG57="","",1-(DG57/Main!$G57))
A58: Accessories | B58: Gifts | C58: WAX LYRICAL LTD CEN | D58: 103782 | E58: WR0301 W/F TRINKET HEDGEROW | F58: 0 | G58: 25 | T58: 0 | U58: 4 | V58: 0 | W58: 0 | X58: 4 | Y58: 41.68 | CT58: 0 | CU58: 4 | CV58: 0 | CW58: 0 | CX58: 4 | CY58: 41.68 | DB58: =IF(DA58="","",1-(DA58/Main!$G58)) | DD58: =IF(DC58="","",1-(DC58/Main!$G58)) | DF58: =IF(DE58="","",1-(DE58/Main!$G58)) | DH58: =IF(DG58="","",1-(DG58/Main!$G58))
A59: Accessories | B59: Gifts | C59: WAX LYRICAL LTD CEN | D59: 103783 | E59: WR0302 W/F TRINKET WOODLAND | F59: 0 | G59: 25 | T59: 0 | U59: 4 | V59: 0 | W59: 0 | X59: 4 | Y59: 41.68 | CT59: 0 | CU59: 4 | CV59: 0 | CW59: 0 | CX59: 4 | CY59: 41.68 | DB59: =IF(DA59="","",1-(DA59/Main!$G59)) | DD59: =IF(DC59="","",1-(DC59/Main!$G59)) | DF59: =IF(DE59="","",1-(DE59/Main!$G59)) | DH59: =IF(DG59="","",1-(DG59/Main!$G59))
A60: Accessories | B60: Handbags | C60: DK BAGS LTD | D60: 105957 | E60: SS22 727 | F60: Asstd | G60: 35 | H60: 0 | I60: -1 | J60: 4 | K60: 0 | L60: 12 | M60: -6 | N60: 0 | O60: 4 | P60: 0 | Q60: 0 | R60: 4 | S60: 24 | T60: 0 | U60: 4 | V60: 1 | W60: 0 | X60: 5 | Y60: 24 | Z60: 0 | AA60: 0 | AB60: 4 | AC60: 0 | AD60: 4 | AE60: 0 | AF60: 0 | AG60: 4 | AH60: 0 | AI60: 0 | AJ60: 4 | AK60: 24 | AL60: 0 | AM60: 4 | AN60: 0 | AO60: 0 | AP60: 4 | AQ60: 24 | AR60: 0 | AS60: 0 | AT60: 4 | AU60: 0 | AV60: 4 | AW60: 0 | AX60: 0 | AY60: 4 | AZ60: 0 | BA60: 0 | BB60: 4 | BC60: 24 | BD60: 0 | BE60: 2 | BF60: 0 | BG60: 0 | BH60: 4 | BI60: 12 | BJ60: 0 | BK60: 3 | BL60: 0 | BM60: 0 | BN60: 12 | BO60: 18 | BP60: 0 | BQ60: 4 | BR60: 0 | BS60: 0 | BT60: 4 | BU60: 24 | BV60: 0 | BW60: 4 | BX60: 0 | BY60: 0 | BZ60: 4 | CA60: 24 | CB60: 0 | CC60: 4 | CD60: 0 | CE60: 0 | CF60: 4 | CG60: 24 | CT60: 0 | CU60: 36 | CV60: 13 | CW60: 0 | CX60: 69 | CY60: 216 | DB60: =IF(DA60="","",1-(DA60/Main!$G60)) | DD60: =IF(DC60="","",1-(DC60/Main!$G60)) | DF60: =IF(DE60="","",1-(DE60/Main!$G60)) | DH60: =IF(DG60="","",1-(DG60/Main!$G60))
A61: Accessories | B61: Handbags | C61: DK BAGS LTD | D61: 105958 | E61: SS22 720 | F61: Asstd | G61: 35 | H61: 0 | I61: 0 | J61: 2 | K61: 0 | L61: 2 | M61: 0 | N61: 0 | O61: 2 | P61: 0 | Q61: 0 | R61: 2 | S61: 12 | T61: 0 | U61: 4 | V61: 4 | W61: 0 | X61: 8 | Y61: 24 | Z61: 0 | AA61: 0 | AB61: 2 | AC61: 0 | AD61: 2 | AE61: 0 | AF61: 0 | AG61: 2 | AH61: 0 | AI61: 0 | AJ61: 2 | AK61: 12 | AL61: 0 | AM61: 2 | AN61: 0 | AO61: 0 | AP61: 2 | AQ61: 12 | AR61: 0 | AS61: 0 | AT61: 2 | AU61: 0 | AV61: 2 | AW61: 0 | AX61: 0 | AY61: 2 | AZ61: 0 | BA61: 0 | BB61: 2 | BC61: 12 | BD61: 0 | BE61: 0 | BF61: 2 | BG61: 0 | BH61: 2 | BI61: 0 | BJ61: 0 | BK61: 2 | BL61: 0 | BM61: 0 | BN61: 8 | BO61: 12 | BP61: 0 | BQ61: 3 | BR61: 1 | BS61: 0 | BT61: 4 | BU61: 18 | BV61: 0 | BW61: 2 | BX61: 0 | BY61: 0 | BZ61: 2 | CA61: 12 | CB61: 0 | CC61: 5 | CD61: 3 | CE61: 0 | CF61: 8 | CG61: 30 | CT61: 0 | CU61: 24 | CV61: 16 | CW61: 0 | CX61: 46 | CY61: 144 | DB61: =IF(DA61="","",1-(DA61/Main!$G61)) | DD61: =IF(DC61="","",1-(DC61/Main!$G61)) | DF61: =IF(DE61="","",1-(DE61/Main!$G61)) | DH61: =IF(DG61="","",1-(DG61/Main!$G61))
A62: Accessories | B62: Handbags | C62: DK BAGS LTD | D62: 105959 | E62: SS22 721 | F62: Asstd | G62: 35 | H62: 0 | I62: 0 | J62: 2 | K62: 0 | L62: 2 | M62: 0 | N62: 0 | O62: 2 | P62: 0 | Q62: 0 | R62: 2 | S62: 12 | T62: 0 | U62: 2 | V62: 0 | W62: 0 | X62: 2 | Y62: 12 | Z62: 0 | AA62: 0 | AB62: 2 | AC62: 0 | AD62: 2 | AE62: 0 | AF62: 0 | AG62: 2 | AH62: 0 | AI62: 0 | AJ62: 2 | AK62: 12 | AL62: 0 | AM62: 1 | AN62: 0 | AO62: 0 | AP62: 4 | AQ62: 6 | AR62: 0 | AS62: -1 | AT62: 2 | AU62: 0 | AV62: 4 | AW62: -6 | AX62: 0 | AY62: 1 | AZ62: 0 | BA62: 0 | BB62: 4 | BC62: 6 | BD62: 0 | BE62: 0 | BF62: 2 | BG62: 0 | BH62: 2 | BI62: 0 | BJ62: 0 | BK62: 2 | BL62: 0 | BM62: 0 | BN62: 2 | BO62: 12 | BP62: 0 | BQ62: 2 | BR62: 0 | BS62: 0 | BT62: 2 | BU62: 12 | BV62: 0 | BW62: 2 | BX62: 0 | BY62: 0 | BZ62: 2 | CA62: 12 | CB62: 0 | CC62: 2 | CD62: 0 | CE62: 0 | CF62: 2 | CG62: 12 | CT62: 0 | CU62: 15 | CV62: 8 | CW62: 0 | CX62: 32 | CY62: 90 | DB62: =IF(DA62="","",1-(DA62/Main!$G62)) | DD62: =IF(DC62="","",1-(DC62/Main!$G62)) | DF62: =IF(DE62="","",1-(DE62/Main!$G62)) | DH62: =IF(DG62="","",1-(DG62/Main!$G62))
A63: Accessories | B63: Handbags | C63: DK BAGS LTD | D63: 105960 | E63: SS22 678 | F63: Asstd | G63: 35 | H63: 0 | I63: -1 | J63: 2 | K63: 0 | L63: 4 | M63: -6 | N63: 0 | O63: 2 | P63: 0 | Q63: 0 | R63: 2 | S63: 12 | T63: 0 | U63: 2 | V63: 1 | W63: 0 | X63: 3 | Y63: 12 | Z63: 0 | AA63: 0 | AB63: 2 | AC63: 0 | AD63: 2 | AE63: 0 | AF63: 0 | AG63: 2 | AH63: 0 | AI63: 0 | AJ63: 2 | AK63: 12 | AL63: 0 | AM63: 1 | AN63: 0 | AO63: 0 | AP63: 4 | AQ63: 6 | AR63: 0 | AS63: 0 | AT63: 2 | AU63: 0 | AV63: 2 | AW63: 0 | AX63: 0 | AY63: 0 | AZ63: 1 | BA63: 0 | BB63: 4 | BC63: 0 | BD63: 0 | BE63: 2 | BF63: 0 | BG63: 0 | BH63: 2 | BI63: 12 | BJ63: 0 | BK63: 2 | BL63: 0 | BM63: 0 | BN63: 2 | BO63: 12 | BP63: 0 | BQ63: 1 | BR63: 0 | BS63: 0 | BT63: 4 | BU63: 6 | BV63: 0 | BW63: 2 | BX63: 0 | BY63: 0 | BZ63: 2 | CA63: 12 | CB63: 0 | CC63: 5 | CD63: 4 | CE63: 0 | CF63: 36 | CG63: 30 | CT63: 0 | CU63: 18 | CV63: 12 | CW63: 0 | CX63: 69 | CY63: 108 | DB63: =IF(DA63="","",1-(DA63/Main!$G63)) | DD63: =IF(DC63="","",1-(DC63/Main!$G63)) | DF63: =IF(DE63="","",1-(DE63/Main!$G63)) | DH63: =IF(DG63="","",1-(DG63/Main!$G63))
A64: Accessories | B64: Handbags | C64: DK BAGS LTD | D64: 105961 | E64: SS22 701 | F64: Asstd | G64: 35 | H64: 0 | I64: 0 | J64: 3 | K64: 0 | L64: 3 | M64: 0 | N64: 0 | O64: 3 | P64: 0 | Q64: 0 | R64: 3 | S64: 18 | T64: 0 | U64: 4 | V64: 1 | W64: 0 | X64: 5 | Y64: 24 | Z64: 0 | AA64: 0 | AB64: 3 | AC64: 0 | AD64: 3 | AE64: 0 | AF64: 0 | AG64: 3 | AH64: 1 | AI64: 0 | AJ64: 16 | AK64: 18 | AL64: 0 | AM64: 6 | AN64: 1 | AO64: 0 | AP64: 7 | AQ64: 36 | AR64: 0 | AS64: 0 | AT64: 3 | AU64: 0 | AV64: 3 | AW64: 0 | AX64: 0 | AY64: 2 | AZ64: 0 | BA64: 0 | BB64: 8 | BC64: 12 | BD64: 0 | BE64: 3 | BF64: 0 | BG64: 0 | BH64: 3 | BI64: 18 | BJ64: 0 | BK64: 5 | BL64: 0 | BM64: 0 | BN64: 20 | BO64: 30 | BP64: 0 | BQ64: 3 | BR64: 0 | BS64: 0 | BT64: 3 | BU64: 18 | BV64: 0 | BW64: 2 | BX64: 1 | BY64: 0 | BZ64: 3 | CA64: 12 | CB64: 0 | CC64: 3 | CD64: 0 | CE64: 0 | CF64: 3 | CG64: 18 | CT64: 0 | CU64: 34 | CV64: 13 | CW64: 0 | CX64: 80 | CY64: 204 | DB64: =IF(DA64="","",1-(DA64/Main!$G64)) | DD64: =IF(DC64="","",1-(DC64/Main!$G64)) | DF64: =IF(DE64="","",1-(DE64/Main!$G64)) | DH64: =IF(DG64="","",1-(DG64/Main!$G64))
A65: Accessories | B65: Handbags | C65: DK BAGS LTD | D65: 105962 | E65: SS22 719 | F65: Asstd | G65: 35 | H65: 0 | I65: 0 | J65: 1 | K65: 0 | L65: 1 | M65: 0 | N65: 0 | O65: 1 | P65: 0 | Q65: 0 | R65: 1 | S65: 6 | T65: 0 | U65: 0 | V65: 1 | W65: 0 | X65: 1 | Y65: 0 | Z65: 0 | AA65: 0 | AB65: 1 | AC65: 0 | AD65: 1 | AE65: 0 | AF65: 0 | AG65: 1 | AH65: 0 | AI65: 0 | AJ65: 1 | AK65: 6 | AL65: 0 | AM65: 1 | AN65: 0 | AO65: 0 | AP65: 1 | AQ65: 6 | AR65: 0 | AS65: 0 | AT65: 1 | AU65: 0 | AV65: 1 | AW65: 0 | BD65: 0 | BE65: 0 | BF65: 1 | BG65: 0 | BH65: 1 | BI65: 0 | BP65: 0 | BQ65: 0 | BR65: 1 | BS65: 0 | BT65: 1 | BU65: 0 | BV65: 0 | BW65: 1 | BX65: 0 | BY65: 0 | BZ65: 1 | CA65: 6 | CT65: 0 | CU65: 4 | CV65: 6 | CW65: 0 | CX65: 10 | CY65: 24 | DB65: =IF(DA65="","",1-(DA65/Main!$G65)) | DD65: =IF(DC65="","",1-(DC65/Main!$G65)) | DF65: =IF(DE65="","",1-(DE65/Main!$G65)) | DH65: =IF(DG65="","",1-(DG65/Main!$G65))
A66: Accessories | B66: Handbags | C66: DK BAGS LTD | D66: 105963 | E66: SS22 656 | F66: Asstd | G66: 35 | H66: 0 | I66: 0 | J66: 2 | K66: 0 | L66: 2 | M66: 0 | N66: 0 | O66: 2 | P66: 0 | Q66: 0 | R66: 2 | S66: 12 | T66: 0 | U66: 0 | V66: 2 | W66: 0 | X66: 2 | Y66: 0 | Z66: 0 | AA66: 0 | AB66: 2 | AC66: 0 | AD66: 2 | AE66: 0 | AF66: 0 | AG66: 2 | AH66: 0 | AI66: 0 | AJ66: 2 | AK66: 12 | AL66: 0 | AM66: 2 | AN66: 0 | AO66: 0 | AP66: 2 | AQ66: 12 | AR66: 0 | AS66: 0 | AT66: 2 | AU66: 0 | AV66: 2 | AW66: 0 | AX66: 0 | AY66: 2 | AZ66: 0 | BA66: 0 | BB66: 2 | BC66: 12 | BD66: 0 | BE66: 2 | BF66: 0 | BG66: 0 | BH66: 2 | BI66: 12 | BJ66: 0 | BK66: 1 | BL66: 0 | BM66: 0 | BN66: 1 | BO66: 6 | BP66: 0 | BQ66: 0 | BR66: 2 | BS66: 0 | BT66: 2 | BU66: 0 | BV66: 0 | BW66: 2 | BX66: 0 | BY66: 0 | BZ66: 2 | CA66: 12 | CT66: 0 | CU66: 13 | CV66: 10 | CW66: 0 | CX66: 23 | CY66: 78 | DB66: =IF(DA66="","",1-(DA66/Main!$G66)) | DD66: =IF(DC66="","",1-(DC66/Main!$G66)) | DF66: =IF(DE66="","",1-(DE66/Main!$G66)) | DH66: =IF(DG66="","",1-(DG66/Main!$G66))
A67: Accessories | B67: Handbags | C67: DK BAGS LTD | D67: 105964 | E67: SS22 648 | F67: Asstd | G67: 35 | H67: 0 | I67: 0 | J67: 6 | K67: 0 | L67: 6 | M67: 0 | N67: 0 | O67: 6 | P67: 1 | Q67: 0 | R67: 28 | S67: 36 | T67: 0 | U67: 5 | V67: 0 | W67: 0 | X67: 20 | Y67: 30 | Z67: 0 | AA67: 0 | AB67: 6 | AC67: 0 | AD67: 6 | AE67: 0 | AF67: 0 | AG67: 8 | AH67: 2 | AI67: 0 | AJ67: 10 | AK67: 48 | AL67: 0 | AM67: 8 | AN67: 2 | AO67: 0 | AP67: 10 | AQ67: 48 | AR67: 0 | AS67: 0 | AT67: 6 | AU67: 0 | AV67: 6 | AW67: 0 | AX67: 0 | AY67: 5 | AZ67: 0 | BA67: 0 | BB67: 20 | BC67: 30 | BD67: 0 | BE67: 6 | BF67: 0 | BG67: 0 | BH67: 6 | BI67: 36 | BJ67: 0 | BK67: 8 | BL67: 0 | BM67: 0 | BN67: 8 | BO67: 48 | BP67: 0 | BQ67: 12 | BR67: 6 | BS67: 0 | BT67: 18 | BU67: 72 | BV67: 0 | BW67: 7 | BX67: 1 | BY67: 0 | BZ67: 8 | CA67: 42 | CB67: 0 | CC67: 12 | CD67: 6 | CE67: 0 | CF67: 18 | CG67: 72 | CT67: 0 | CU67: 77 | CV67: 36 | CW67: 0 | CX67: 164 | CY67: 462 | DB67: =IF(DA67="","",1-(DA67/Main!$G67)) | DD67: =IF(DC67="","",1-(DC67/Main!$G67)) | DF67: =IF(DE67="","",1-(DE67/Main!$G67)) | DH67: =IF(DG67="","",1-(DG67/Main!$G67))
A68: Accessories | B68: Handbags | C68: DK BAGS LTD | D68: 105965 | E68: SS22 649 | F68: Asstd | G68: 35 | H68: 0 | I68: 0 | J68: 6 | K68: 0 | L68: 6 | M68: 0 | N68: 0 | O68: 6 | P68: 0 | Q68: 0 | R68: 6 | S68: 36 | T68: 0 | U68: 6 | V68: 0 | W68: 0 | X68: 6 | Y68: 36 | Z68: 0 | AA68: 0 | AB68: 6 | AC68: 0 | AD68: 6 | AE68: 0 | AF68: 0 | AG68: 6 | AH68: 0 | AI68: 0 | AJ68: 6 | AK68: 36 | AL68: 0 | AM68: 6 | AN68: 0 | AO68: 0 | AP68: 6 | AQ68: 36 | AR68: 0 | AS68: 0 | AT68: 6 | AU68: 0 | AV68: 6 | AW68: 0 | AX68: 0 | AY68: 6 | AZ68: 0 | BA68: 0 | BB68: 6 | BC68: 36 | BD68: 0 | BE68: 6 | BF68: 0 | BG68: 0 | BH68: 6 | BI68: 36 | BJ68: 0 | BK68: 6 | BL68: 0 | BM68: 0 | BN68: 6 | BO68: 36 | BP68: 0 | BQ68: 6 | BR68: 0 | BS68: 0 | BT68: 6 | BU68: 36 | BV68: 0 | BW68: 6 | BX68: 0 | BY68: 0 | BZ68: 6 | CA68: 36 | CB68: 0 | CC68: 5 | CD68: 0 | CE68: 0 | CF68: 20 | CG68: 30 | CT68: 0 | CU68: 59 | CV68: 18 | CW68: 0 | CX68: 92 | CY68: 354 | DB68: =IF(DA68="","",1-(DA68/Main!$G68)) | DD68: =IF(DC68="","",1-(DC68/Main!$G68)) | DF68: =IF(DE68="","",1-(DE68/Main!$G68)) | DH68: =IF(DG68="","",1-(DG68/Main!$G68))
A69: Accessories | B69: Handbags | C69: DK BAGS LTD | D69: 105966 | E69: SS22 667 | F69: Asstd | G69: 35 | H69: 0 | I69: 0 | J69: 3 | K69: 0 | L69: 3 | M69: 0 | N69: 0 | O69: 3 | P69: 0 | Q69: 0 | R69: 3 | S69: 18 | T69: 0 | U69: 3 | V69: 0 | W69: 0 | X69: 3 | Y69: 18 | Z69: 0 | AA69: 0 | AB69: 3 | AC69: 0 | AD69: 3 | AE69: 0 | AF69: 0 | AG69: 3 | AH69: 0 | AI69: 0 | AJ69: 3 | AK69: 18 | AL69: 0 | AM69: 3 | AN69: 0 | AO69: 0 | AP69: 3 | AQ69: 18 | AR69: 0 | AS69: 0 | AT69: 3 | AU69: 0 | AV69: 3 | AW69: 0 | AX69: 0 | AY69: 1 | AZ69: 0 | BA69: 0 | BB69: 2 | BC69: 6 | BD69: 0 | BE69: 2 | BF69: 0 | BG69: 0 | BH69: 8 | BI69: 12 | BJ69: 0 | BK69: 3 | BL69: 0 | BM69: 0 | BN69: 3 | BO69: 18 | BP69: 0 | BQ69: 3 | BR69: 0 | BS69: 0 | BT69: 3 | BU69: 18 | BV69: 0 | BW69: 2 | BX69: 0 | BY69: 0 | BZ69: 8 | CA69: 12 | CB69: 0 | CC69: 3 | CD69: 0 | CE69: 0 | CF69: 3 | CG69: 18 | CT69: 0 | CU69: 26 | CV69: 9 | CW69: 0 | CX69: 48 | CY69: 156 | DB69: =IF(DA69="","",1-(DA69/Main!$G69)) | DD69: =IF(DC69="","",1-(DC69/Main!$G69)) | DF69: =IF(DE69="","",1-(DE69/Main!$G69)) | DH69: =IF(DG69="","",1-(DG69/Main!$G69))
A70: Accessories | B70: Handbags | C70: DK BAGS LTD | D70: 105967 | E70: SS22 661 | F70: Asstd | G70: 35 | H70: 0 | I70: 0 | J70: 10 | K70: 0 | L70: 10 | M70: 0 | N70: 0 | O70: 10 | P70: 0 | Q70: 0 | R70: 10 | S70: 60 | T70: 0 | U70: 5 | V70: 5 | W70: 0 | X70: 10 | Y70: 30 | Z70: 0 | AA70: -1 | AB70: 10 | AC70: 0 | AD70: 36 | AE70: -6 | AF70: 0 | AG70: 9 | AH70: 0 | AI70: 0 | AJ70: 36 | AK70: 54 | AL70: 0 | AM70: 9 | AN70: 0 | AO70: 0 | AP70: 9 | AQ70: 54 | AR70: 0 | AS70: -2 | AT70: 10 | AU70: 0 | AV70: 16 | AW70: -12 | AX70: 0 | AY70: 8 | AZ70: 0 | BA70: 0 | BB70: 16 | BC70: 48 | BD70: 0 | BE70: 9 | BF70: 0 | BG70: 0 | BH70: 36 | BI70: 54 | BJ70: 0 | BK70: 7 | BL70: 0 | BM70: 0 | BN70: 7 | BO70: 42 | BP70: 0 | BQ70: 7 | BR70: 2 | BS70: 0 | BT70: 36 | BU70: 42 | BV70: 0 | BW70: 7 | BX70: 1 | BY70: 0 | BZ70: 16 | CA70: 42 | CB70: 0 | CC70: 3 | CD70: 0 | CE70: 0 | CF70: 12 | CG70: 18 | CT70: 0 | CU70: 71 | CV70: 38 | CW70: 0 | CX70: 250 | CY70: 426 | DB70: =IF(DA70="","",1-(DA70/Main!$G70)) | DD70: =IF(DC70="","",1-(DC70/Main!$G70)) | DF70: =IF(DE70="","",1-(DE70/Main!$G70)) | DH70: =IF(DG70="","",1-(DG70/Main!$G70))
A71: Accessories | B71: Handbags | C71: DK BAGS LTD | D71: 105968 | E71: SS22 662 | F71: Asstd | G71: 35 | H71: 0 | I71: 0 | J71: 6 | K71: 0 | L71: 6 | M71: 0 | N71: 0 | O71: 6 | P71: 0 | Q71: 0 | R71: 6 | S71: 36 | T71: 0 | U71: 0 | V71: 6 | W71: 0 | X71: 6 | Y71: 0 | Z71: 0 | AA71: 0 | AB71: 6 | AC71: 0 | AD71: 6 | AE71: 0 | AF71: 0 | AG71: 5 | AH71: 0 | AI71: 0 | AJ71: 20 | AK71: 30 | AL71: 0 | AM71: 5 | AN71: 0 | AO71: 0 | AP71: 5 | AQ71: 30 | AR71: 0 | AS71: -2 | AT71: 6 | AU71: 0 | AV71: 8 | AW71: -12 | AX71: 0 | AY71: 5 | AZ71: 1 | BA71: 0 | BB71: 6 | BC71: 30 | BD71: 0 | BE71: 6 | BF71: 0 | BG71: 0 | BH71: 6 | BI71: 36 | BJ71: 0 | BK71: 2 | BL71: 0 | BM71: 0 | BN71: 8 | BO71: 12 | BP71: 0 | BQ71: 1 | BR71: 5 | BS71: 0 | BT71: 6 | BU71: 6 | BV71: 0 | BW71: 6 | BX71: 0 | BY71: 0 | BZ71: 6 | CA71: 36 | CB71: 0 | CC71: 2 | CD71: 0 | CE71: 0 | CF71: 2 | CG71: 12 | CT71: 0 | CU71: 36 | CV71: 30 | CW71: 0 | CX71: 91 | CY71: 216 | DB71: =IF(DA71="","",1-(DA71/Main!$G71)) | DD71: =IF(DC71="","",1-(DC71/Main!$G71)) | DF71: =IF(DE71="","",1-(DE71/Main!$G71)) | DH71: =IF(DG71="","",1-(DG71/Main!$G71))
A72: Accessories | B72: Handbags | C72: DK BAGS LTD | D72: 105969 | E72: SS22 575 | F72: Asstd | G72: 35 | H72: 0 | I72: 0 | J72: 4 | K72: 0 | L72: 4 | M72: 0 | N72: 0 | O72: 3 | P72: 0 | Q72: 0 | R72: 12 | S72: 18 | T72: 0 | U72: 0 | V72: 4 | W72: 0 | X72: 4 | Y72: 0 | Z72: 0 | AA72: 0 | AB72: 4 | AC72: 0 | AD72: 4 | AE72: 0 | AF72: 0 | AG72: 2 | AH72: 0 | AI72: 0 | AJ72: 8 | AK72: 12 | AL72: 0 | AM72: 3 | AN72: 0 | AO72: 0 | AP72: 12 | AQ72: 18 | AR72: 0 | AS72: 0 | AT72: 4 | AU72: 0 | AV72: 4 | AW72: 0 | AX72: 0 | AY72: 2 | AZ72: 1 | BA72: 0 | BB72: 12 | BC72: 12 | BD72: 0 | BE72: 0 | BF72: 4 | BG72: 0 | BH72: 4 | BI72: 0 | BP72: 0 | BQ72: 1 | BR72: 3 | BS72: 0 | BT72: 4 | BU72: 6 | BV72: 0 | BW72: 5 | BX72: 1 | BY72: 0 | BZ72: 6 | CA72: 30 | CT72: 0 | CU72: 16 | CV72: 25 | CW72: 0 | CX72: 74 | CY72: 96 | DB72: =IF(DA72="","",1-(DA72/Main!$G72)) | DD72: =IF(DC72="","",1-(DC72/Main!$G72)) | DF72: =IF(DE72="","",1-(DE72/Main!$G72)) | DH72: =IF(DG72="","",1-(DG72/Main!$G72))
A73: Accessories | B73: Handbags | C73: DK BAGS LTD | D73: 105970 | E73: SS22 650 | F73: Asstd | G73: 35 | H73: 0 | I73: 0 | J73: 4 | K73: 0 | L73: 4 | M73: 0 | N73: 0 | O73: 4 | P73: 0 | Q73: 0 | R73: 4 | S73: 24 | T73: 0 | U73: 2 | V73: 1 | W73: 0 | X73: 12 | Y73: 12 | Z73: 0 | AA73: -1 | AB73: 4 | AC73: 0 | AD73: 12 | AE73: -6 | AF73: 0 | AG73: 5 | AH73: 1 | AI73: 0 | AJ73: 6 | AK73: 30 | AL73: 0 | AM73: 3 | AN73: 0 | AO73: 0 | AP73: 3 | AQ73: 18 | AR73: 0 | AS73: 0 | AT73: 4 | AU73: 0 | AV73: 4 | AW73: 0 | AX73: 0 | AY73: 3 | AZ73: 1 | BA73: 0 | BB73: 4 | BC73: 18 | BD73: 0 | BE73: 4 | BF73: 0 | BG73: 0 | BH73: 4 | BI73: 24 | BJ73: 0 | BK73: 3 | BL73: 0 | BM73: 0 | BN73: 3 | BO73: 18 | BP73: 0 | BQ73: 3 | BR73: 1 | BS73: 0 | BT73: 4 | BU73: 18 | BV73: 0 | BW73: 4 | BX73: 0 | BY73: 0 | BZ73: 4 | CA73: 24 | CB73: 0 | CC73: 3 | CD73: 0 | CE73: 0 | CF73: 3 | CG73: 18 | CT73: 0 | CU73: 33 | CV73: 16 | CW73: 0 | CX73: 67 | CY73: 198 | DB73: =IF(DA73="","",1-(DA73/Main!$G73)) | DD73: =IF(DC73="","",1-(DC73/Main!$G73)) | DF73: =IF(DE73="","",1-(DE73/Main!$G73)) | DH73: =IF(DG73="","",1-(DG73/Main!$G73))
A74: Accessories | B74: Handbags | C74: DK BAGS LTD | D74: 105971 | E74: SS22 632 | F74: Asstd | G74: 35 | H74: 0 | I74: -2 | J74: 4 | K74: 0 | L74: 4 | M74: -12 | N74: 0 | O74: 4 | P74: 0 | Q74: 0 | R74: 4 | S74: 24 | T74: 0 | U74: 4 | V74: 5 | W74: 0 | X74: 36 | Y74: 24 | Z74: 0 | AA74: 0 | AB74: 4 | AC74: 0 | AD74: 4 | AE74: 0 | AF74: 0 | AG74: 4 | AH74: 0 | AI74: 0 | AJ74: 4 | AK74: 24 | AL74: 0 | AM74: 4 | AN74: 0 | AO74: 0 | AP74: 4 | AQ74: 24 | AR74: 0 | AS74: 0 | AT74: 4 | AU74: 0 | AV74: 4 | AW74: 0 | AX74: 0 | AY74: 2 | AZ74: 0 | BA74: 0 | BB74: 4 | BC74: 12 | BD74: 0 | BE74: 4 | BF74: 0 | BG74: 0 | BH74: 4 | BI74: 24 | BJ74: 0 | BK74: 5 | BL74: 0 | BM74: 0 | BN74: 7 | BO74: 30 | BP74: 0 | BQ74: 4 | BR74: 0 | BS74: 0 | BT74: 4 | BU74: 24 | BV74: 0 | BW74: 4 | BX74: 0 | BY74: 0 | BZ74: 4 | CA74: 24 | CB74: 0 | CC74: 6 | CD74: 5 | CE74: 0 | CF74: 15 | CG74: 36 | CT74: 0 | CU74: 39 | CV74: 22 | CW74: 0 | CX74: 98 | CY74: 234 | DB74: =IF(DA74="","",1-(DA74/Main!$G74)) | DD74: =IF(DC74="","",1-(DC74/Main!$G74)) | DF74: =IF(DE74="","",1-(DE74/Main!$G74)) | DH74: =IF(DG74="","",1-(DG74/Main!$G74))
A75: Accessories | B75: Handbags | C75: DK BAGS LTD | D75: 105972 | E75: SS22 652 | F75: Asstd | G75: 35 | H75: 0 | I75: 0 | J75: 2 | K75: 0 | L75: 2 | M75: 0 | N75: 0 | O75: 3 | P75: 1 | Q75: 0 | R75: 4 | S75: 18 | Z75: 0 | AA75: 0 | AB75: 2 | AC75: 0 | AD75: 2 | AE75: 0 | AF75: 0 | AG75: 2 | AH75: 0 | AI75: 0 | AJ75: 2 | AK75: 12 | AL75: 0 | AM75: 1 | AN75: 0 | AO75: 0 | AP75: 2 | AQ75: 6 | AR75: 0 | AS75: 0 | AT75: 2 | AU75: 0 | AV75: 2 | AW75: 0 | AX75: 0 | AY75: 2 | AZ75: 1 | BA75: 0 | BB75: 12 | BC75: 12 | BD75: 0 | BE75: -1 | BF75: 2 | BG75: 0 | BH75: 4 | BI75: -6 | BJ75: 0 | BK75: 4 | BL75: 1 | BM75: 0 | BN75: 5 | BO75: 24 | BP75: 0 | BQ75: 2 | BR75: 0 | BS75: 0 | BT75: 2 | BU75: 12 | BV75: 0 | BW75: 2 | BX75: 0 | BY75: 0 | BZ75: 2 | CA75: 12 | CB75: 0 | CC75: 1 | CD75: 1 | CE75: 0 | CF75: 4 | CG75: 6 | CT75: 0 | CU75: 16 | CV75: 12 | CW75: 0 | CX75: 43 | CY75: 96 | DB75: =IF(DA75="","",1-(DA75/Main!$G75)) | DD75: =IF(DC75="","",1-(DC75/Main!$G75)) | DF75: =IF(DE75="","",1-(DE75/Main!$G75)) | DH75: =IF(DG75="","",1-(DG75/Main!$G75))
A76: Accessories | B76: Handbags | C76: DK BAGS LTD | D76: 105973 | E76: SS22 674 | F76: Asstd | G76: 35 | H76: 0 | I76: 0 | J76: 12 | K76: 0 | L76: 12 | M76: 0 | N76: 0 | O76: 12 | P76: 0 | Q76: 0 | R76: 12 | S76: 72 | T76: 0 | U76: 12 | V76: 0 | W76: 0 | X76: 12 | Y76: 72 | Z76: 0 | AA76: 0 | AB76: 12 | AC76: 0 | AD76: 12 | AE76: 0 | AF76: 0 | AG76: 12 | AH76: 0 | AI76: 0 | AJ76: 12 | AK76: 72 | AL76: 0 | AM76: 12 | AN76: 0 | AO76: 0 | AP76: 24 | AQ76: 72 | AR76: 0 | AS76: -2 | AT76: 12 | AU76: 0 | AV76: 20 | AW76: -12 | AX76: 0 | AY76: 11 | AZ76: 0 | BA76: 0 | BB76: 44 | BC76: 66 | BD76: 0 | BE76: 11 | BF76: 0 | BG76: 0 | BH76: 44 | BI76: 66 | BJ76: 0 | BK76: 11 | BL76: 0 | BM76: 0 | BN76: 44 | BO76: 66 | BP76: 0 | BQ76: 11 | BR76: 0 | BS76: 0 | BT76: 44 | BU76: 66 | BV76: 0 | BW76: 10 | BX76: 0 | BY76: 0 | BZ76: 20 | CA76: 60 | CB76: 0 | CC76: 12 | CD76: 0 | CE76: 0 | CF76: 12 | CG76: 72 | CT76: 0 | CU76: 112 | CV76: 36 | CW76: 0 | CX76: 312 | CY76: 672 | DB76: =IF(DA76="","",1-(DA76/Main!$G76)) | DD76: =IF(DC76="","",1-(DC76/Main!$G76)) | DF76: =IF(DE76="","",1-(DE76/Main!$G76)) | DH76: =IF(DG76="","",1-(DG76/Main!$G76))
A77: Accessories | B77: Handbags | C77: DK BAGS LTD | D77: 105974 | E77: SS22 683 | F77: Asstd | G77: 35 | H77: 0 | I77: 0 | J77: 10 | K77: 0 | L77: 10 | M77: 0 | N77: 0 | O77: 8 | P77: 0 | Q77: 0 | R77: 16 | S77: 48 | T77: 0 | U77: 12 | V77: 6 | W77: 0 | X77: 18 | Y77: 72 | Z77: 0 | AA77: 0 | AB77: 10 | AC77: 0 | AD77: 10 | AE77: 0 | AF77: 0 | AG77: 10 | AH77: 0 | AI77: 0 | AJ77: 10 | AK77: 60 | AL77: 0 | AM77: 7 | AN77: 0 | AO77: 0 | AP77: 28 | AQ77: 42 | AR77: 0 | AS77: 0 | AT77: 10 | AU77: 0 | AV77: 10 | AW77: 0 | AX77: 0 | AY77: 10 | AZ77: 0 | BA77: 0 | BB77: 10 | BC77: 60 | BD77: 0 | BE77: 10 | BF77: 0 | BG77: 0 | BH77: 10 | BI77: 60 | BJ77: 0 | BK77: 13 | BL77: 0 | BM77: 0 | BN77: 13 | BO77: 78 | BP77: 0 | BQ77: 9 | BR77: 0 | BS77: 0 | BT77: 36 | BU77: 54 | BV77: 0 | BW77: 10 | BX77: 0 | BY77: 0 | BZ77: 10 | CA77: 60 | CB77: 0 | CC77: 10 | CD77: 0 | CE77: 0 | CF77: 10 | CG77: 60 | CT77: 0 | CU77: 99 | CV77: 36 | CW77: 0 | CX77: 191 | CY77: 594 | DB77: =IF(DA77="","",1-(DA77/Main!$G77)) | DD77: =IF(DC77="","",1-(DC77/Main!$G77)) | DF77: =IF(DE77="","",1-(DE77/Main!$G77)) | DH77: =IF(DG77="","",1-(DG77/Main!$G77))
A78: Accessories | B78: Handbags | C78: DK BAGS LTD | D78: 105975 | E78: SS22 684 | F78: Asstd | G78: 35 | H78: 0 | I78: 0 | J78: 12 | K78: 0 | L78: 12 | M78: 0 | N78: 0 | O78: 12 | P78: 0 | Q78: 0 | R78: 12 | S78: 72 | T78: 0 | U78: 6 | V78: 6 | W78: 0 | X78: 12 | Y78: 36 | Z78: 0 | AA78: 0 | AB78: 12 | AC78: 0 | AD78: 12 | AE78: 0 | AF78: 0 | AG78: 9 | AH78: 3 | AI78: 0 | AJ78: 12 | AK78: 54 | AL78: 0 | AM78: 10 | AN78: 0 | AO78: 0 | AP78: 10 | AQ78: 60 | AR78: 0 | AS78: -1 | AT78: 12 | AU78: 0 | AV78: 44 | AW78: -6 | AX78: 0 | AY78: 0 | AZ78: 12 | BA78: 0 | BB78: 12 | BC78: 0 | BD78: 0 | BE78: 11 | BF78: 0 | BG78: 0 | BH78: 44 | BI78: 66 | BJ78: 0 | BK78: 10 | BL78: 0 | BM78: 0 | BN78: 10 | BO78: 60 | BP78: 0 | BQ78: 6 | BR78: 5 | BS78: 0 | BT78: 44 | BU78: 36 | BV78: 0 | BW78: 12 | BX78: 0 | BY78: 0 | BZ78: 12 | CA78: 72 | CB78: 0 | CC78: 8 | CD78: 0 | CE78: 0 | CF78: 8 | CG78: 48 | CT78: 0 | CU78: 83 | CV78: 62 | CW78: 0 | CX78: 244 | CY78: 498 | DB78: =IF(DA78="","",1-(DA78/Main!$G78)) | DD78: =IF(DC78="","",1-(DC78/Main!$G78)) | DF78: =IF(DE78="","",1-(DE78/Main!$G78)) | DH78: =IF(DG78="","",1-(DG78/Main!$G78))
A79: Accessories | B79: Handbags | C79: DK BAGS LTD | D79: 105976 | E79: SS22 602 | F79: Asstd | G79: 35 | H79: 0 | I79: 0 | J79: 3 | K79: 0 | L79: 3 | M79: 0 | N79: 0 | O79: 3 | P79: 0 | Q79: 0 | R79: 3 | S79: 18 | T79: 0 | U79: 3 | V79: 2 | W79: 0 | X79: 5 | Y79: 18 | Z79: 0 | AA79: -1 | AB79: 3 | AC79: 0 | AD79: 8 | AE79: -6 | AF79: 0 | AG79: 3 | AH79: 0 | AI79: 0 | AJ79: 3 | AK79: 18 | AL79: 0 | AM79: 3 | AN79: 0 | AO79: 0 | AP79: 3 | AQ79: 18 | AR79: 0 | AS79: -1 | AT79: 3 | AU79: 0 | AV79: 8 | AW79: -6 | AX79: 0 | AY79: 3 | AZ79: 0 | BA79: 0 | BB79: 3 | BC79: 18 | BD79: 0 | BE79: 3 | BF79: 0 | BG79: 0 | BH79: 3 | BI79: 18 | BJ79: 0 | BK79: 3 | BL79: 0 | BM79: 0 | BN79: 3 | BO79: 18 | BP79: 0 | BQ79: 3 | BR79: 0 | BS79: 0 | BT79: 3 | BU79: 18 | BV79: 0 | BW79: 3 | BX79: 0 | BY79: 0 | BZ79: 3 | CA79: 18 | CB79: 0 | CC79: 4 | CD79: 1 | CE79: 0 | CF79: 5 | CG79: 24 | CT79: 0 | CU79: 29 | CV79: 12 | CW79: 0 | CX79: 53 | CY79: 174 | DB79: =IF(DA79="","",1-(DA79/Main!$G79)) | DD79: =IF(DC79="","",1-(DC79/Main!$G79)) | DF79: =IF(DE79="","",1-(DE79/Main!$G79)) | DH79: =IF(DG79="","",1-(DG79/Main!$G79))
A80: Accessories | B80: Handbags | C80: DK BAGS LTD | D80: 105977 | E80: SS22 565 | F80: Asstd | G80: 35 | H80: 0 | I80: 0 | J80: 2 | K80: 0 | L80: 2 | M80: 0 | N80: 0 | O80: 2 | P80: 0 | Q80: 0 | R80: 2 | S80: 12 | T80: 0 | U80: 3 | V80: 1 | W80: 0 | X80: 4 | Y80: 18 | Z80: 0 | AA80: 0 | AB80: 2 | AC80: 0 | AD80: 2 | AE80: 0 | AF80: 0 | AG80: 2 | AH80: 0 | AI80: 0 | AJ80: 2 | AK80: 12 | AL80: 0 | AM80: 2 | AN80: 0 | AO80: 0 | AP80: 2 | AQ80: 12 | AR80: 0 | AS80: 0 | AT80: 2 | AU80: 0 | AV80: 2 | AW80: 0 | BD80: 0 | BE80: 2 | BF80: 0 | BG80: 0 | BH80: 2 | BI80: 12 | BP80: 0 | BQ80: 2 | BR80: 0 | BS80: 0 | BT80: 2 | BU80: 12 | BV80: 0 | BW80: 1 | BX80: 0 | BY80: 0 | BZ80: 4 | CA80: 6 | CB80: 0 | CC80: 3 | CD80: 1 | CE80: 0 | CF80: 4 | CG80: 18 | CT80: 0 | CU80: 17 | CV80: 8 | CW80: 0 | CX80: 28 | CY80: 102 | DB80: =IF(DA80="","",1-(DA80/Main!$G80)) | DD80: =IF(DC80="","",1-(DC80/Main!$G80)) | DF80: =IF(DE80="","",1-(DE80/Main!$G80)) | DH80: =IF(DG80="","",1-(DG80/Main!$G80))
A81: Accessories | B81: Handbags | C81: EARTH SQUARED LTD CEN | D81: 103119 | E81: SS22 STRBKPBL VOYAGE ALICE BACKPACK | F81: BLUE | G81: 37.99 | T81: 0 | U81: 3 | V81: 0 | W81: 0 | X81: 3 | Y81: 47.49 | Z81: 2 | AA81: -2 | AB81: 2 | AC81: 1 | AD81: 0 | AE81: -31.66 | AF81: 0 | AG81: 2 | AH81: 0 | AI81: 0 | AJ81: 2 | AK81: 31.66 | AX81: 2 | AY81: 1 | AZ81: 2 | BA81: 0.66666667 | BB81: 12 | BC81: 15.83 | BD81: 0 | BE81: 2 | BF81: 2 | BG81: 0 | BH81: 4 | BI81: 31.66 | BJ81: 0 | BK81: 1 | BL81: 0 | BM81: 0 | BN81: 1 | BO81: 15.83 | BP81: 1 | BQ81: 1 | BR81: 0 | BS81: 0.5 | BT81: 4 | BU81: 15.83 | BV81: 2 | BW81: 0 | BX81: 0 | BY81: 1 | BZ81: 0 | CA81: 0 | CB81: 2 | CC81: 1 | CD81: 0 | CE81: 0.66666667 | CF81: 4 | CG81: 15.83 | CT81: 9 | CU81: 9 | CV81: 6 | CW81: 0.42592593 | CX81: 30 | CY81: 142.47 | DB81: =IF(DA81="","",1-(DA81/Main!$G81)) | DD81: =IF(DC81="","",1-(DC81/Main!$G81)) | DF81: =IF(DE81="","",1-(DE81/Main!$G81)) | DH81: =IF(DG81="","",1-(DG81/Main!$G81))
A82: Accessories | B82: Handbags | C82: EARTH SQUARED LTD CEN | D82: 103119 | E82: SS22 STRBKPBL VOYAGE ALICE BACKPACK | F82: Grey | G82: 37.99 | H82: 1 | I82: 1 | J82: 0 | K82: 0.5 | L82: 4 | M82: 15.83 | T82: 0 | U82: 2 | V82: 0 | W82: 0 | X82: 2 | Y82: 31.66 | Z82: 0 | AA82: -2 | AB82: 3 | AC82: 0 | AD82: 1 | AE82: -31.66 | AF82: 2 | AG82: 2 | AH82: 0 | AI82: 0.5 | AJ82: 8 | AK82: 31.66 | AX82: 1 | AY82: 2 | AZ82: 3 | BA82: 0.33333333 | BB82: 20 | BC82: 31.66 | BD82: 1 | BE82: 1 | BF82: 2 | BG82: 0.5 | BH82: 3 | BI82: 15.83 | BJ82: 0 | BK82: 2 | BL82: 0 | BM82: 0 | BN82: 2 | BO82: 31.66 | BP82: 1 | BQ82: 1 | BR82: 1 | BS82: 0.5 | BT82: 8 | BU82: 15.83 | BV82: 2 | BW82: 0 | BX82: 0 | BY82: 1 | BZ82: 0 | CA82: 0 | CB82: 1 | CC82: 1 | CD82: 0 | CE82: 0.5 | CF82: 4 | CG82: 15.83 | CT82: 9 | CU82: 10 | CV82: 9 | CW82: 0.38333333 | CX82: 52 | CY82: 158.3 | DB82: =IF(DA82="","",1-(DA82/Main!$G82)) | DD82: =IF(DC82="","",1-(DC82/Main!$G82)) | DF82: =IF(DE82="","",1-(DE82/Main!$G82)) | DH82: =IF(DG82="","",1-(DG82/Main!$G82))
A83: Accessories | B83: Handbags | C83: EARTH SQUARED LTD CEN | D83: 103120 | E83: SS22 STRMOONPK VOYAGE HALF MOON BAG | F83: Grey | G83: 33.99 | T83: 0 | U83: 2 | V83: 0 | W83: 0 | X83: 2 | Y83: 28.32 | Z83: 0 | AA83: -1 | AB83: 3 | AC83: 0 | AD83: 2 | AE83: -14.16 | AF83: 0 | AG83: 2 | AH83: 0 | AI83: 0 | AJ83: 2 | AK83: 28.32 | AR83: 0 | AS83: 1 | AT83: 0 | AU83: 0 | AV83: 1 | AW83: 14.16 | AX83: 1 | AY83: 1 | AZ83: 2 | BA83: 0.5 | BB83: 12 | BC83: 14.16 | BD83: 0 | BE83: 2 | BF83: 2 | BG83: 0 | BH83: 4 | BI83: 28.32 | BJ83: 1 | BK83: 1 | BL83: 0 | BM83: 0.5 | BN83: 4 | BO83: 14.16 | BP83: 1 | BQ83: 1 | BR83: 0 | BS83: 0.5 | BT83: 4 | BU83: 14.16 | BV83: 2 | BW83: 0 | BX83: 0 | BY83: 1 | BZ83: 0 | CA83: 0 | CT83: 5 | CU83: 9 | CV83: 7 | CW83: 0.27777778 | CX83: 31 | CY83: 127.44 | DB83: =IF(DA83="","",1-(DA83/Main!$G83)) | DD83: =IF(DC83="","",1-(DC83/Main!$G83)) | DF83: =IF(DE83="","",1-(DE83/Main!$G83)) | DH83: =IF(DG83="","",1-(DG83/Main!$G83))
A84: Accessories | B84: Handbags | C84: EARTH SQUARED LTD CEN | D84: 103120 | E84: SS22 STRMOONPK VOYAGE HALF MOON BAG | F84: Pink | G84: 33.99 | H84: 1 | I84: 1 | J84: 0 | K84: 0.5 | L84: 4 | M84: 14.16 | T84: 0 | U84: 2 | V84: 0 | W84: 0 | X84: 2 | Y84: 28.32 | Z84: 0 | AA84: 0 | AB84: 3 | AC84: 0 | AD84: 3 | AE84: 0 | AF84: 0 | AG84: 2 | AH84: 0 | AI84: 0 | AJ84: 2 | AK84: 28.32 | AR84: 0 | AS84: 2 | AT84: 0 | AU84: 0 | AV84: 2 | AW84: 28.32 | AX84: 0 | AY84: 2 | AZ84: 2 | BA84: 0 | BB84: 4 | BC84: 28.32 | BD84: 0 | BE84: 2 | BF84: 2 | BG84: 0 | BH84: 4 | BI84: 28.32 | BJ84: 0 | BK84: 2 | BL84: 0 | BM84: 0 | BN84: 2 | BO84: 28.32 | BP84: 0 | BQ84: 2 | BR84: 0 | BS84: 0 | BT84: 2 | BU84: 28.32 | BV84: 0 | BW84: 2 | BX84: 0 | BY84: 0 | BZ84: 2 | CA84: 28.32 | CT84: 1 | CU84: 17 | CV84: 7 | CW84: 0.05 | CX84: 27 | CY84: 240.72 | DB84: =IF(DA84="","",1-(DA84/Main!$G84)) | DD84: =IF(DC84="","",1-(DC84/Main!$G84)) | DF84: =IF(DE84="","",1-(DE84/Main!$G84)) | DH84: =IF(DG84="","",1-(DG84/Main!$G84))
A85: Accessories | B85: Handbags | C85: EARTH SQUARED LTD CEN | D85: 103121 | E85: SS22 SOMMBBL SPRING PATCHWORK MEGAN MESSENGER BAG | F85: BLUE | G85: 35.99 | H85: 2 | I85: 0 | J85: 0 | K85: 1 | L85: 0 | M85: 0 | AF85: 1 | AG85: 1 | AH85: 0 | AI85: 0.5 | AJ85: 4 | AK85: 15 | AR85: 1 | AS85: 1 | AT85: 0 | AU85: 0.5 | AV85: 4 | AW85: 15 | AX85: 1 | AY85: 1 | AZ85: 2 | BA85: 0.5 | BB85: 12 | BC85: 15 | BD85: 0 | BE85: 1 | BF85: 2 | BG85: 0 | BH85: 3 | BI85: 15 | BJ85: 0 | BK85: 1 | BL85: 0 | BM85: 0 | BN85: 1 | BO85: 15 | BP85: 0 | BQ85: 1 | BR85: 0 | BS85: 0 | BT85: 1 | BU85: 15 | BV85: 0 | BW85: 0 | BX85: 1 | BY85: 0 | BZ85: 1 | CA85: 0 | CT85: 5 | CU85: 6 | CV85: 5 | CW85: 0.3125 | CX85: 26 | CY85: 90 | DB85: =IF(DA85="","",1-(DA85/Main!$G85)) | DD85: =IF(DC85="","",1-(DC85/Main!$G85)) | DF85: =IF(DE85="","",1-(DE85/Main!$G85)) | DH85: =IF(DG85="","",1-(DG85/Main!$G85))
A86: Accessories | B86: Handbags | C86: EARTH SQUARED LTD CEN | D86: 103122 | E86: SS22 DOGMB DOG TWEED ANIMAL APPLIQUE AMELIA MESSENGER BAG | F86: Multi | G86: 31.99 | H86: 0 | I86: 1 | J86: 0 | K86: 0 | L86: 4 | M86: 13.33 | T86: 2 | U86: 0 | V86: 0 | W86: 1 | X86: 0 | Y86: 0 | Z86: 0 | AA86: 0 | AB86: 2 | AC86: 0 | AD86: 2 | AE86: 0 | AF86: 0 | AG86: 2 | AH86: 2 | AI86: 0 | AJ86: 4 | AK86: 26.66 | AR86: 2 | AS86: 0 | AT86: 2 | AU86: 1 | AV86: 8 | AW86: 0 | AX86: 1 | AY86: 1 | AZ86: 2 | BA86: 0.5 | BB86: 12 | BC86: 13.33 | BD86: 0 | BE86: 0 | BF86: 5 | BG86: 0 | BH86: 5 | BI86: 0 | BJ86: 0 | BK86: 0 | BL86: 3 | BM86: 0 | BN86: 3 | BO86: 0 | BP86: 2 | BQ86: 0 | BR86: 3 | BS86: 1 | BT86: 12 | BU86: 0 | CT86: 7 | CU86: 4 | CV86: 19 | CW86: 0.38888889 | CX86: 50 | CY86: 53.32 | DB86: =IF(DA86="","",1-(DA86/Main!$G86)) | DD86: =IF(DC86="","",1-(DC86/Main!$G86)) | DF86: =IF(DE86="","",1-(DE86/Main!$G86)) | DH86: =IF(DG86="","",1-(DG86/Main!$G86))
A87: Accessories | B87: Handbags | C87: EARTH SQUARED LTD CEN | D87: 103123 | E87: SS22 BEEMB BEE TWEED ANIMAL APPLIQUE AMELIA MESSENGER BAG | F87: Multi | G87: 31.99 | T87: 0 | U87: 2 | V87: 0 | W87: 0 | X87: 2 | Y87: 26.66 | Z87: 0 | AA87: 2 | AB87: 2 | AC87: 0 | AD87: 4 | AE87: 26.66 | AF87: 0 | AG87: 2 | AH87: 0 | AI87: 0 | AJ87: 2 | AK87: 26.66 | AR87: 3 | AS87: -1 | AT87: 2 | AU87: 1.5 | AV87: 2 | AW87: -13.33 | AX87: 0 | AY87: 0 | AZ87: 2 | BA87: 0 | BB87: 2 | BC87: 0 | BD87: 0 | BE87: 3 | BF87: 4 | BG87: 0 | BH87: 7 | BI87: 39.99 | BJ87: 0 | BK87: 3 | BL87: 0 | BM87: 0 | BN87: 3 | BO87: 39.99 | BP87: 1 | BQ87: 4 | BR87: 0 | BS87: 0.2 | BT87: 16 | BU87: 53.32 | BV87: 0 | BW87: 0 | BX87: 3 | BY87: 0 | BZ87: 3 | CA87: 0 | CB87: 1 | CC87: 1 | CD87: 0 | CE87: 0.5 | CF87: 4 | CG87: 13.33 | CT87: 5 | CU87: 16 | CV87: 13 | CW87: 0.22 | CX87: 45 | CY87: 213.28 | DB87: =IF(DA87="","",1-(DA87/Main!$G87)) | DD87: =IF(DC87="","",1-(DC87/Main!$G87)) | DF87: =IF(DE87="","",1-(DE87/Main!$G87)) | DH87: =IF(DG87="","",1-(DG87/Main!$G87))
A88: Accessories | B88: Handbags | C88: EARTH SQUARED LTD CEN | D88: 103124 | E88: SS22 LUFFNESS TWEED TOTE BAG | F88: Multi | G88: 37.99 | H88: 0 | I88: 2 | J88: 0 | K88: 0 | L88: 2 | M88: 31.66 | T88: 3 | U88: -1 | V88: 2 | W88: 1.5 | X88: 4 | Y88: -15.83 | Z88: 0 | AA88: 0 | AB88: 2 | AC88: 0 | AD88: 2 | AE88: 0 | AF88: 0 | AG88: 4 | AH88: 0 | AI88: 0 | AJ88: 4 | AK88: 63.32 | AR88: 3 | AS88: 1 | AT88: 0 | AU88: 0.75 | AV88: 4 | AW88: 15.83 | AX88: 0 | AY88: 2 | AZ88: 2 | BA88: 0 | BB88: 4 | BC88: 31.66 | BD88: 0 | BE88: 5 | BF88: 2 | BG88: 0 | BH88: 7 | BI88: 79.15 | BJ88: 3 | BK88: 2 | BL88: 0 | BM88: 0.6 | BN88: 8 | BO88: 31.66 | BP88: 0 | BQ88: 3 | BR88: 0 | BS88: 0 | BT88: 3 | BU88: 47.49 | BV88: 0 | BW88: 4 | BX88: 0 | BY88: 0 | BZ88: 4 | CA88: 63.32 | CB88: 0 | CC88: 2 | CD88: 0 | CE88: 0 | CF88: 2 | CG88: 31.66 | CT88: 9 | CU88: 24 | CV88: 8 | CW88: 0.25909091 | CX88: 44 | CY88: 379.92 | DB88: =IF(DA88="","",1-(DA88/Main!$G88)) | DD88: =IF(DC88="","",1-(DC88/Main!$G88)) | DF88: =IF(DE88="","",1-(DE88/Main!$G88)) | DH88: =IF(DG88="","",1-(DG88/Main!$G88))
A89: Accessories | B89: Handbags | C89: EARTH SQUARED LTD CEN | D89: 103248 | E89: SS22 SOMMBGY SPRING PATCHWORK MEGAN MESSENGER BAG | F89: Grey | G89: 35.99 | H89: 0 | I89: 0 | J89: 1 | K89: 0 | L89: 1 | M89: 0 | T89: 2 | U89: 1 | V89: 1 | W89: 0.66666667 | X89: 8 | Y89: 15 | Z89: 1 | AA89: 0 | AB89: 0 | AC89: 1 | AD89: 0 | AE89: 0 | AF89: 0 | AG89: 2 | AH89: 0 | AI89: 0 | AJ89: 2 | AK89: 30 | AR89: 0 | AS89: 4 | AT89: 0 | AU89: 0 | AV89: 4 | AW89: 60 | AX89: 1 | AY89: 0 | AZ89: 1 | BA89: 1 | BB89: 4 | BC89: 0 | BD89: 0 | BE89: 4 | BF89: 1 | BG89: 0 | BH89: 5 | BI89: 60 | BJ89: 0 | BK89: 1 | BL89: 0 | BM89: 0 | BN89: 1 | BO89: 15 | BP89: 1 | BQ89: 1 | BR89: 0 | BS89: 0.5 | BT89: 4 | BU89: 15 | BV89: 1 | BW89: 0 | BX89: 0 | BY89: 1 | BZ89: 0 | CA89: 0 | CT89: 6 | CU89: 13 | CV89: 4 | CW89: 0.41666667 | CX89: 29 | CY89: 195 | DB89: =IF(DA89="","",1-(DA89/Main!$G89)) | DD89: =IF(DC89="","",1-(DC89/Main!$G89)) | DF89: =IF(DE89="","",1-(DE89/Main!$G89)) | DH89: =IF(DG89="","",1-(DG89/Main!$G89))
A90: Accessories | B90: Handbags | C90: EARTH SQUARED LTD CEN | D90: 103249 | E90: SS22 HCOWMB COW TWEED ANIMAL APPLIQUE AMELIA MESSENGER BAG | F90: Multi | G90: 31.99 | T90: 0 | U90: 2 | V90: 0 | W90: 0 | X90: 2 | Y90: 26.66 | Z90: 0 | AA90: 0 | AB90: 2 | AC90: 0 | AD90: 2 | AE90: 0 | AR90: 0 | AS90: 1 | AT90: 2 | AU90: 0 | AV90: 3 | AW90: 13.33 | BD90: 0 | BE90: 0 | BF90: 3 | BG90: 0 | BH90: 3 | BI90: 0 | BJ90: 0 | BK90: 0 | BL90: 3 | BM90: 0 | BN90: 3 | BO90: 0 | BP90: 2 | BQ90: 0 | BR90: 3 | BS90: 1 | BT90: 12 | BU90: 0 | BV90: 0 | BW90: 0 | BX90: 3 | BY90: 0 | BZ90: 3 | CA90: 0 | CB90: 0 | CC90: 0 | CD90: 2 | CE90: 0 | CF90: 2 | CG90: 0 | CT90: 2 | CU90: 3 | CV90: 18 | CW90: 0.125 | CX90: 30 | CY90: 39.99 | DB90: =IF(DA90="","",1-(DA90/Main!$G90)) | DD90: =IF(DC90="","",1-(DC90/Main!$G90)) | DF90: =IF(DE90="","",1-(DE90/Main!$G90)) | DH90: =IF(DG90="","",1-(DG90/Main!$G90))
A91: Accessories | B91: Handbags | C91: EARTH SQUARED LTD CEN | D91: 103647 | E91: SS22 SOMTT SPRING PATCHWORK SLOUCH TOTE BAG | F91: BLUE | G91: 37.99 | H91: 0 | I91: 0 | J91: 2 | K91: 0 | L91: 2 | M91: 0 | T91: 0 | U91: 2 | V91: 0 | W91: 0 | X91: 2 | Y91: 31.66 | Z91: 2 | AA91: 1 | AB91: 0 | AC91: 0.66666667 | AD91: 4 | AE91: 15.83 | AF91: 2 | AG91: 2 | AH91: 0 | AI91: 0.33333333 | AJ91: 5 | AK91: 31.66 | AR91: 0 | AS91: 1 | AT91: 1 | AU91: 0 | AV91: 2 | AW91: 15.83 | AX91: 0 | AY91: 2 | AZ91: 2 | BA91: 0 | BB91: 4 | BC91: 31.66 | BD91: 0 | BE91: 2 | BF91: 0 | BG91: 0 | BH91: 2 | BI91: 31.66 | BJ91: 0 | BK91: 1 | BL91: 0 | BM91: 0 | BN91: 1 | BO91: 15.83 | BP91: 0 | BQ91: 1 | BR91: 0 | BS91: 0 | BT91: 1 | BU91: 15.83 | BV91: 0 | BW91: 0 | BX91: 1 | BY91: 0 | BZ91: 1 | CA91: 0 | CB91: 1 | CC91: 0 | CD91: 0 | CE91: 1 | CF91: 0 | CG91: 0 | CT91: 5 | CU91: 12 | CV91: 6 | CW91: 0.19444444 | CX91: 24 | CY91: 189.96 | DB91: =IF(DA91="","",1-(DA91/Main!$G91)) | DD91: =IF(DC91="","",1-(DC91/Main!$G91)) | DF91: =IF(DE91="","",1-(DE91/Main!$G91)) | DH91: =IF(DG91="","",1-(DG91/Main!$G91))
A92: Accessories | B92: Handbags | C92: EARTH SQUARED LTD CEN | D92: 103647 | E92: SS22 SOMTT SPRING PATCHWORK SLOUCH TOTE BAG | F92: Grey | G92: 37.99 | H92: 0 | I92: 0 | J92: 1 | K92: 0 | L92: 1 | M92: 0 | T92: 1 | U92: 0 | V92: 0 | W92: 1 | X92: 0 | Y92: 0 | Z92: 0 | AA92: 1 | AB92: 0 | AC92: 0 | AD92: 1 | AE92: 15.83 | AF92: 0 | AG92: 2 | AH92: 0 | AI92: 0 | AJ92: 2 | AK92: 31.66 | AR92: 0 | AS92: 0 | AT92: 1 | AU92: 0 | AV92: 1 | AW92: 0 | AX92: 0 | AY92: 1 | AZ92: 1 | BA92: 0 | BB92: 2 | BC92: 15.83 | BD92: 0 | BE92: 1 | BF92: 0 | BG92: 0 | BH92: 1 | BI92: 15.83 | BJ92: 0 | BK92: 1 | BL92: 0 | BM92: 0 | BN92: 1 | BO92: 15.83 | BV92: 0 | BW92: 0 | BX92: 1 | BY92: 0 | BZ92: 1 | CA92: 0 | CB92: 1 | CC92: 0 | CD92: 0 | CE92: 1 | CF92: 0 | CG92: 0 | CT92: 2 | CU92: 6 | CV92: 4 | CW92: 0.18181818 | CX92: 10 | CY92: 94.98 | DB92: =IF(DA92="","",1-(DA92/Main!$G92)) | DD92: =IF(DC92="","",1-(DC92/Main!$G92)) | DF92: =IF(DE92="","",1-(DE92/Main!$G92)) | DH92: =IF(DG92="","",1-(DG92/Main!$G92))
A93: Accessories | B93: Handbags | C93: EARTH SQUARED LTD CEN | D93: 103671 | E93: SS22 SEACLIFFE TWEED WEEKEND BAG | F93: Multi | G93: 54.99 | AF93: 0 | AG93: 4 | AH93: 0 | AI93: 0 | AJ93: 4 | AK93: 91.64 | AR93: 0 | AS93: 3 | AT93: 0 | AU93: 0 | AV93: 3 | AW93: 68.73 | AX93: 0 | AY93: 4 | AZ93: 4 | BA93: 0 | BB93: 8 | BC93: 91.64 | BJ93: 0 | BK93: 2 | BL93: 0 | BM93: 0 | BN93: 2 | BO93: 45.82 | BP93: 3 | BQ93: 0 | BR93: 0 | BS93: 1 | BT93: 0 | BU93: 0 | CT93: 3 | CU93: 13 | CV93: 4 | CW93: 0.22222222 | CX93: 17 | CY93: 297.83 | DB93: =IF(DA93="","",1-(DA93/Main!$G93)) | DD93: =IF(DC93="","",1-(DC93/Main!$G93)) | DF93: =IF(DE93="","",1-(DE93/Main!$G93)) | DH93: =IF(DG93="","",1-(DG93/Main!$G93))
A94: Accessories | B94: Handbags | C94: EARTH SQUARED LTD CEN | D94: 105997 | E94: SS22 BEESB FLOWER SLING BAG | F94: Multi | G94: 17.99 | T94: 0 | U94: 0 | V94: 2 | W94: 0 | X94: 2 | Y94: 0 | Z94: 0 | AA94: 0 | AB94: 2 | AC94: 0 | AD94: 2 | AE94: 0 | AF94: 0 | AG94: 0 | AH94: 2 | AI94: 0 | AJ94: 2 | AK94: 0 | AR94: 0 | AS94: 0 | AT94: 2 | AU94: 0 | AV94: 2 | AW94: 0 | BD94: 0 | BE94: 0 | BF94: 2 | BG94: 0 | BH94: 2 | BI94: 0 | BJ94: 0 | BK94: 0 | BL94: 2 | BM94: 0 | BN94: 2 | BO94: 0 | BP94: 0 | BQ94: 0 | BR94: 2 | BS94: 0 | BT94: 2 | BU94: 0 | BV94: 0 | BW94: 0 | BX94: 2 | BY94: 0 | BZ94: 2 | CA94: 0 | CT94: 0 | CU94: 0 | CV94: 16 | CW94: 0 | CX94: 16 | CY94: 0 | DB94: =IF(DA94="","",1-(DA94/Main!$G94)) | DD94: =IF(DC94="","",1-(DC94/Main!$G94)) | DF94: =IF(DE94="","",1-(DE94/Main!$G94)) | DH94: =IF(DG94="","",1-(DG94/Main!$G94))
A95: Accessories | B95: Handbags | C95: EARTH SQUARED LTD CEN | D95: 105999 | E95: SS22 DOGSB SLING BAG | F95: Multi | G95: 17.99 | T95: 0 | U95: 0 | V95: 2 | W95: 0 | X95: 2 | Y95: 0 | Z95: 0 | AA95: 2 | AB95: 0 | AC95: 0 | AD95: 2 | AE95: 15 | AF95: 0 | AG95: 2 | AH95: 0 | AI95: 0 | AJ95: 2 | AK95: 15 | AR95: 0 | AS95: 2 | AT95: 0 | AU95: 0 | AV95: 2 | AW95: 15 | AX95: 0 | AY95: 1 | AZ95: 0 | BA95: 0 | BB95: 4 | BC95: 7.5 | BD95: 0 | BE95: 2 | BF95: 0 | BG95: 0 | BH95: 2 | BI95: 15 | BJ95: 0 | BK95: 1 | BL95: 0 | BM95: 0 | BN95: 4 | BO95: 7.5 | BP95: 0 | BQ95: 1 | BR95: 0 | BS95: 0 | BT95: 4 | BU95: 7.5 | BV95: 0 | BW95: 1 | BX95: 0 | BY95: 0 | BZ95: 4 | CA95: 7.5 | CT95: 0 | CU95: 12 | CV95: 2 | CW95: 0 | CX95: 26 | CY95: 90 | DB95: =IF(DA95="","",1-(DA95/Main!$G95)) | DD95: =IF(DC95="","",1-(DC95/Main!$G95)) | DF95: =IF(DE95="","",1-(DE95/Main!$G95)) | DH95: =IF(DG95="","",1-(DG95/Main!$G95))
A96: Accessories | B96: Handbags | C96: EARTH SQUARED LTD CEN | D96: 106000 | E96: HCOWSB SLING BAG | F96: Multi | G96: 17.99 | T96: 0 | U96: 0 | V96: 2 | W96: 0 | X96: 2 | Y96: 0 | Z96: 0 | AA96: 2 | AB96: 0 | AC96: 0 | AD96: 2 | AE96: 15 | AF96: 0 | AG96: 2 | AH96: 0 | AI96: 0 | AJ96: 2 | AK96: 15 | AR96: 0 | AS96: 1 | AT96: 1 | AU96: 0 | AV96: 2 | AW96: 7.5 | AX96: 0 | AY96: 0 | AZ96: 2 | BA96: 0 | BB96: 2 | BC96: 0 | BD96: 0 | BE96: 0 | BF96: 2 | BG96: 0 | BH96: 2 | BI96: 0 | BJ96: 0 | BK96: 0 | BL96: 2 | BM96: 0 | BN96: 2 | BO96: 0 | BP96: 0 | BQ96: 0 | BR96: 2 | BS96: 0 | BT96: 2 | BU96: 0 | CT96: 0 | CU96: 5 | CV96: 11 | CW96: 0 | CX96: 16 | CY96: 37.5 | DB96: =IF(DA96="","",1-(DA96/Main!$G96)) | DD96: =IF(DC96="","",1-(DC96/Main!$G96)) | DF96: =IF(DE96="","",1-(DE96/Main!$G96)) | DH96: =IF(DG96="","",1-(DG96/Main!$G96))
A97: Accessories | B97: Handbags | C97: EARTH SQUARED LTD CEN | D97: 106001 | E97: SOM3ZIPBL SMALL PATCH BAG | F97: BLUE | G97: 15.99 | T97: 0 | U97: 0 | V97: 2 | W97: 0 | X97: 2 | Y97: 0 | Z97: 0 | AA97: 2 | AB97: 0 | AC97: 0 | AD97: 2 | AE97: 13.32 | AF97: 0 | AG97: 2 | AH97: 0 | AI97: 0 | AJ97: 2 | AK97: 13.32 | AR97: 0 | AS97: 2 | AT97: 0 | AU97: 0 | AV97: 2 | AW97: 13.32 | AX97: 0 | AY97: 2 | AZ97: 0 | BA97: 0 | BB97: 2 | BC97: 13.32 | BD97: 0 | BE97: 2 | BF97: 0 | BG97: 0 | BH97: 2 | BI97: 13.32 | BJ97: 0 | BK97: 2 | BL97: 0 | BM97: 0 | BN97: 2 | BO97: 13.32 | BP97: 0 | BQ97: 2 | BR97: 0 | BS97: 0 | BT97: 2 | BU97: 13.32 | BV97: 0 | BW97: 2 | BX97: 0 | BY97: 0 | BZ97: 2 | CA97: 13.32 | CT97: 0 | CU97: 16 | CV97: 2 | CW97: 0 | CX97: 18 | CY97: 106.56 | DB97: =IF(DA97="","",1-(DA97/Main!$G97)) | DD97: =IF(DC97="","",1-(DC97/Main!$G97)) | DF97: =IF(DE97="","",1-(DE97/Main!$G97)) | DH97: =IF(DG97="","",1-(DG97/Main!$G97))
A98: Accessories | B98: Handbags | C98: EARTH SQUARED LTD CEN | D98: 106002 | E98: SOM3ZIPGY SMALL PATCH BAG | F98: Grey | G98: 15.99 | T98: 0 | U98: 0 | V98: 2 | W98: 0 | X98: 2 | Y98: 0 | Z98: 0 | AA98: 2 | AB98: 0 | AC98: 0 | AD98: 2 | AE98: 13.32 | AF98: 0 | AG98: 2 | AH98: 0 | AI98: 0 | AJ98: 2 | AK98: 13.32 | AR98: 0 | AS98: 2 | AT98: 0 | AU98: 0 | AV98: 2 | AW98: 13.32 | AX98: 0 | AY98: 2 | AZ98: 0 | BA98: 0 | BB98: 2 | BC98: 13.32 | BD98: 0 | BE98: 2 | BF98: 0 | BG98: 0 | BH98: 2 | BI98: 13.32 | BJ98: 0 | BK98: 2 | BL98: 0 | BM98: 0 | BN98: 2 | BO98: 13.32 | BP98: 0 | BQ98: 2 | BR98: 0 | BS98: 0 | BT98: 2 | BU98: 13.32 | BV98: 0 | BW98: 1 | BX98: 0 | BY98: 0 | BZ98: 4 | CA98: 6.66 | CT98: 0 | CU98: 15 | CV98: 2 | CW98: 0 | CX98: 20 | CY98: 99.9 | DB98: =IF(DA98="","",1-(DA98/Main!$G98)) | DD98: =IF(DC98="","",1-(DC98/Main!$G98)) | DF98: =IF(DE98="","",1-(DE98/Main!$G98)) | DH98: =IF(DG98="","",1-(DG98/Main!$G98))
A99: Accessories | B99: Handbags | C99: ITSUMO FASHIONS LTD | D99: 103125 | E99: SS22 GR003N SMALL SQUARE LEATHER ZIP BAG | F99: Black | G99: 19 | H99: 5 | I99: -1 | J99: 4 | K99: 1.25 | L99: 12 | M99: -6.4 | N99: 0 | O99: 3 | P99: 0 | Q99: 0 | R99: 3 | S99: 19.2 | T99: 4 | U99: 0 | V99: 0 | W99: 1 | X99: 0 | Y99: 0 | Z99: 7 | AA99: -3 | AB99: 4 | AC99: 1.75 | AD99: 1 | AE99: -19.2 | AF99: 4 | AG99: 2 | AH99: 0 | AI99: 0.66666667 | AJ99: 4 | AK99: 12.8 | AL99: 5 | AM99: 3 | AN99: 0 | AO99: 0.625 | AP99: 12 | AQ99: 19.2 | AR99: 0 | AS99: 2 | AT99: 0 | AU99: 0 | AV99: 2 | AW99: 12.8 | AX99: 0 | AY99: 4 | AZ99: 0 | BA99: 0 | BB99: 4 | BC99: 25.6 | BD99: 4 | BE99: -4 | BF99: 8 | BG99: 1 | BH99: 16 | BI99: -25.6 | BJ99: 0 | BK99: 7 | BL99: 0 | BM99: 0 | BN99: 7 | BO99: 44.8 | BP99: 0 | BQ99: 4 | BR99: 0 | BS99: 0 | BT99: 4 | BU99: 25.6 | BV99: 6 | BW99: 2 | BX99: 4 | BY99: 0.75 | BZ99: 6 | CA99: 12.8 | CH99: 0 | CI99: -4 | CJ99: 0 | CK99: 0 | CL99: -4 | CM99: -25.6 | CT99: 35 | CU99: 15 | CV99: 20 | CW99: 0.54166667 | CX99: 67 | CY99: 96 | DB99: =IF(DA99="","",1-(DA99/Main!$G99)) | DD99: =IF(DC99="","",1-(DC99/Main!$G99)) | DF99: =IF(DE99="","",1-(DE99/Main!$G99)) | DH99: =IF(DG99="","",1-(DG99/Main!$G99))
A100: Accessories | B100: Handbags | C100: ITSUMO FASHIONS LTD | D100: 103125 | E100: SS22 GR003N SMALL SQUARE LEATHER ZIP BAG | F100: Cream | G100: 19 | H100: 3 | I100: -1 | J100: 2 | K100: 1.5 | L100: 4 | M100: -6.4 | N100: 2 | O100: 0 | P100: 0 | Q100: 1 | R100: 0 | S100: 0 | T100: 0 | U100: -1 | V100: 0 | W100: 0 | X100: -1 | Y100: -6.4 | Z100: 3 | AA100: -2 | AB100: 2 | AC100: 3 | AD100: 0 | AE100: -12.8 | AF100: 3 | AG100: 1 | AH100: 0 | AI100: 0.75 | AJ100: 4 | AK100: 6.4 | AL100: 3 | AM100: 1 | AN100: 0 | AO100: 0.75 | AP100: 2 | AQ100: 6.4 | AR100: 0 | AS100: 1 | AT100: 0 | AU100: 0 | AV100: 1 | AW100: 6.4 | AX100: 3 | AY100: 1 | AZ100: 0 | BA100: 0.75 | BB100: 4 | BC100: 6.4 | BD100: 0 | BE100: -1 | BF100: 4 | BG100: 0 | BH100: 3 | BI100: -6.4 | BJ100: 4 | BK100: 0 | BL100: 0 | BM100: 1 | BN100: 0 | BO100: 0 | BP100: 3 | BQ100: 1 | BR100: 0 | BS100: 0.75 | BT100: 4 | BU100: 6.4 | BV100: 4 | BW100: 0 | BX100: 2 | BY100: 1 | BZ100: 4 | CA100: 0 | CH100: 0 | CI100: -2 | CJ100: 0 | CK100: 0 | CL100: -2 | CM100: -12.8 | CT100: 28 | CU100: -2 | CV100: 10 | CW100: 0.80769231 | CX100: 23 | CY100: -12.8 | DB100: =IF(DA100="","",1-(DA100/Main!$G100)) | DD100: =IF(DC100="","",1-(DC100/Main!$G100)) | DF100: =IF(DE100="","",1-(DE100/Main!$G100)) | DH100: =IF(DG100="","",1-(DG100/Main!$G100))
...

Sheet Summary
C1: Branch Code | D1: Values
C2: 1 | G2: 2 | K2: 3 | O2: 4 | S2: 5 | W2: 6 | AA2: 8 | AE2: 9 | AI2: 11 | AM2: 12 | AQ2: 13 | AU2: 15 | AY2: 16 | BC2: 90 | BG2: 990 | BK2: Total Sales | BL2: Total Stock | BM2: Total Sell-Through | BN2: Total Weekly Cover
A3: SectionCode | B3: SectionName | C3: Sales | D3: Stock | E3: Sell-Through | F3: Weekly Cover | G3: Sales | H3: Stock | I3: Sell-Through | J3: Weekly Cover | K3: Sales | L3: Stock | M3: Sell-Through | N3: Weekly Cover | O3: Sales | P3: Stock | Q3: Sell-Through | R3: Weekly Cover | S3: Sales | T3: Stock | U3: Sell-Through | V3: Weekly Cover | W3: Sales | X3: Stock | Y3: Sell-Through | Z3: Weekly Cover | AA3: Sales | AB3: Stock | AC3: Sell-Through | AD3: Weekly Cover | AE3: Sales | AF3: Stock | AG3: Sell-Through | AH3: Weekly Cover | AI3: Sales | AJ3: Stock | AK3: Sell-Through | AL3: Weekly Cover | AM3: Sales | AN3: Stock | AO3: Sell-Through | AP3: Weekly Cover | AQ3: Sales | AR3: Stock | AS3: Sell-Through | AT3: Weekly Cover | AU3: Sales | AV3: Stock | AW3: Sell-Through | AX3: Weekly Cover | AY3: Sales | AZ3: Stock | BA3: Sell-Through | BB3: Weekly Cover | BC3: Sales | BD3: Stock | BE3: Sell-Through | BF3: Weekly Cover | BG3: Sales | BH3: Stock | BI3: Sell-Through | BJ3: Weekly Cover
A4: 2 | B4: Handbags | C4: 49 | D4: 217 | E4: 0.18421053 | F4: 55 | G4: 11 | H4: 226 | I4: 0.046413502 | J4: 76 | K4: 49 | L4: 249 | M4: 0.16442953 | N4: 54 | O4: 60 | P4: 177 | Q4: 0.25316456 | R4: 35 | S4: 47 | T4: 294 | U4: 0.13782991 | V4: 43 | W4: 45 | X4: 252 | Y4: 0.15151515 | Z4: 27 | AA4: 34 | AB4: 94 | AC4: 0.265625 | AD4: 29 | AE4: 58 | AF4: 301 | AG4: 0.16155989 | AH4: 25 | AI4: 57 | AJ4: 297 | AK4: 0.16101695 | AL4: 43 | AM4: 32 | AN4: 344 | AO4: 0.085106383 | AP4: 43 | AQ4: 53 | AR4: 252 | AS4: 0.17377049 | AT4: 29 | AU4: 43 | AV4: 262 | AW4: 0.14098361 | AX4: 31 | AY4: 36 | AZ4: 231 | BA4: 0.13483146 | BB4: 28 | BC4: 0 | BD4: -28 | BE4: 0 | BF4: -28 | BK4: 574 | BL4: 3168 | BM4: 0.1471755 | BN4: 490
A5: 5 | B5: Gifts | C5: 77 | D5: 380 | E5: 0.16849015 | F5: 56 | G5: 29 | H5: 219 | I5: 0.11693548 | J5: 41 | K5: 42 | L5: 245 | M5: 0.14634146 | N5: 75 | O5: 46 | P5: 329 | Q5: 0.12266667 | R5: 52 | S5: 31 | T5: 171 | U5: 0.15346535 | V5: 45 | W5: 58 | X5: 370 | Y5: 0.13551402 | Z5: 60 | AA5: 32 | AB5: 94 | AC5: 0.25396825 | AD5: 45 | AE5: 71 | AF5: 209 | AG5: 0.25357143 | AH5: 29 | AI5: 31 | AJ5: 312 | AK5: 0.090379009 | AL5: 83 | AM5: 32 | AN5: 250 | AO5: 0.11347518 | AP5: 73 | AQ5: 49 | AR5: 214 | AS5: 0.18631179 | AT5: 37 | AU5: 6 | AV5: 147 | AW5: 0.039215686 | AX5: 84 | AY5: 54 | AZ5: 80 | BA5: 0.40298507 | BB5: 13 | BG5: 0 | BH5: 43 | BI5: 0 | BJ5: 43 | BK5: 558 | BL5: 3063 | BM5: 0.1559514 | BN5: 736
A6: 9 | B6: Accessories | C6: 98 | D6: 40 | E6: 0.71014493 | F6: 23 | G6: 31 | H6: 53 | I6: 0.36904762 | J6: 23 | K6: 49 | L6: 100 | M6: 0.32885906 | N6: 29 | O6: 89 | P6: 38 | Q6: 0.7007874 | R6: 29 | S6: 61 | T6: -36 | U6: 2.44 | V6: -12 | W6: 52 | X6: 33 | Y6: 0.61176471 | Z6: 11 | AA6: 74 | AB6: 19 | AC6: 0.79569892 | AD6: 76 | AE6: 79 | AF6: 68 | AG6: 0.53741497 | AH6: 44 | AI6: 80 | AJ6: 72 | AK6: 0.52631579 | AL6: 47 | AM6: 34 | AN6: 102 | AO6: 0.25 | AP6: 76 | AQ6: 82 | AR6: 81 | AS6: 0.50306748 | AT6: 16 | AU6: 39 | AV6: 52 | AW6: 0.42857143 | AX6: 71 | AY6: 66 | AZ6: 31 | BA6: 0.68041237 | BB6: 26 | BK6: 834 | BL6: 653 | BM6: 0.68323728 | BN6: 459
A7: 24 | B7: Bras | S7: 0 | T7: 1 | U7: 0 | V7: 1 | BK7: 0 | BL7: 1 | BM7: 0 | BN7: 1
A8: 41 | B8: Rainwear | C8: 41 | D8: 229 | E8: 0.15185185 | F8: 33 | G8: 30 | H8: 137 | I8: 0.17964072 | J8: 23 | K8: 28 | L8: 156 | M8: 0.15217391 | N8: 38 | O8: 46 | P8: 180 | Q8: 0.20353982 | R8: 20 | S8: 49 | T8: 224 | U8: 0.17948718 | V8: 31 | W8: 47 | X8: 155 | Y8: 0.23267327 | Z8: 21 | AA8: 33 | AB8: 123 | AC8: 0.21153846 | AD8: 23 | AE8: 54 | AF8: 172 | AG8: 0.23893805 | AH8: 17 | AI8: 60 | AJ8: 174 | AK8: 0.25641026 | AL8: 21 | AM8: 54 | AN8: 142 | AO8: 0.2755102 | AP8: 30 | AQ8: 35 | AR8: 119 | AS8: 0.22727273 | AT8: 21 | AU8: 17 | AV8: 145 | AW8: 0.10493827 | AX8: 42 | AY8: 54 | AZ8: 96 | BA8: 0.36 | BB8: 18 | BG8: 0 | BH8: 22 | BI8: 0 | BJ8: 22 | BK8: 548 | BL8: 2074 | BM8: 0.19814105 | BN8: 360
A9: 80 | B9: Co-Ordinates | C9: 0 | D9: 0 | E9: 0 | F9: 4 | G9: 0 | H9: 0 | I9: 0 | J9: 12 | K9: 0 | L9: -1 | M9: 0 | N9: 11 | O9: 0 | P9: 0 | Q9: 0 | R9: 14 | S9: 0 | T9: 5 | U9: 0 | V9: 56 | W9: 0 | X9: 5 | Y9: 0 | Z9: 2 | AA9: 0 | AB9: 4 | AC9: 0 | AD9: 10 | AE9: 0 | AF9: 1 | AG9: 0 | AH9: 5 | AI9: 0 | AJ9: 0 | AK9: 0 | AL9: 4 | AM9: 0 | AN9: 4 | AO9: 0 | AP9: 20 | AQ9: 0 | AR9: 2 | AS9: 0 | AT9: 8 | AU9: 0 | AV9: 0 | AW9: 0 | AX9: 12 | AY9: 0 | AZ9: 4 | BA9: 0 | BB9: 20 | BG9: 0 | BH9: 0 | BI9: 0 | BJ9: 6 | BK9: 0 | BL9: 24 | BM9: 0 | BN9: 184
A10: 81 | B10: Blouses | C10: 0 | D10: 18 | E10: 0 | F10: 18 | G10: 0 | H10: 0 | I10: 0 | J10: 48 | K10: 0 | L10: -3 | M10: 0 | N10: 60 | O10: 0 | P10: 9 | Q10: 0 | R10: 21 | S10: 0 | T10: 24 | U10: 0 | V10: 51 | W10: 0 | X10: 42 | Y10: 0 | Z10: 16 | AA10: 0 | AB10: 20 | AC10: 0 | AD10: 73 | AE10: 0 | AF10: 19 | AG10: 0 | AH10: 36 | AI10: 0 | AJ10: 22 | AK10: 0 | AL10: 98 | AM10: 0 | AN10: 18 | AO10: 0 | AP10: 30 | AQ10: 0 | AR10: 13 | AS10: 0 | AT10: 20 | AU10: 0 | AV10: 0 | AW10: 0 | AX10: 48 | AY10: 0 | AZ10: 19 | BA10: 0 | BB10: 92 | BG10: 0 | BH10: 0 | BI10: 0 | BJ10: 24 | BK10: 0 | BL10: 201 | BM10: 0 | BN10: 635
A11: 83 | B11: Knitwear | C11: 46 | D11: 187 | E11: 0.19742489 | F11: 24 | G11: 47 | H11: 144 | I11: 0.2460733 | J11: 20 | K11: 66 | L11: 104 | M11: 0.38823529 | N11: 13 | O11: 38 | P11: 138 | Q11: 0.21590909 | R11: 30 | S11: 45 | T11: 174 | U11: 0.20547945 | V11: 27 | W11: 82 | X11: 124 | Y11: 0.39805825 | Z11: 10 | AA11: 53 | AB11: 85 | AC11: 0.38405797 | AD11: 19 | AE11: 80 | AF11: 149 | AG11: 0.34934498 | AH11: 16 | AI11: 75 | AJ11: 55 | AK11: 0.57692308 | AL11: 12 | AM11: 61 | AN11: 103 | AO11: 0.37195122 | AP11: 13 | AQ11: 47 | AR11: 158 | AS11: 0.22926829 | AT11: 21 | AU11: 35 | AV11: 98 | AW11: 0.26315789 | AX11: 33 | AY11: 53 | AZ11: 113 | BA11: 0.31927711 | BB11: 19 | BK11: 728 | BL11: 1632 | BM11: 0.31885852 | BN11: 257
A12: 84 | B12: Trousers | C12: 3 | D12: 26 | E12: 0.10344828 | F12: 74 | G12: 2 | H12: 17 | I12: 0.10526316 | J12: 258 | K12: 16 | L12: 54 | M12: 0.22857143 | N12: 40 | O12: 14 | P12: 29 | Q12: 0.3255814 | R12: 38 | S12: 1 | T12: 37 | U12: 0.026315789 | V12: 107 | W12: 5 | X12: 62 | Y12: 0.074626866 | Z12: 41 | AA12: 7 | AB12: 21 | AC12: 0.25 | AD12: 21 | AE12: 7 | AF12: 57 | AG12: 0.109375 | AH12: 176 | AI12: 3 | AJ12: 29 | AK12: 0.09375 | AL12: 58 | AM12: 7 | AN12: 69 | AO12: 0.092105263 | AP12: 64 | AQ12: 10 | AR12: 63 | AS12: 0.1369863 | AT12: 31 | AU12: 1 | AV12: 10 | AW12: 0.090909091 | AX12: 80 | AY12: 12 | AZ12: 75 | BA12: 0.13793103 | BB12: 43 | BG12: 0 | BH12: 0 | BI12: 0 | BJ12: 12 | BK12: 88 | BL12: 549 | BM12: 0.12677597 | BN12: 1043
A13: 85 | B13: Leisurewear | C13: 121 | D13: 404 | E13: 0.23047619 | F13: 21 | G13: 91 | H13: 229 | I13: 0.284375 | J13: 17 | K13: 168 | L13: 348 | M13: 0.3255814 | N13: 13 | O13: 180 | P13: 151 | Q13: 0.54380665 | R13: 9 | S13: 108 | T13: 372 | U13: 0.225 | V13: 19 | W13: 203 | X13: 354 | Y13: 0.36445242 | Z13: 10 | AA13: 125 | AB13: 205 | AC13: 0.37878788 | AD13: 14 | AE13: 155 | AF13: 353 | AG13: 0.30511811 | AH13: 15 | AI13: 94 | AJ13: 101 | AK13: 0.48205128 | AL13: 20 | AM13: 131 | AN13: 334 | AO13: 0.28172043 | AP13: 20 | AQ13: 105 | AR13: 376 | AS13: 0.21829522 | AT13: 22 | AU13: 78 | AV13: 127 | AW13: 0.3804878 | AX13: 18 | AY13: 119 | AZ13: 455 | BA13: 0.20731707 | BB13: 21 | BC13: 0 | BD13: 0 | BE13: 0 | BF13: 768 | BG13: 0 | BH13: 0 | BI13: 0 | BJ13: 3 | BK13: 1678 | BL13: 3809 | BM13: 0.2818313 | BN13: 990
A14: 103 | B14: Olsen | C14: 9 | D14: 65 | E14: 0.12162162 | F14: 36 | G14: 27 | H14: 119 | I14: 0.18493151 | J14: 30 | S14: 0 | T14: 119 | U14: 0 | V14: 119 | AE14: 5 | AF14: 120 | AG14: 0.04 | AH14: 121 | BK14: 41 | BL14: 423 | BM14: 0.086638282 | BN14: 306
A15: 123 | B15: Barbour Ladies | O15: 11 | P15: 73 | Q15: 0.13095238 | R15: 32 | AA15: 14 | AB15: 75 | AC15: 0.15730337 | AD15: 32 | AM15: 10 | AN15: 5 | AO15: 0.66666667 | AP15: 2 | AQ15: 31 | AR15: 95 | AS15: 0.24603175 | AT15: 14 | BG15: 4 | BH15: 78 | BI15: 0.048780488 | BJ15: 114 | BK15: 70 | BL15: 326 | BM15: 0.24994693 | BN15: 194
A16: 125 | B16: Joules | C16: 21 | D16: 86 | E16: 0.19626168 | F16: 45 | G16: 20 | H16: 78 | I16: 0.20408163 | J16: 22 | K16: 5 | L16: 54 | M16: 0.084745763 | N16: 61 | O16: 42 | P16: 95 | Q16: 0.30656934 | R16: 14 | S16: 12 | T16: 108 | U16: 0.1 | V16: 42 | AE16: 19 | AF16: 101 | AG16: 0.15833333 | AH16: 35 | AM16: 43 | AN16: 123 | AO16: 0.25903614 | AP16: 45 | AQ16: 27 | AR16: 114 | AS16: 0.19148936 | AT16: 27 | AU16: 11 | AV16: 52 | AW16: 0.17460317 | AX16: 82 | BG16: 4 | BH16: 106 | BI16: 0.036363636 | BJ16: 185 | BK16: 204 | BL16: 917 | BM16: 0.17114841 | BN16: 558
A17: 126 | B17: Masai | O17: 1 | P17: 3 | Q17: 0.25 | R17: 12 | AA17: 1 | AB17: 3 | AC17: 0.25 | AD17: 12 | AQ17: 0 | AR17: 5 | AS17: 0 | AT17: 5 | BK17: 2 | BL17: 11 | BM17: 0.16666667 | BN17: 29
A18: 128 | B18: Weird Fish Women | C18: 48 | D18: 78 | E18: 0.38095238 | F18: 26 | G18: 27 | H18: 27 | I18: 0.5 | J18: 20 | K18: 28 | L18: 44 | M18: 0.38888889 | N18: 19 | O18: 29 | P18: 116 | Q18: 0.2 | R18: 37 | S18: 13 | T18: 120 | U18: 0.097744361 | V18: 80 | W18: 21 | X18: 55 | Y18: 0.27631579 | Z18: 47 | AA18: 38 | AB18: 95 | AC18: 0.28571429 | AD18: 32 | AE18: 22 | AF18: 130 | AG18: 0.14473684 | AH18: 46 | AI18: 11 | AJ18: 28 | AK18: 0.28205128 | AL18: 161 | AM18: 62 | AN18: -5 | AO18: 1.0877193 | AP18: 6 | AQ18: 36 | AR18: 117 | AS18: 0.23529412 | AT18: 25 | AU18: 8 | AV18: 9 | AW18: 0.47058824 | AX18: 46 | AY18: 27 | AZ18: 129 | BA18: 0.17307692 | BB18: 36 | BG18: 5 | BH18: 144 | BI18: 0.033557047 | BJ18: 166 | BK18: 375 | BL18: 1087 | BM18: 0.32547425 | BN18: 747
A19: 130 | B19: Seasalt | C19: 96 | D19: 407 | E19: 0.19085487 | F19: 58 | K19: 29 | L19: 175 | M19: 0.14215686 | N19: 41 | O19: 61 | P19: 236 | Q19: 0.20538721 | R19: 59 | S19: 30 | T19: 223 | U19: 0.11857708 | V19: 75 | W19: 0 | X19: 1 | Y19: 0 | Z19: 1 | AA19: 41 | AB19: 170 | AC19: 0.1943128 | AD19: 63 | AE19: 63 | AF19: 193 | AG19: 0.24609375 | AH19: 37 | AM19: 78 | AN19: 92 | AO19: 0.45882353 | AP19: 35 | AQ19: 28 | AR19: 137 | AS19: 0.16969697 | AT19: 46 | AU19: 3 | AV19: 131 | AW19: 0.02238806 | AX19: 474 | BC19: 0 | BD19: -1 | BE19: 0 | BF19: -1 | BG19: 1 | BH19: 275 | BI19: 0.0036231884 | BJ19: 1792 | BK19: 430 | BL19: 2039 | BM19: 0.14599286 | BN19: 2680
A20: 131 | B20: Betty Barclay | C20: 8 | D20: 113 | E20: 0.066115702 | F20: 64 | G20: 21 | H20: 195 | I20: 0.097222222 | J20: 39 | O20: 8 | P20: 144 | Q20: 0.052631579 | R20: 64 | S20: 3 | T20: 213 | U20: 0.013888889 | V20: 284 | AA20: 19 | AB20: 110 | AC20: 0.14728682 | AD20: 24 | AE20: 23 | AF20: 199 | AG20: 0.1036036 | AH20: 49 | AM20: 5 | AN20: 27 | AO20: 0.15625 | AP20: 27 | AQ20: 14 | AR20: 101 | AS20: 0.12173913 | AT20: 29 | BG20: 0 | BH20: 208 | BI20: 0 | BJ20: 208 | BK20: 101 | BL20: 1310 | BM20: 0.084304216 | BN20: 788
A21: 132 | B21: White Stuff | C21: 51 | D21: 214 | E21: 0.19245283 | F21: 31 | K21: 9 | L21: 55 | M21: 0.140625 | N21: 59 | O21: 34 | P21: 101 | Q21: 0.25185185 | R21: 34 | S21: 0 | T21: 160 | U21: 0 | V21: 160 | AE21: 35 | AF21: 153 | AG21: 0.18617021 | AH21: 28 | AM21: 30 | AN21: 28 | AO21: 0.51724138 | AP21: 24 | AQ21: 21 | AR21: 70 | AS21: 0.23076923 | AT21: 44 | BC21: 0 | BD21: -1 | BE21: 0 | BF21: -1 | BG21: 7 | BH21: 112 | BI21: 0.058823529 | BJ21: 112 | BK21: 187 | BL21: 892 | BM21: 0.175326 | BN21: 491
A22: 136 | B22: Soya Concept | C22: 0 | D22: 6 | E22: 0 | F22: 6 | O22: 0 | P22: 2 | Q22: 0 | R22: 2 | S22: 0 | T22: 6 | U22: 0 | V22: 6 | W22: 0 | X22: 6 | Y22: 0 | Z22: 6 | AE22: 0 | AF22: 5 | AG22: 0 | AH22: 5 | AM22: 0 | AN22: 3 | AO22: 0 | AP22: 3 | BK22: 0 | BL22: 28 | BM22: 0 | BN22: 28
A23: 137 | B23: Joe Browns | G23: 8 | H23: 35 | I23: 0.18604651 | J23: 29 | O23: 18 | P23: 35 | Q23: 0.33962264 | R23: 13 | S23: 0 | T23: 36 | U23: 0 | V23: 36 | W23: 3 | X23: 20 | Y23: 0.13043478 | Z23: 57 | AE23: 4 | AF23: 32 | AG23: 0.11111111 | AH23: 49 | AM23: 0 | AN23: -10 | AO23: 0 | AP23: -10 | AY23: 7 | AZ23: 31 | BA23: 0.18421053 | BB23: 50 | BC23: 0 | BD23: -1 | BE23: 0 | BF23: -1 | BG23: 3 | BH23: 44 | BI23: 0.063829787 | BJ23: 122 | BK23: 43 | BL23: 222 | BM23: 0.11280615 | BN23: 345
A24: 139 | B24: Vero Moda | C24: 42 | D24: 79 | E24: 0.34710744 | F24: 18 | O24: 21 | P24: 94 | Q24: 0.1826087 | R24: 50 | S24: 13 | T24: 88 | U24: 0.12871287 | V24: 123 | W24: 18 | X24: 40 | Y24: 0.31034483 | Z24: 26 | AA24: 0 | AB24: 0 | AC24: 0 | AD24: 39 | AE24: 42 | AF24: 101 | AG24: 0.29370629 | AH24: 40 | AM24: 25 | AN24: 150 | AO24: 0.14285714 | AP24: 109 | AQ24: 9 | AR24: 20 | AS24: 0.31034483 | AT24: 30 | BG24: 0 | BH24: 69 | BI24: 0 | BJ24: 69 | BK24: 170 | BL24: 641 | BM24: 0.19063134 | BN24: 504
A25: 141 | B25: Superdry Ladies | C25: 0 | D25: 57 | E25: 0 | F25: 57 | G25: 10 | H25: 198 | I25: 0.048076923 | J25: 81 | K25: 8 | L25: 151 | M25: 0.050314465 | N25: 85 | O25: 11 | P25: 185 | Q25: 0.056122449 | R25: 61 | S25: 0 | T25: 119 | U25: 0 | V25: 119 | AE25: 13 | AF25: 121 | AG25: 0.097014925 | AH25: 23 | AM25: 31 | AN25: 159 | AO25: 0.16315789 | AP25: 68 | BG25: 0 | BH25: 223 | BI25: 0 | BJ25: 223 | BK25: 73 | BL25: 1213 | BM25: 0.051835832 | BN25: 717
A26: 143 | B26: Mistral | AA26: 5 | AB26: 64 | AC26: 0.072463768 | AD26: 128 | BK26: 5 | BL26: 64 | BM26: 0.072463768 | BN26: 128
A27: 158 | B27: Skechers | C27: 6 | D27: 35 | E27: 0.14634146 | F27: 29 | G27: 10 | H27: 42 | I27: 0.19230769 | J27: 21 | K27: 7 | L27: 34 | M27: 0.17073171 | N27: 21 | O27: 6 | P27: 45 | Q27: 0.11764706 | R27: 25 | S27: 1 | T27: 44 | U27: 0.022222222 | V27: 380 | W27: 11 | X27: 55 | Y27: 0.16666667 | Z27: 20 | AA27: 9 | AB27: 63 | AC27: 0.125 | AD27: 37 | AE27: 21 | AF27: 45 | AG27: 0.31818182 | AH27: 11 | AI27: 0 | AJ27: 24 | AK27: 0 | AL27: 24 | AM27: 16 | AN27: 46 | AO27: 0.25806452 | AP27: 22 | AQ27: 4 | AR27: 38 | AS27: 0.095238095 | AT27: 28 | AU27: 5 | AV27: 33 | AW27: 0.13157895 | AX27: 26 | AY27: 7 | AZ27: 40 | BA27: 0.14893617 | BB27: 32 | BG27: 0 | BH27: 18 | BI27: 0 | BJ27: 18 | BK27: 103 | BL27: 562 | BM27: 0.13520831 | BN27: 694
A28: 159 | B28: Superga Own Bought | C28: 4 | D28: 9 | E28: 0.30769231 | F28: 34 | O28: 0 | P28: 6 | Q28: 0 | R28: 21 | S28: 0 | T28: 13 | U28: 0 | V28: 13 | AE28: 0 | AF28: 13 | AG28: 0 | AH28: 21 | AM28: 3 | AN28: 9 | AO28: 0.25 | AP28: 40 | AQ28: 2 | AR28: 9 | AS28: 0.18181818 | AT28: 48 | BK28: 9 | BL28: 59 | BM28: 0.12325175 | BN28: 177
A29: 164 | B29: Hotter | C29: 3 | D29: 38 | E29: 0.073170732 | F29: 80 | G29: 5 | H29: 38 | I29: 0.11627907 | J29: 78 | K29: 5 | L29: 33 | M29: 0.13157895 | N29: 74 | O29: 6 | P29: 24 | Q29: 0.2 | R29: 34 | S29: 7 | T29: 23 | U29: 0.23333333 | V29: 37 | W29: 6 | X29: 34 | Y29: 0.15 | Z29: 47 | AE29: 2 | AF29: 34 | AG29: 0.055555556 | AH29: 124 | AI29: 6 | AJ29: 52 | AK29: 0.10344828 | AL29: 46 | AM29: 9 | AN29: 63 | AO29: 0.125 | AP29: 50 | AQ29: 1 | AR29: 30 | AS29: 0.032258065 | AT29: 120 | AU29: 6 | AV29: 34 | AW29: 0.15 | AX29: 45 | AY29: 2 | AZ29: 19 | BA29: 0.095238095 | BB29: 86 | BK29: 58 | BL29: 422 | BM29: 0.12215517 | BN29: 821
A30: 410 | B30: Cookware | K30: 5 | L30: -2 | M30: 1.6666667 | N30: 24 | AA30: 2 | AB30: 21 | AC30: 0.086956522 | AD30: 94 | AQ30: 0 | AR30: 59 | AS30: 0 | AT30: 111 | BK30: 7 | BL30: 78 | BM30: 0.58454106 | BN30: 229
A31: 411 | B31: Kitchen Accessories | K31: 18 | L31: 117 | M31: 0.13333333 | N31: 80 | AA31: 16 | AB31: 116 | AC31: 0.12121212 | AD31: 142 | AQ31: 119 | AR31: 201 | AS31: 0.371875 | AT31: 26 | BK31: 153 | BL31: 434 | BM31: 0.20880682 | BN31: 248
A32: 412 | B32: Electrical | K32: 39 | L32: 215 | M32: 0.15354331 | N32: 43 | AA32: 35 | AB32: 201 | AC32: 0.14830508 | AD32: 63 | AQ32: 92 | AR32: 235 | AS32: 0.28134557 | AT32: 29 | BK32: 166 | BL32: 651 | BM32: 0.19439799 | BN32: 135
A33: 413 | B33: Tableware | K33: 2 | L33: -10 | M33: 1 | N33: 44 | AA33: 6 | AB33: 30 | AC33: 0.16666667 | AD33: 42 | AQ33: 4 | AR33: 40 | AS33: 0.090909091 | AT33: 72 | BK33: 12 | BL33: 60 | BM33: 0.41919192 | BN33: 158
A34: 415 | B34: Cutlery | K34: 0 | L34: 6 | M34: 0 | N34: 6 | AA34: 0 | AB34: 6 | AC34: 0 | AD34: 6 | AQ34: 1 | AR34: 7 | AS34: 0.125 | AT34: 28 | BK34: 1 | BL34: 19 | BM34: 0.041666667 | BN34: 40
A35: 417 | B35: OB homewares | K35: 0 | L35: 7 | M35: 0 | N35: 7 | AA35: 4 | AB35: 44 | AC35: 0.083333333 | AD35: 88 | AQ35: 7 | AR35: 14 | AS35: 0.33333333 | AT35: 8 | BK35: 11 | BL35: 65 | BM35: 0.13888889 | BN35: 103
A36: 502 | B36: Mens Casual Jackets (AIS) | C36: 0 | D36: 6 | E36: 0 | F36: 6 | K36: 4 | L36: 74 | M36: 0.051282051 | N36: 79 | O36: 2 | P36: 60 | Q36: 0.032258065 | R36: 92 | S36: 0 | T36: 29 | U36: 0 | V36: 130 | W36: 0 | X36: 18 | Y36: 0 | Z36: 40 | AA36: 0 | AB36: 16 | AC36: 0 | AD36: 32 | AE36: 1 | AF36: 28 | AG36: 0.034482759 | AH36: 69 | AM36: 5 | AN36: 53 | AO36: 0.086206897 | AP36: 104 | AQ36: 24 | AR36: 141 | AS36: 0.14545455 | AT36: 40 | BK36: 36 | BL36: 425 | BM36: 0.038853813 | BN36: 592
A37: 503 | B37: Mens Shirts (AIS) | K37: 5 | L37: 10 | M37: 0.33333333 | N37: 10 | O37: 4 | P37: 23 | Q37: 0.14814815 | R37: 30 | S37: 11 | T37: 22 | U37: 0.33333333 | V37: 12 | W37: 3 | X37: 37 | Y37: 0.075 | Z37: 49 | AA37: 0 | AB37: 1 | AC37: 0 | AD37: 1 | AE37: 6 | AF37: 26 | AG37: 0.1875 | AH37: 34 | AM37: 1 | AN37: 63 | AO37: 0.015625 | AP37: 252 | AQ37: 5 | AR37: 32 | AS37: 0.13513514 | AT37: 32 | BK37: 35 | BL37: 214 | BM37: 0.15350937 | BN37: 420
A38: 504 | B38: Mens Knitwear (AIS) | K38: 0 | L38: -3 | M38: 0 | N38: -12 | O38: 3 | P38: 14 | Q38: 0.17647059 | R38: 18 | S38: 8 | T38: 19 | U38: 0.2962963 | V38: 25 | W38: 8 | X38: 18 | Y38: 0.30769231 | Z38: 18 | AA38: 10 | AB38: 4 | AC38: 0.71428571 | AD38: 4 | AE38: 6 | AF38: 14 | AG38: 0.3 | AH38: 28 | AM38: 10 | AN38: 8 | AO38: 0.55555556 | AP38: 5 | AQ38: 7 | AR38: 18 | AS38: 0.28 | AT38: 14 | BK38: 52 | BL38: 92 | BM38: 0.32878756 | BN38: 100
A39: 521 | B39: Weird Fish Men | K39: 10 | L39: 27 | M39: 0.27027027 | N39: 15 | O39: 20 | P39: 71 | Q39: 0.21978022 | R39: 45 | S39: 28 | T39: 162 | U39: 0.14736842 | V39: 30 | W39: 14 | X39: 18 | Y39: 0.4375 | Z39: 10 | AA39: 19 | AB39: 102 | AC39: 0.15702479 | AD39: 32 | AE39: 28 | AF39: 101 | AG39: 0.21705426 | AH39: 16 | AM39: 35 | AN39: 0 | AO39: 1 | AP39: 0 | AQ39: 95 | AR39: 123 | AS39: 0.43577982 | AT39: 8 | BG39: 0 | BH39: 228 | BI39: 0 | BJ39: 289 | BK39: 249 | BL39: 832 | BM39: 0.32053086 | BN39: 445
A40: 523 | B40: Barbour Gents | O40: 30 | P40: 171 | Q40: 0.14925373 | R40: 39 | AA40: 7 | AB40: 90 | AC40: 0.072164948 | AD40: 58 | AQ40: 54 | AR40: 246 | AS40: 0.18 | AT40: 22 | BK40: 91 | BL40: 507 | BM40: 0.13380623 | BN40: 119
A41: 524 | B41: Superdry Gents | C41: 0 | D41: 27 | E41: 0 | F41: 27 | K41: 12 | L41: 221 | M41: 0.051502146 | N41: 68 | O41: 48 | P41: 165 | Q41: 0.22535211 | R41: 34 | S41: 8 | T41: 194 | U41: 0.03960396 | V41: 155 | AA41: 0 | AB41: 26 | AC41: 0 | AD41: 26 | AE41: 64 | AF41: 240 | AG41: 0.21052632 | AH41: 24 | AM41: 41 | AN41: 148 | AO41: 0.21693122 | AP41: 29 | BG41: 1 | BH41: 199 | BI41: 0.005 | BJ41: 1492 | BK41: 174 | BL41: 1220 | BM41: 0.093614469 | BN41: 1855
A42: 525 | B42: Haworth | K42: 0 | L42: -1 | M42: 0 | N42: -1 | O42: 9 | P42: 30 | Q42: 0.23076923 | R42: 17 | S42: 9 | T42: 30 | U42: 0.23076923 | V42: 20 | W42: 2 | X42: 10 | Y42: 0.16666667 | Z42: 40 | AA42: 3 | AB42: 6 | AC42: 0.33333333 | AD42: 12 | AE42: 16 | AF42: 24 | AG42: 0.4 | AH42: 8 | AM42: 24 | AN42: 19 | AO42: 0.55813953 | AP42: 5 | AQ42: 10 | AR42: 13 | AS42: 0.43478261 | AT42: 7 | BK42: 73 | BL42: 131 | BM42: 0.29430758 | BN42: 108
A43: 526 | B43: Jack & Jones | K43: 3 | L43: 52 | M43: 0.054545455 | N43: 86 | O43: 18 | P43: 125 | Q43: 0.12587413 | R43: 27 | S43: 11 | T43: 49 | U43: 0.18333333 | V43: 19 | AE43: 43 | AF43: 51 | AG43: 0.45744681 | AH43: 53 | AM43: 86 | AN43: 128 | AO43: 0.40186916 | AP43: 35 | BG43: 0 | BH43: 57 | BI43: 0 | BJ43: 81 | BK43: 161 | BL43: 462 | BM43: 0.20384481 | BN43: 301
A44: 527 | B44: Meyer Menswear | O44: 2 | P44: 8 | Q44: 0.2 | R44: 16 | AQ44: 0 | AR44: -1 | AS44: 0 | AT44: -1 | BK44: 2 | BL44: 7 | BM44: 0.1 | BN44: 15
A45: 530 | B45: Craghopper Gents | K45: 22 | L45: 134 | M45: 0.14102564 | N45: 38 | S45: 0 | T45: 63 | U45: 0 | V45: 63 | W45: 27 | X45: 59 | Y45: 0.31395349 | Z45: 11 | AE45: 16 | AF45: 68 | AG45: 0.19047619 | AH45: 19 | AQ45: 47 | AR45: 147 | AS45: 0.24226804 | AT45: 18 | BK45: 112 | BL45: 471 | BM45: 0.17754467 | BN45: 149
A46: 800 | B46: Joules Kids | AQ46: 14 | AR46: 52 | AS46: 0.21212121 | AT46: 23 | BK46: 14 | BL46: 52 | BM46: 0.21212121 | BN46: 23
A47: 801 | B47: Barbour Kids | AQ47: 0 | AR47: 0 | AS47: 0 | AT47: 40 | BK47: 0 | BL47: 0 | BM47: 0 | BN47: 40

Sheet Developer
A1: path
A2: {=LEFT(CELL("filename",$A$1),FIND("[",CELL("filename",$A$1),1)-1) & "reports\"} -> P:\Silvia\Markdown\reports\
